Workbook

Sheet Hypothèses
A1: Paramètre | B1: Valeur
A2: Capital initial (€) | B2: 2100
A3: Frais fixes infra départ (€/mois) | B3: 500
A4: Hausse frais fixes / trimestre | B4: 0.15
A5: Frais variables (% CA HT) | B5: 0.01
A6: TVA (%) | B6: 0.2
A7: Churn — début (mois) | B7: 9
A8: Churn initial (%/mois) | B8: 0.05
A9: Décroissance churn (%/mois) | B9: 0.1
A10: Rattrapage rampe (%/mois) | B10: 0.4
A11: Prix Atelier TTC (€/mois) | B11: 89
A12: Prix Horizon TTC (€/mois) | B12: 149
A13: Prix L'Envergure TTC (€/mois) | B13: 499
... A16: Jours / mois / développeur | B16: 10
A17: Coût mensuel / développeur (€ HT) | B17: =B15*B16 -> 4500
A19: Facturation par année
A20: A1 | B20: 0.6 | C20: 0.05 | D20: 20
A21: A2 | B21: 0.5 | C21: 0.1 | D21: 25
A22: A3 | B22: 0.4 | C22: 0.12 | D22: 30
A24: Effectifs cibles fin d'année (base, avant facteur scénario)
A25: Plan | B25: Fin A1 | C25: Fin A2 | D25: Fin A3
A26: Atelier | B26: 5 | C26: 10 | D26: 20
A27: Horizon | B27: 10 | C27: 35 | D27: 70
A28: L'Envergure | B28: 0 | C28: 1 | D28: 3
A29: Rayonnement | B29: 0 | C29: 1 | D29: 2
A30: Zénith (contrats) | B30: 0 | C30: 1 | D30: 3
A32: Zénith — montants TTC (base)
A33: Mois 18 | B33: 15000
A34: Mois 30/34 | B34: 17000
A36: Note | B36: Modifier les valeurs ci-dessus : les 3 onglets scénario se recalculent automatiquement.

Sheet Prudent (-30%)
A1: Facteur clients (scénario) | B1: 0.7
A2: Zénith fin A2 (cible) | B2: =ROUND(Hypothèses!$C$30*$B$1,0) -> 1 | C2: Zénith fin A3 (cible) | D2: =ROUND(Hypothèses!$D$30*$B$1,0) -> 2
A3: Mois | B3: Année | C3: Atelier | D3: Horizon | E3: Envergure | F3: Rayonnement | G3: Cible Atelier | H3: Cible Horizon | I3: Cible Enverg. | J3: Cible Rayonn. | K3: Taux churn | L3: Clients payants | M3: MRR abo TTC | N3: Options TTC | O3: Zénith TTC | P3: CA TTC | Q3: CA HT | R3: Frais fixes infra | S3: Nb développeurs | T3: Sous-traitance dev (HT) | U3: Frais variables 1% | V3: EBITDA | W3: Trésorerie
A4: 1 | B4: =INT((A4-1)/12)+1 -> 1 | C4: =ROUND(IF(MOD($A4,12)=0,G4,(IF(4=4,0,C3))*(1-$K4)+IF((IF(4=4,0,C3))*(1-$K4)<G4,(G4-(IF(4=4,0,C3))*(1-$K4))*Hypothèses!$B$10,0)),1) -> 0.1 | D4: =ROUND(IF(MOD($A4,12)=0,H4,(IF(4=4,0,D3))*(1-$K4)+IF((IF(4=4,0,D3))*(1-$K4)<H4,(H4-(IF(4=4,0,D3))*(1-$K4))*Hypothèses!$B$10,0)),1) -> 0.2 | E4: =ROUND(IF(MOD($A4,12)=0,I4,(IF(4=4,0,E3))*(1-$K4)+IF((IF(4=4,0,E3))*(1-$K4)<I4,(I4-(IF(4=4,0,E3))*(1-$K4))*Hypothèses!$B$10,0)),1) -> 0 | F4: =ROUND(IF(MOD($A4,12)=0,J4,(IF(4=4,0,F3))*(1-$K4)+IF((IF(4=4,0,F3))*(1-$K4)<J4,(J4-(IF(4=4,0,F3))*(1-$K4))*Hypothèses!$B$10,0)),1) -> 0 | G4: =(IF(B4=1,0,IF(B4=2,Hypothèses!$B$26,IF(B4=3,Hypothèses!$C$26,Hypothèses!$D$26)))+(IF(B4=1,Hypothèses!$B$26,IF(B4=2,Hypothèses!$C$26,IF(B4=3,Hypothèses!$D$26,Hypothèses!$D$26)))-(IF(B4=1,0,IF(B4=2,Hypothèses!$B$26,IF(B4=3,Hypothèses!$C$26,Hypothèses!$D$26)))))*((A4)-INT((A4-1)/12)*12)/12)*$B$1 -> 0.29166667 | H4: =(IF(B4=1,0,IF(B4=2,Hypothèses!$B$27,IF(B4=3,Hypothèses!$C$27,Hypothèses!$D$27)))+(IF(B4=1,Hypothèses!$B$27,IF(B4=2,Hypothèses!$C$27,IF(B4=3,Hypothèses!$D$27,Hypothèses!$D$27)))-(IF(B4=1,0,IF(B4=2,Hypothèses!$B$27,IF(B4=3,Hypothèses!$C$27,Hypothèses!$D$27)))))*((A4)-INT((A4-1)/12)*12)/12)*$B$1 -> 0.58333333 | I4: =(IF(B4=1,0,IF(B4=2,Hypothèses!$B$28,IF(B4=3,Hypothèses!$C$28,Hypothèses!$D$28)))+(IF(B4=1,Hypothèses!$B$28,IF(B4=2,Hypothèses!$C$28,IF(B4=3,Hypothèses!$D$28,Hypothèses!$D$28)))-(IF(B4=1,0,IF(B4=2,Hypothèses!$B$28,IF(B4=3,Hypothèses!$C$28,Hypothèses!$D$28)))))*((A4)-INT((A4-1)/12)*12)/12)*$B$1 -> 0 | J4: =(IF(B4=1,0,IF(B4=2,Hypothèses!$B$29,IF(B4=3,Hypothèses!$C$29,Hypothèses!$D$29)))+(IF(B4=1,Hypothèses!$B$29,IF(B4=2,Hypothèses!$C$29,IF(B4=3,Hypothèses!$D$29,Hypothèses!$D$29)))-(IF(B4=1,0,IF(B4=2,Hypothèses!$B$29,IF(B4=3,Hypothèses!$C$29,Hypothèses!$D$29)))))*((A4)-INT((A4-1)/12)*12)/12)*$B$1 -> 0 | K4: =IF(A4<Hypothèses!$B$7,0,Hypothèses!$B$8*(1-Hypothèses!$B$9)^(A4-Hypothèses!$B$7)) -> 0 | L4: =C4+D4+E4+F4 -> 0.3 | M4: =(C4*Hypothèses!$B$11+D4*Hypothèses!$B$12+E4*Hypothèses!$B$13+F4*Hypothèses!$B$14)*(IF(B4=1,Hypothèses!$B$20,IF(B4=2,Hypothèses!$B$21,Hypothèses!$B$22))+(1-(IF(B4=1,Hypothèses!$B$20,IF(B4=2,Hypothèses!$B$21,Hypothèses!$B$22))))*11/12) -> 37.41 | N4: =L4*IF(B4=1,Hypothèses!$C$20,IF(B4=2,Hypothèses!$C$21,Hypothèses!$C$22))*IF(B4=1,Hypothèses!$D$20,IF(B4=2,Hypothèses!$D$21,Hypothèses!$D$22)) -> 0.3 | O4: =IF(A4=18,IF($B$2>=1,Hypothèses!$B$33,0),IF(AND(OR(A4=30,A4=34),$D$2>=1),Hypothèses!$B$34*MIN(1,$D$2/3),0)) -> 0 | P4: =M4+N4+O4 -> 37.71 | Q4: =P4/(1+Hypothèses!$B$6) -> 31.425 | R4: =Hypothèses!$B$3*(1+Hypothèses!$B$4)^INT((A4-1)/3) -> 500 | S4: =0 -> 0 | T4: =S4*Hypothèses!$B$17 -> 0 | U4: =Q4*Hypothèses!$B$5 -> 0.31425 | V4: =Q4-R4-T4-U4 -> -468.88925 | W4: =Hypothèses!$B$2+V4 -> 1631.1108
A5: 2 | B5: =INT((A5-1)/12)+1 -> 1 | C5: =ROUND(IF(MOD($A5,12)=0,G5,(IF(5=4,0,C4))*(1-$K5)+IF((IF(5=4,0,C4))*(1-$K5)<G5,(G5-(IF(5=4,0,C4))*(1-$K5))*Hypothèses!$B$10,0)),1) -> 0.3 | D5: =ROUND(IF(MOD($A5,12)=0,H5,(IF(5=4,0,D4))*(1-$K5)+IF((IF(5=4,0,D4))*(1-$K5)<H5,(H5-(IF(5=4,0,D4))*(1-$K5))*Hypothèses!$B$10,0)),1) -> 0.6 | E5: =ROUND(IF(MOD($A5,12)=0,I5,(IF(5=4,0,E4))*(1-$K5)+IF((IF(5=4,0,E4))*(1-$K5)<I5,(I5-(IF(5=4,0,E4))*(1-$K5))*Hypothèses!$B$10,0)),1) -> 0 | F5: =ROUND(IF(MOD($A5,12)=0,J5,(IF(5=4,0,F4))*(1-$K5)+IF((IF(5=4,0,F4))*(1-$K5)<J5,(J5-(IF(5=4,0,F4))*(1-$K5))*Hypothèses!$B$10,0)),1) -> 0 | G5: =(IF(B5=1,0,IF(B5=2,Hypothèses!$B$26,IF(B5=3,Hypothèses!$C$26,Hypothèses!$D$26)))+(IF(B5=1,Hypothèses!$B$26,IF(B5=2,Hypothèses!$C$26,IF(B5=3,Hypothèses!$D$26,Hypothèses!$D$26)))-(IF(B5=1,0,IF(B5=2,Hypothèses!$B$26,IF(B5=3,Hypothèses!$C$26,Hypothèses!$D$26)))))*((A5)-INT((A5-1)/12)*12)/12)*$B$1 -> 0.58333333 | H5: =(IF(B5=1,0,IF(B5=2,Hypothèses!$B$27,IF(B5=3,Hypothèses!$C$27,Hypothèses!$D$27)))+(IF(B5=1,Hypothèses!$B$27,IF(B5=2,Hypothèses!$C$27,IF(B5=3,Hypothèses!$D$27,Hypothèses!$D$27)))-(IF(B5=1,0,IF(B5=2,Hypothèses!$B$27,IF(B5=3,Hypothèses!$C$27,Hypothèses!$D$27)))))*((A5)-INT((A5-1)/12)*12)/12)*$B$1 -> 1.1666667 | I5: =(IF(B5=1,0,IF(B5=2,Hypothèses!$B$28,IF(B5=3,Hypothèses!$C$28,Hypothèses!$D$28)))+(IF(B5=1,Hypothèses!$B$28,IF(B5=2,Hypothèses!$C$28,IF(B5=3,Hypothèses!$D$28,Hypothèses!$D$28)))-(IF(B5=1,0,IF(B5=2,Hypothèses!$B$28,IF(B5=3,Hypothèses!$C$28,Hypothèses!$D$28)))))*((A5)-INT((A5-1)/12)*12)/12)*$B$1 -> 0 | J5: =(IF(B5=1,0,IF(B5=2,Hypothèses!$B$29,IF(B5=3,Hypothèses!$C$29,Hypothèses!$D$29)))+(IF(B5=1,Hypothèses!$B$29,IF(B5=2,Hypothèses!$C$29,IF(B5=3,Hypothèses!$D$29,Hypothèses!$D$29)))-(IF(B5=1,0,IF(B5=2,Hypothèses!$B$29,IF(B5=3,Hypothèses!$C$29,Hypothèses!$D$29)))))*((A5)-INT((A5-1)/12)*12)/12)*$B$1 -> 0 | K5: =IF(A5<Hypothèses!$B$7,0,Hypothèses!$B$8*(1-Hypothèses!$B$9)^(A5-Hypothèses!$B$7)) -> 0 | L5: =C5+D5+E5+F5 -> 0.9 | M5: =(C5*Hypothèses!$B$11+D5*Hypothèses!$B$12+E5*Hypothèses!$B$13+F5*Hypothèses!$B$14)*(IF(B5=1,Hypothèses!$B$20,IF(B5=2,Hypothèses!$B$21,Hypothèses!$B$22))+(1-(IF(B5=1,Hypothèses!$B$20,IF(B5=2,Hypothèses!$B$21,Hypothèses!$B$22))))*11/12) -> 112.23 | N5: =L5*IF(B5=1,Hypothèses!$C$20,IF(B5=2,Hypothèses!$C$21,Hypothèses!$C$22))*IF(B5=1,Hypothèses!$D$20,IF(B5=2,Hypothèses!$D$21,Hypothèses!$D$22)) -> 0.9 | O5: =IF(A5=18,IF($B$2>=1,Hypothèses!$B$33,0),IF(AND(OR(A5=30,A5=34),$D$2>=1),Hypothèses!$B$34*MIN(1,$D$2/3),0)) -> 0 | P5: =M5+N5+O5 -> 113.13 | Q5: =P5/(1+Hypothèses!$B$6) -> 94.275 | R5: =Hypothèses!$B$3*(1+Hypothèses!$B$4)^INT((A5-1)/3) -> 500 | S5: =0 -> 0 | T5: =S5*Hypothèses!$B$17 -> 0 | U5: =Q5*Hypothèses!$B$5 -> 0.94275 | V5: =Q5-R5-T5-U5 -> -406.66775 | W5: =W4+V5 -> 1224.443
A6: 3 | B6: =INT((A6-1)/12)+1 -> 1 | C6: =ROUND(IF(MOD($A6,12)=0,G6,(IF(6=4,0,C5))*(1-$K6)+IF((IF(6=4,0,C5))*(1-$K6)<G6,(G6-(IF(6=4,0,C5))*(1-$K6))*Hypothèses!$B$10,0)),1) -> 0.5 | D6: =ROUND(IF(MOD($A6,12)=0,H6,(IF(6=4,0,D5))*(1-$K6)+IF((IF(6=4,0,D5))*(1-$K6)<H6,(H6-(IF(6=4,0,D5))*(1-$K6))*Hypothèses!$B$10,0)),1) -> 1.1 | E6: =ROUND(IF(MOD($A6,12)=0,I6,(IF(6=4,0,E5))*(1-$K6)+IF((IF(6=4,0,E5))*(1-$K6)<I6,(I6-(IF(6=4,0,E5))*(1-$K6))*Hypothèses!$B$10,0)),1) -> 0 | F6: =ROUND(IF(MOD($A6,12)=0,J6,(IF(6=4,0,F5))*(1-$K6)+IF((IF(6=4,0,F5))*(1-$K6)<J6,(J6-(IF(6=4,0,F5))*(1-$K6))*Hypothèses!$B$10,0)),1) -> 0 | G6: =(IF(B6=1,0,IF(B6=2,Hypothèses!$B$26,IF(B6=3,Hypothèses!$C$26,Hypothèses!$D$26)))+(IF(B6=1,Hypothèses!$B$26,IF(B6=2,Hypothèses!$C$26,IF(B6=3,Hypothèses!$D$26,Hypothèses!$D$26)))-(IF(B6=1,0,IF(B6=2,Hypothèses!$B$26,IF(B6=3,Hypothèses!$C$26,Hypothèses!$D$26)))))*((A6)-INT((A6-1)/12)*12)/12)*$B$1 -> 0.875 | H6: =(IF(B6=1,0,IF(B6=2,Hypothèses!$B$27,IF(B6=3,Hypothèses!$C$27,Hypothèses!$D$27)))+(IF(B6=1,Hypothèses!$B$27,IF(B6=2,Hypothèses!$C$27,IF(B6=3,Hypothèses!$D$27,Hypothèses!$D$27)))-(IF(B6=1,0,IF(B6=2,Hypothèses!$B$27,IF(B6=3,Hypothèses!$C$27,Hypothèses!$D$27)))))*((A6)-INT((A6-1)/12)*12)/12)*$B$1 -> 1.75 | I6: =(IF(B6=1,0,IF(B6=2,Hypothèses!$B$28,IF(B6=3,Hypothèses!$C$28,Hypothèses!$D$28)))+(IF(B6=1,Hypothèses!$B$28,IF(B6=2,Hypothèses!$C$28,IF(B6=3,Hypothèses!$D$28,Hypothèses!$D$28)))-(IF(B6=1,0,IF(B6=2,Hypothèses!$B$28,IF(B6=3,Hypothèses!$C$28,Hypothèses!$D$28)))))*((A6)-INT((A6-1)/12)*12)/12)*$B$1 -> 0 | J6: =(IF(B6=1,0,IF(B6=2,Hypothèses!$B$29,IF(B6=3,Hypothèses!$C$29,Hypothèses!$D$29)))+(IF(B6=1,Hypothèses!$B$29,IF(B6=2,Hypothèses!$C$29,IF(B6=3,Hypothèses!$D$29,Hypothèses!$D$29)))-(IF(B6=1,0,IF(B6=2,Hypothèses!$B$29,IF(B6=3,Hypothèses!$C$29,Hypothèses!$D$29)))))*((A6)-INT((A6-1)/12)*12)/12)*$B$1 -> 0 | K6: =IF(A6<Hypothèses!$B$7,0,Hypothèses!$B$8*(1-Hypothèses!$B$9)^(A6-Hypothèses!$B$7)) -> 0 | L6: =C6+D6+E6+F6 -> 1.6 | M6: =(C6*Hypothèses!$B$11+D6*Hypothèses!$B$12+E6*Hypothèses!$B$13+F6*Hypothèses!$B$14)*(IF(B6=1,Hypothèses!$B$20,IF(B6=2,Hypothèses!$B$21,Hypothèses!$B$22))+(1-(IF(B6=1,Hypothèses!$B$20,IF(B6=2,Hypothèses!$B$21,Hypothèses!$B$22))))*11/12) -> 201.45333 | N6: =L6*IF(B6=1,Hypothèses!$C$20,IF(B6=2,Hypothèses!$C$21,Hypothèses!$C$22))*IF(B6=1,Hypothèses!$D$20,IF(B6=2,Hypothèses!$D$21,Hypothèses!$D$22)) -> 1.6 | O6: =IF(A6=18,IF($B$2>=1,Hypothèses!$B$33,0),IF(AND(OR(A6=30,A6=34),$D$2>=1),Hypothèses!$B$34*MIN(1,$D$2/3),0)) -> 0 | P6: =M6+N6+O6 -> 203.05333 | Q6: =P6/(1+Hypothèses!$B$6) -> 169.21111 | R6: =Hypothèses!$B$3*(1+Hypothèses!$B$4)^INT((A6-1)/3) -> 500 | S6: =0 -> 0 | T6: =S6*Hypothèses!$B$17 -> 0 | U6: =Q6*Hypothèses!$B$5 -> 1.6921111 | V6: =Q6-R6-T6-U6 -> -332.481 | W6: =W5+V6 -> 891.962
A7: 4 | B7: =INT((A7-1)/12)+1 -> 1 | C7: =ROUND(IF(MOD($A7,12)=0,G7,(IF(7=4,0,C6))*(1-$K7)+IF((IF(7=4,0,C6))*(1-$K7)<G7,(G7-(IF(7=4,0,C6))*(1-$K7))*Hypothèses!$B$10,0)),1) -> 0.8 | D7: =ROUND(IF(MOD($A7,12)=0,H7,(IF(7=4,0,D6))*(1-$K7)+IF((IF(7=4,0,D6))*(1-$K7)<H7,(H7-(IF(7=4,0,D6))*(1-$K7))*Hypothèses!$B$10,0)),1) -> 1.6 | E7: =ROUND(IF(MOD($A7,12)=0,I7,(IF(7=4,0,E6))*(1-$K7)+IF((IF(7=4,0,E6))*(1-$K7)<I7,(I7-(IF(7=4,0,E6))*(1-$K7))*Hypothèses!$B$10,0)),1) -> 0 | F7: =ROUND(IF(MOD($A7,12)=0,J7,(IF(7=4,0,F6))*(1-$K7)+IF((IF(7=4,0,F6))*(1-$K7)<J7,(J7-(IF(7=4,0,F6))*(1-$K7))*Hypothèses!$B$10,0)),1) -> 0 | G7: =(IF(B7=1,0,IF(B7=2,Hypothèses!$B$26,IF(B7=3,Hypothèses!$C$26,Hypothèses!$D$26)))+(IF(B7=1,Hypothèses!$B$26,IF(B7=2,Hypothèses!$C$26,IF(B7=3,Hypothèses!$D$26,Hypothèses!$D$26)))-(IF(B7=1,0,IF(B7=2,Hypothèses!$B$26,IF(B7=3,Hypothèses!$C$26,Hypothèses!$D$26)))))*((A7)-INT((A7-1)/12)*12)/12)*$B$1 -> 1.1666667 | H7: =(IF(B7=1,0,IF(B7=2,Hypothèses!$B$27,IF(B7=3,Hypothèses!$C$27,Hypothèses!$D$27)))+(IF(B7=1,Hypothèses!$B$27,IF(B7=2,Hypothèses!$C$27,IF(B7=3,Hypothèses!$D$27,Hypothèses!$D$27)))-(IF(B7=1,0,IF(B7=2,Hypothèses!$B$27,IF(B7=3,Hypothèses!$C$27,Hypothèses!$D$27)))))*((A7)-INT((A7-1)/12)*12)/12)*$B$1 -> 2.3333333 | I7: =(IF(B7=1,0,IF(B7=2,Hypothèses!$B$28,IF(B7=3,Hypothèses!$C$28,Hypothèses!$D$28)))+(IF(B7=1,Hypothèses!$B$28,IF(B7=2,Hypothèses!$C$28,IF(B7=3,Hypothèses!$D$28,Hypothèses!$D$28)))-(IF(B7=1,0,IF(B7=2,Hypothèses!$B$28,IF(B7=3,Hypothèses!$C$28,Hypothèses!$D$28)))))*((A7)-INT((A7-1)/12)*12)/12)*$B$1 -> 0 | J7: =(IF(B7=1,0,IF(B7=2,Hypothèses!$B$29,IF(B7=3,Hypothèses!$C$29,Hypothèses!$D$29)))+(IF(B7=1,Hypothèses!$B$29,IF(B7=2,Hypothèses!$C$29,IF(B7=3,Hypothèses!$D$29,Hypothèses!$D$29)))-(IF(B7=1,0,IF(B7=2,Hypothèses!$B$29,IF(B7=3,Hypothèses!$C$29,Hypothèses!$D$29)))))*((A7)-INT((A7-1)/12)*12)/12)*$B$1 -> 0 | K7: =IF(A7<Hypothèses!$B$7,0,Hypothèses!$B$8*(1-Hypothèses!$B$9)^(A7-Hypothèses!$B$7)) -> 0 | L7: =C7+D7+E7+F7 -> 2.4 | M7: =(C7*Hypothèses!$B$11+D7*Hypothèses!$B$12+E7*Hypothèses!$B$13+F7*Hypothèses!$B$14)*(IF(B7=1,Hypothèses!$B$20,IF(B7=2,Hypothèses!$B$21,Hypothèses!$B$22))+(1-(IF(B7=1,Hypothèses!$B$20,IF(B7=2,Hypothèses!$B$21,Hypothèses!$B$22))))*11/12) -> 299.28 | N7: =L7*IF(B7=1,Hypothèses!$C$20,IF(B7=2,Hypothèses!$C$21,Hypothèses!$C$22))*IF(B7=1,Hypothèses!$D$20,IF(B7=2,Hypothèses!$D$21,Hypothèses!$D$22)) -> 2.4 | O7: =IF(A7=18,IF($B$2>=1,Hypothèses!$B$33,0),IF(AND(OR(A7=30,A7=34),$D$2>=1),Hypothèses!$B$34*MIN(1,$D$2/3),0)) -> 0 | P7: =M7+N7+O7 -> 301.68 | Q7: =P7/(1+Hypothèses!$B$6) -> 251.4 | R7: =Hypothèses!$B$3*(1+Hypothèses!$B$4)^INT((A7-1)/3) -> 575 | S7: =0 -> 0 | T7: =S7*Hypothèses!$B$17 -> 0 | U7: =Q7*Hypothèses!$B$5 -> 2.514 | V7: =Q7-R7-T7-U7 -> -326.114 | W7: =W6+V7 -> 565.848
A8: 5 | B8: =INT((A8-1)/12)+1 -> 1 | C8: =ROUND(IF(MOD($A8,12)=0,G8,(IF(8=4,0,C7))*(1-$K8)+IF((IF(8=4,0,C7))*(1-$K8)<G8,(G8-(IF(8=4,0,C7))*(1-$K8))*Hypothèses!$B$10,0)),1) -> 1.1 | D8: =ROUND(IF(MOD($A8,12)=0,H8,(IF(8=4,0,D7))*(1-$K8)+IF((IF(8=4,0,D7))*(1-$K8)<H8,(H8-(IF(8=4,0,D7))*(1-$K8))*Hypothèses!$B$10,0)),1) -> 2.1 | E8: =ROUND(IF(MOD($A8,12)=0,I8,(IF(8=4,0,E7))*(1-$K8)+IF((IF(8=4,0,E7))*(1-$K8)<I8,(I8-(IF(8=4,0,E7))*(1-$K8))*Hypothèses!$B$10,0)),1) -> 0 | F8: =ROUND(IF(MOD($A8,12)=0,J8,(IF(8=4,0,F7))*(1-$K8)+IF((IF(8=4,0,F7))*(1-$K8)<J8,(J8-(IF(8=4,0,F7))*(1-$K8))*Hypothèses!$B$10,0)),1) -> 0 | G8: =(IF(B8=1,0,IF(B8=2,Hypothèses!$B$26,IF(B8=3,Hypothèses!$C$26,Hypothèses!$D$26)))+(IF(B8=1,Hypothèses!$B$26,IF(B8=2,Hypothèses!$C$26,IF(B8=3,Hypothèses!$D$26,Hypothèses!$D$26)))-(IF(B8=1,0,IF(B8=2,Hypothèses!$B$26,IF(B8=3,Hypothèses!$C$26,Hypothèses!$D$26)))))*((A8)-INT((A8-1)/12)*12)/12)*$B$1 -> 1.4583333 | H8: =(IF(B8=1,0,IF(B8=2,Hypothèses!$B$27,IF(B8=3,Hypothèses!$C$27,Hypothèses!$D$27)))+(IF(B8=1,Hypothèses!$B$27,IF(B8=2,Hypothèses!$C$27,IF(B8=3,Hypothèses!$D$27,Hypothèses!$D$27)))-(IF(B8=1,0,IF(B8=2,Hypothèses!$B$27,IF(B8=3,Hypothèses!$C$27,Hypothèses!$D$27)))))*((A8)-INT((A8-1)/12)*12)/12)*$B$1 -> 2.9166667 | I8: =(IF(B8=1,0,IF(B8=2,Hypothèses!$B$28,IF(B8=3,Hypothèses!$C$28,Hypothèses!$D$28)))+(IF(B8=1,Hypothèses!$B$28,IF(B8=2,Hypothèses!$C$28,IF(B8=3,Hypothèses!$D$28,Hypothèses!$D$28)))-(IF(B8=1,0,IF(B8=2,Hypothèses!$B$28,IF(B8=3,Hypothèses!$C$28,Hypothèses!$D$28)))))*((A8)-INT((A8-1)/12)*12)/12)*$B$1 -> 0 | J8: =(IF(B8=1,0,IF(B8=2,Hypothèses!$B$29,IF(B8=3,Hypothèses!$C$29,Hypothèses!$D$29)))+(IF(B8=1,Hypothèses!$B$29,IF(B8=2,Hypothèses!$C$29,IF(B8=3,Hypothèses!$D$29,Hypothèses!$D$29)))-(IF(B8=1,0,IF(B8=2,Hypothèses!$B$29,IF(B8=3,Hypothèses!$C$29,Hypothèses!$D$29)))))*((A8)-INT((A8-1)/12)*12)/12)*$B$1 -> 0 | K8: =IF(A8<Hypothèses!$B$7,0,Hypothèses!$B$8*(1-Hypothèses!$B$9)^(A8-Hypothèses!$B$7)) -> 0 | L8: =C8+D8+E8+F8 -> 3.2 | M8: =(C8*Hypothèses!$B$11+D8*Hypothèses!$B$12+E8*Hypothèses!$B$13+F8*Hypothèses!$B$14)*(IF(B8=1,Hypothèses!$B$20,IF(B8=2,Hypothèses!$B$21,Hypothèses!$B$22))+(1-(IF(B8=1,Hypothèses!$B$20,IF(B8=2,Hypothèses!$B$21,Hypothèses!$B$22))))*11/12) -> 397.10667 | N8: =L8*IF(B8=1,Hypothèses!$C$20,IF(B8=2,Hypothèses!$C$21,Hypothèses!$C$22))*IF(B8=1,Hypothèses!$D$20,IF(B8=2,Hypothèses!$D$21,Hypothèses!$D$22)) -> 3.2 | O8: =IF(A8=18,IF($B$2>=1,Hypothèses!$B$33,0),IF(AND(OR(A8=30,A8=34),$D$2>=1),Hypothèses!$B$34*MIN(1,$D$2/3),0)) -> 0 | P8: =M8+N8+O8 -> 400.30667 | Q8: =P8/(1+Hypothèses!$B$6) -> 333.58889 | R8: =Hypothèses!$B$3*(1+Hypothèses!$B$4)^INT((A8-1)/3) -> 575 | S8: =0 -> 0 | T8: =S8*Hypothèses!$B$17 -> 0 | U8: =Q8*Hypothèses!$B$5 -> 3.3358889 | V8: =Q8-R8-T8-U8 -> -244.747 | W8: =W7+V8 -> 321.101
A9: 6 | B9: =INT((A9-1)/12)+1 -> 1 | C9: =ROUND(IF(MOD($A9,12)=0,G9,(IF(9=4,0,C8))*(1-$K9)+IF((IF(9=4,0,C8))*(1-$K9)<G9,(G9-(IF(9=4,0,C8))*(1-$K9))*Hypothèses!$B$10,0)),1) -> 1.4 | D9: =ROUND(IF(MOD($A9,12)=0,H9,(IF(9=4,0,D8))*(1-$K9)+IF((IF(9=4,0,D8))*(1-$K9)<H9,(H9-(IF(9=4,0,D8))*(1-$K9))*Hypothèses!$B$10,0)),1) -> 2.7 | E9: =ROUND(IF(MOD($A9,12)=0,I9,(IF(9=4,0,E8))*(1-$K9)+IF((IF(9=4,0,E8))*(1-$K9)<I9,(I9-(IF(9=4,0,E8))*(1-$K9))*Hypothèses!$B$10,0)),1) -> 0 | F9: =ROUND(IF(MOD($A9,12)=0,J9,(IF(9=4,0,F8))*(1-$K9)+IF((IF(9=4,0,F8))*(1-$K9)<J9,(J9-(IF(9=4,0,F8))*(1-$K9))*Hypothèses!$B$10,0)),1) -> 0 | G9: =(IF(B9=1,0,IF(B9=2,Hypothèses!$B$26,IF(B9=3,Hypothèses!$C$26,Hypothèses!$D$26)))+(IF(B9=1,Hypothèses!$B$26,IF(B9=2,Hypothèses!$C$26,IF(B9=3,Hypothèses!$D$26,Hypothèses!$D$26)))-(IF(B9=1,0,IF(B9=2,Hypothèses!$B$26,IF(B9=3,Hypothèses!$C$26,Hypothèses!$D$26)))))*((A9)-INT((A9-1)/12)*12)/12)*$B$1 -> 1.75 | H9: =(IF(B9=1,0,IF(B9=2,Hypothèses!$B$27,IF(B9=3,Hypothèses!$C$27,Hypothèses!$D$27)))+(IF(B9=1,Hypothèses!$B$27,IF(B9=2,Hypothèses!$C$27,IF(B9=3,Hypothèses!$D$27,Hypothèses!$D$27)))-(IF(B9=1,0,IF(B9=2,Hypothèses!$B$27,IF(B9=3,Hypothèses!$C$27,Hypothèses!$D$27)))))*((A9)-INT((A9-1)/12)*12)/12)*$B$1 -> 3.5 | I9: =(IF(B9=1,0,IF(B9=2,Hypothèses!$B$28,IF(B9=3,Hypothèses!$C$28,Hypothèses!$D$28)))+(IF(B9=1,Hypothèses!$B$28,IF(B9=2,Hypothèses!$C$28,IF(B9=3,Hypothèses!$D$28,Hypothèses!$D$28)))-(IF(B9=1,0,IF(B9=2,Hypothèses!$B$28,IF(B9=3,Hypothèses!$C$28,Hypothèses!$D$28)))))*((A9)-INT((A9-1)/12)*12)/12)*$B$1 -> 0 | J9: =(IF(B9=1,0,IF(B9=2,Hypothèses!$B$29,IF(B9=3,Hypothèses!$C$29,Hypothèses!$D$29)))+(IF(B9=1,Hypothèses!$B$29,IF(B9=2,Hypothèses!$C$29,IF(B9=3,Hypothèses!$D$29,Hypothèses!$D$29)))-(IF(B9=1,0,IF(B9=2,Hypothèses!$B$29,IF(B9=3,Hypothèses!$C$29,Hypothèses!$D$29)))))*((A9)-INT((A9-1)/12)*12)/12)*$B$1 -> 0 | K9: =IF(A9<Hypothèses!$B$7,0,Hypothèses!$B$8*(1-Hypothèses!$B$9)^(A9-Hypothèses!$B$7)) -> 0 | L9: =C9+D9+E9+F9 -> 4.1 | M9: =(C9*Hypothèses!$B$11+D9*Hypothèses!$B$12+E9*Hypothèses!$B$13+F9*Hypothèses!$B$14)*(IF(B9=1,Hypothèses!$B$20,IF(B9=2,Hypothèses!$B$21,Hypothèses!$B$22))+(1-(IF(B9=1,Hypothèses!$B$20,IF(B9=2,Hypothèses!$B$21,Hypothèses!$B$22))))*11/12) -> 509.33667 | N9: =L9*IF(B9=1,Hypothèses!$C$20,IF(B9=2,Hypothèses!$C$21,Hypothèses!$C$22))*IF(B9=1,Hypothèses!$D$20,IF(B9=2,Hypothèses!$D$21,Hypothèses!$D$22)) -> 4.1 | O9: =IF(A9=18,IF($B$2>=1,Hypothèses!$B$33,0),IF(AND(OR(A9=30,A9=34),$D$2>=1),Hypothèses!$B$34*MIN(1,$D$2/3),0)) -> 0 | P9: =M9+N9+O9 -> 513.43667 | Q9: =P9/(1+Hypothèses!$B$6) -> 427.86389 | R9: =Hypothèses!$B$3*(1+Hypothèses!$B$4)^INT((A9-1)/3) -> 575 | S9: =0 -> 0 | T9: =S9*Hypothèses!$B$17 -> 0 | U9: =Q9*Hypothèses!$B$5 -> 4.2786389 | V9: =Q9-R9-T9-U9 -> -151.41475 | W9: =W8+V9 -> 169.68625
A10: 7 | B10: =INT((A10-1)/12)+1 -> 1 | C10: =ROUND(IF(MOD($A10,12)=0,G10,(IF(10=4,0,C9))*(1-$K10)+IF((IF(10=4,0,C9))*(1-$K10)<G10,(G10-(IF(10=4,0,C9))*(1-$K10))*Hypothèses!$B$10,0)),1) -> 1.7 | D10: =ROUND(IF(MOD($A10,12)=0,H10,(IF(10=4,0,D9))*(1-$K10)+IF((IF(10=4,0,D9))*(1-$K10)<H10,(H10-(IF(10=4,0,D9))*(1-$K10))*Hypothèses!$B$10,0)),1) -> 3.3 | E10: =ROUND(IF(MOD($A10,12)=0,I10,(IF(10=4,0,E9))*(1-$K10)+IF((IF(10=4,0,E9))*(1-$K10)<I10,(I10-(IF(10=4,0,E9))*(1-$K10))*Hypothèses!$B$10,0)),1) -> 0 | F10: =ROUND(IF(MOD($A10,12)=0,J10,(IF(10=4,0,F9))*(1-$K10)+IF((IF(10=4,0,F9))*(1-$K10)<J10,(J10-(IF(10=4,0,F9))*(1-$K10))*Hypothèses!$B$10,0)),1) -> 0 | G10: =(IF(B10=1,0,IF(B10=2,Hypothèses!$B$26,IF(B10=3,Hypothèses!$C$26,Hypothèses!$D$26)))+(IF(B10=1,Hypothèses!$B$26,IF(B10=2,Hypothèses!$C$26,IF(B10=3,Hypothèses!$D$26,Hypothèses!$D$26)))-(IF(B10=1,0,IF(B10=2,Hypothèses!$B$26,IF(B10=3,Hypothèses!$C$26,Hypothèses!$D$26)))))*((A10)-INT((A10-1)/12)*12)/12)*$B$1 -> 2.0416667 | H10: =(IF(B10=1,0,IF(B10=2,Hypothèses!$B$27,IF(B10=3,Hypothèses!$C$27,Hypothèses!$D$27)))+(IF(B10=1,Hypothèses!$B$27,IF(B10=2,Hypothèses!$C$27,IF(B10=3,Hypothèses!$D$27,Hypothèses!$D$27)))-(IF(B10=1,0,IF(B10=2,Hypothèses!$B$27,IF(B10=3,Hypothèses!$C$27,Hypothèses!$D$27)))))*((A10)-INT((A10-1)/12)*12)/12)*$B$1 -> 4.0833333 | I10: =(IF(B10=1,0,IF(B10=2,Hypothèses!$B$28,IF(B10=3,Hypothèses!$C$28,Hypothèses!$D$28)))+(IF(B10=1,Hypothèses!$B$28,IF(B10=2,Hypothèses!$C$28,IF(B10=3,Hypothèses!$D$28,Hypothèses!$D$28)))-(IF(B10=1,0,IF(B10=2,Hypothèses!$B$28,IF(B10=3,Hypothèses!$C$28,Hypothèses!$D$28)))))*((A10)-INT((A10-1)/12)*12)/12)*$B$1 -> 0 | J10: =(IF(B10=1,0,IF(B10=2,Hypothèses!$B$29,IF(B10=3,Hypothèses!$C$29,Hypothèses!$D$29)))+(IF(B10=1,Hypothèses!$B$29,IF(B10=2,Hypothèses!$C$29,IF(B10=3,Hypothèses!$D$29,Hypothèses!$D$29)))-(IF(B10=1,0,IF(B10=2,Hypothèses!$B$29,IF(B10=3,Hypothèses!$C$29,Hypothèses!$D$29)))))*((A10)-INT((A10-1)/12)*12)/12)*$B$1 -> 0 | K10: =IF(A10<Hypothèses!$B$7,0,Hypothèses!$B$8*(1-Hypothèses!$B$9)^(A10-Hypothèses!$B$7)) -> 0 | L10: =C10+D10+E10+F10 -> 5 | M10: =(C10*Hypothèses!$B$11+D10*Hypothèses!$B$12+E10*Hypothèses!$B$13+F10*Hypothèses!$B$14)*(IF(B10=1,Hypothèses!$B$20,IF(B10=2,Hypothèses!$B$21,Hypothèses!$B$22))+(1-(IF(B10=1,Hypothèses!$B$20,IF(B10=2,Hypothèses!$B$21,Hypothèses!$B$22))))*11/12) -> 621.56667 | N10: =L10*IF(B10=1,Hypothèses!$C$20,IF(B10=2,Hypothèses!$C$21,Hypothèses!$C$22))*IF(B10=1,Hypothèses!$D$20,IF(B10=2,Hypothèses!$D$21,Hypothèses!$D$22)) -> 5 | O10: =IF(A10=18,IF($B$2>=1,Hypothèses!$B$33,0),IF(AND(OR(A10=30,A10=34),$D$2>=1),Hypothèses!$B$34*MIN(1,$D$2/3),0)) -> 0 | P10: =M10+N10+O10 -> 626.56667 | Q10: =P10/(1+Hypothèses!$B$6) -> 522.13889 | R10: =Hypothèses!$B$3*(1+Hypothèses!$B$4)^INT((A10-1)/3) -> 661.25 | S10: =0 -> 0 | T10: =S10*Hypothèses!$B$17 -> 0 | U10: =Q10*Hypothèses!$B$5 -> 5.2213889 | V10: =Q10-R10-T10-U10 -> -144.3325 | W10: =W9+V10 -> 25.35375
A11: 8 | B11: =INT((A11-1)/12)+1 -> 1 | C11: =ROUND(IF(MOD($A11,12)=0,G11,(IF(11=4,0,C10))*(1-$K11)+IF((IF(11=4,0,C10))*(1-$K11)<G11,(G11-(IF(11=4,0,C10))*(1-$K11))*Hypothèses!$B$10,0)),1) -> 2 | D11: =ROUND(IF(MOD($A11,12)=0,H11,(IF(11=4,0,D10))*(1-$K11)+IF((IF(11=4,0,D10))*(1-$K11)<H11,(H11-(IF(11=4,0,D10))*(1-$K11))*Hypothèses!$B$10,0)),1) -> 3.8 | E11: =ROUND(IF(MOD($A11,12)=0,I11,(IF(11=4,0,E10))*(1-$K11)+IF((IF(11=4,0,E10))*(1-$K11)<I11,(I11-(IF(11=4,0,E10))*(1-$K11))*Hypothèses!$B$10,0)),1) -> 0 | F11: =ROUND(IF(MOD($A11,12)=0,J11,(IF(11=4,0,F10))*(1-$K11)+IF((IF(11=4,0,F10))*(1-$K11)<J11,(J11-(IF(11=4,0,F10))*(1-$K11))*Hypothèses!$B$10,0)),1) -> 0 | G11: =(IF(B11=1,0,IF(B11=2,Hypothèses!$B$26,IF(B11=3,Hypothèses!$C$26,Hypothèses!$D$26)))+(IF(B11=1,Hypothèses!$B$26,IF(B11=2,Hypothèses!$C$26,IF(B11=3,Hypothèses!$D$26,Hypothèses!$D$26)))-(IF(B11=1,0,IF(B11=2,Hypothèses!$B$26,IF(B11=3,Hypothèses!$C$26,Hypothèses!$D$26)))))*((A11)-INT((A11-1)/12)*12)/12)*$B$1 -> 2.3333333 | H11: =(IF(B11=1,0,IF(B11=2,Hypothèses!$B$27,IF(B11=3,Hypothèses!$C$27,Hypothèses!$D$27)))+(IF(B11=1,Hypothèses!$B$27,IF(B11=2,Hypothèses!$C$27,IF(B11=3,Hypothèses!$D$27,Hypothèses!$D$27)))-(IF(B11=1,0,IF(B11=2,Hypothèses!$B$27,IF(B11=3,Hypothèses!$C$27,Hypothèses!$D$27)))))*((A11)-INT((A11-1)/12)*12)/12)*$B$1 -> 4.6666667 | I11: =(IF(B11=1,0,IF(B11=2,Hypothèses!$B$28,IF(B11=3,Hypothèses!$C$28,Hypothèses!$D$28)))+(IF(B11=1,Hypothèses!$B$28,IF(B11=2,Hypothèses!$C$28,IF(B11=3,Hypothèses!$D$28,Hypothèses!$D$28)))-(IF(B11=1,0,IF(B11=2,Hypothèses!$B$28,IF(B11=3,Hypothèses!$C$28,Hypothèses!$D$28)))))*((A11)-INT((A11-1)/12)*12)/12)*$B$1 -> 0 | J11: =(IF(B11=1,0,IF(B11=2,Hypothèses!$B$29,IF(B11=3,Hypothèses!$C$29,Hypothèses!$D$29)))+(IF(B11=1,Hypothèses!$B$29,IF(B11=2,Hypothèses!$C$29,IF(B11=3,Hypothèses!$D$29,Hypothèses!$D$29)))-(IF(B11=1,0,IF(B11=2,Hypothèses!$B$29,IF(B11=3,Hypothèses!$C$29,Hypothèses!$D$29)))))*((A11)-INT((A11-1)/12)*12)/12)*$B$1 -> 0 | K11: =IF(A11<Hypothèses!$B$7,0,Hypothèses!$B$8*(1-Hypothèses!$B$9)^(A11-Hypothèses!$B$7)) -> 0 | L11: =C11+D11+E11+F11 -> 5.8 | M11: =(C11*Hypothèses!$B$11+D11*Hypothèses!$B$12+E11*Hypothèses!$B$13+F11*Hypothèses!$B$14)*(IF(B11=1,Hypothèses!$B$20,IF(B11=2,Hypothèses!$B$21,Hypothèses!$B$22))+(1-(IF(B11=1,Hypothèses!$B$20,IF(B11=2,Hypothèses!$B$21,Hypothèses!$B$22))))*11/12) -> 719.39333 | N11: =L11*IF(B11=1,Hypothèses!$C$20,IF(B11=2,Hypothèses!$C$21,Hypothèses!$C$22))*IF(B11=1,Hypothèses!$D$20,IF(B11=2,Hypothèses!$D$21,Hypothèses!$D$22)) -> 5.8 | O11: =IF(A11=18,IF($B$2>=1,Hypothèses!$B$33,0),IF(AND(OR(A11=30,A11=34),$D$2>=1),Hypothèses!$B$34*MIN(1,$D$2/3),0)) -> 0 | P11: =M11+N11+O11 -> 725.19333 | Q11: =P11/(1+Hypothèses!$B$6) -> 604.32778 | R11: =Hypothèses!$B$3*(1+Hypothèses!$B$4)^INT((A11-1)/3) -> 661.25 | S11: =0 -> 0 | T11: =S11*Hypothèses!$B$17 -> 0 | U11: =Q11*Hypothèses!$B$5 -> 6.0432778 | V11: =Q11-R11-T11-U11 -> -62.9655 | W11: =W10+V11 -> -37.61175
A12: 9 | B12: =INT((A12-1)/12)+1 -> 1 | C12: =ROUND(IF(MOD($A12,12)=0,G12,(IF(12=4,0,C11))*(1-$K12)+IF((IF(12=4,0,C11))*(1-$K12)<G12,(G12-(IF(12=4,0,C11))*(1-$K12))*Hypothèses!$B$10,0)),1) -> 2.2 | D12: =ROUND(IF(MOD($A12,12)=0,H12,(IF(12=4,0,D11))*(1-$K12)+IF((IF(12=4,0,D11))*(1-$K12)<H12,(H12-(IF(12=4,0,D11))*(1-$K12))*Hypothèses!$B$10,0)),1) -> 4.3 | E12: =ROUND(IF(MOD($A12,12)=0,I12,(IF(12=4,0,E11))*(1-$K12)+IF((IF(12=4,0,E11))*(1-$K12)<I12,(I12-(IF(12=4,0,E11))*(1-$K12))*Hypothèses!$B$10,0)),1) -> 0 | F12: =ROUND(IF(MOD($A12,12)=0,J12,(IF(12=4,0,F11))*(1-$K12)+IF((IF(12=4,0,F11))*(1-$K12)<J12,(J12-(IF(12=4,0,F11))*(1-$K12))*Hypothèses!$B$10,0)),1) -> 0 | G12: =(IF(B12=1,0,IF(B12=2,Hypothèses!$B$26,IF(B12=3,Hypothèses!$C$26,Hypothèses!$D$26)))+(IF(B12=1,Hypothèses!$B$26,IF(B12=2,Hypothèses!$C$26,IF(B12=3,Hypothèses!$D$26,Hypothèses!$D$26)))-(IF(B12=1,0,IF(B12=2,Hypothèses!$B$26,IF(B12=3,Hypothèses!$C$26,Hypothèses!$D$26)))))*((A12)-INT((A12-1)/12)*12)/12)*$B$1 -> 2.625 | H12: =(IF(B12=1,0,IF(B12=2,Hypothèses!$B$27,IF(B12=3,Hypothèses!$C$27,Hypothèses!$D$27)))+(IF(B12=1,Hypothèses!$B$27,IF(B12=2,Hypothèses!$C$27,IF(B12=3,Hypothèses!$D$27,Hypothèses!$D$27)))-(IF(B12=1,0,IF(B12=2,Hypothèses!$B$27,IF(B12=3,Hypothèses!$C$27,Hypothèses!$D$27)))))*((A12)-INT((A12-1)/12)*12)/12)*$B$1 -> 5.25 | I12: =(IF(B12=1,0,IF(B12=2,Hypothèses!$B$28,IF(B12=3,Hypothèses!$C$28,Hypothèses!$D$28)))+(IF(B12=1,Hypothèses!$B$28,IF(B12=2,Hypothèses!$C$28,IF(B12=3,Hypothèses!$D$28,Hypothèses!$D$28)))-(IF(B12=1,0,IF(B12=2,Hypothèses!$B$28,IF(B12=3,Hypothèses!$C$28,Hypothèses!$D$28)))))*((A12)-INT((A12-1)/12)*12)/12)*$B$1 -> 0 | J12: =(IF(B12=1,0,IF(B12=2,Hypothèses!$B$29,IF(B12=3,Hypothèses!$C$29,Hypothèses!$D$29)))+(IF(B12=1,Hypothèses!$B$29,IF(B12=2,Hypothèses!$C$29,IF(B12=3,Hypothèses!$D$29,Hypothèses!$D$29)))-(IF(B12=1,0,IF(B12=2,Hypothèses!$B$29,IF(B12=3,Hypothèses!$C$29,Hypothèses!$D$29)))))*((A12)-INT((A12-1)/12)*12)/12)*$B$1 -> 0 | K12: =IF(A12<Hypothèses!$B$7,0,Hypothèses!$B$8*(1-Hypothèses!$B$9)^(A12-Hypothèses!$B$7)) -> 0.05 | L12: =C12+D12+E12+F12 -> 6.5 | M12: =(C12*Hypothèses!$B$11+D12*Hypothèses!$B$12+E12*Hypothèses!$B$13+F12*Hypothèses!$B$14)*(IF(B12=1,Hypothèses!$B$20,IF(B12=2,Hypothèses!$B$21,Hypothèses!$B$22))+(1-(IF(B12=1,Hypothèses!$B$20,IF(B12=2,Hypothèses!$B$21,Hypothèses!$B$22))))*11/12) -> 808.61667 | N12: =L12*IF(B12=1,Hypothèses!$C$20,IF(B12=2,Hypothèses!$C$21,Hypothèses!$C$22))*IF(B12=1,Hypothèses!$D$20,IF(B12=2,Hypothèses!$D$21,Hypothèses!$D$22)) -> 6.5 | O12: =IF(A12=18,IF($B$2>=1,Hypothèses!$B$33,0),IF(AND(OR(A12=30,A12=34),$D$2>=1),Hypothèses!$B$34*MIN(1,$D$2/3),0)) -> 0 | P12: =M12+N12+O12 -> 815.11667 | Q12: =P12/(1+Hypothèses!$B$6) -> 679.26389 | R12: =Hypothèses!$B$3*(1+Hypothèses!$B$4)^INT((A12-1)/3) -> 661.25 | S12: =0 -> 0 | T12: =S12*Hypothèses!$B$17 -> 0 | U12: =Q12*Hypothèses!$B$5 -> 6.7926389 | V12: =Q12-R12-T12-U12 -> 11.22125 | W12: =W11+V12 -> -26.3905
A13: 10 | B13: =INT((A13-1)/12)+1 -> 1 | C13: =ROUND(IF(MOD($A13,12)=0,G13,(IF(13=4,0,C12))*(1-$K13)+IF((IF(13=4,0,C12))*(1-$K13)<G13,(G13-(IF(13=4,0,C12))*(1-$K13))*Hypothèses!$B$10,0)),1) -> 2.4 | D13: =ROUND(IF(MOD($A13,12)=0,H13,(IF(13=4,0,D12))*(1-$K13)+IF((IF(13=4,0,D12))*(1-$K13)<H13,(H13-(IF(13=4,0,D12))*(1-$K13))*Hypothèses!$B$10,0)),1) -> 4.8 | E13: =ROUND(IF(MOD($A13,12)=0,I13,(IF(13=4,0,E12))*(1-$K13)+IF((IF(13=4,0,E12))*(1-$K13)<I13,(I13-(IF(13=4,0,E12))*(1-$K13))*Hypothèses!$B$10,0)),1) -> 0 | F13: =ROUND(IF(MOD($A13,12)=0,J13,(IF(13=4,0,F12))*(1-$K13)+IF((IF(13=4,0,F12))*(1-$K13)<J13,(J13-(IF(13=4,0,F12))*(1-$K13))*Hypothèses!$B$10,0)),1) -> 0 | G13: =(IF(B13=1,0,IF(B13=2,Hypothèses!$B$26,IF(B13=3,Hypothèses!$C$26,Hypothèses!$D$26)))+(IF(B13=1,Hypothèses!$B$26,IF(B13=2,Hypothèses!$C$26,IF(B13=3,Hypothèses!$D$26,Hypothèses!$D$26)))-(IF(B13=1,0,IF(B13=2,Hypothèses!$B$26,IF(B13=3,Hypothèses!$C$26,Hypothèses!$D$26)))))*((A13)-INT((A13-1)/12)*12)/12)*$B$1 -> 2.9166667 | H13: =(IF(B13=1,0,IF(B13=2,Hypothèses!$B$27,IF(B13=3,Hypothèses!$C$27,Hypothèses!$D$27)))+(IF(B13=1,Hypothèses!$B$27,IF(B13=2,Hypothèses!$C$27,IF(B13=3,Hypothèses!$D$27,Hypothèses!$D$27)))-(IF(B13=1,0,IF(B13=2,Hypothèses!$B$27,IF(B13=3,Hypothèses!$C$27,Hypothèses!$D$27)))))*((A13)-INT((A13-1)/12)*12)/12)*$B$1 -> 5.8333333 | I13: =(IF(B13=1,0,IF(B13=2,Hypothèses!$B$28,IF(B13=3,Hypothèses!$C$28,Hypothèses!$D$28)))+(IF(B13=1,Hypothèses!$B$28,IF(B13=2,Hypothèses!$C$28,IF(B13=3,Hypothèses!$D$28,Hypothèses!$D$28)))-(IF(B13=1,0,IF(B13=2,Hypothèses!$B$28,IF(B13=3,Hypothèses!$C$28,Hypothèses!$D$28)))))*((A13)-INT((A13-1)/12)*12)/12)*$B$1 -> 0 | J13: =(IF(B13=1,0,IF(B13=2,Hypothèses!$B$29,IF(B13=3,Hypothèses!$C$29,Hypothèses!$D$29)))+(IF(B13=1,Hypothèses!$B$29,IF(B13=2,Hypothèses!$C$29,IF(B13=3,Hypothèses!$D$29,Hypothèses!$D$29)))-(IF(B13=1,0,IF(B13=2,Hypothèses!$B$29,IF(B13=3,Hypothèses!$C$29,Hypothèses!$D$29)))))*((A13)-INT((A13-1)/12)*12)/12)*$B$1 -> 0 | K13: =IF(A13<Hypothèses!$B$7,0,Hypothèses!$B$8*(1-Hypothèses!$B$9)^(A13-Hypothèses!$B$7)) -> 0.045 | L13: =C13+D13+E13+F13 -> 7.2 | M13: =(C13*Hypothèses!$B$11+D13*Hypothèses!$B$12+E13*Hypothèses!$B$13+F13*Hypothèses!$B$14)*(IF(B13=1,Hypothèses!$B$20,IF(B13=2,Hypothèses!$B$21,Hypothèses!$B$22))+(1-(IF(B13=1,Hypothèses!$B$20,IF(B13=2,Hypothèses!$B$21,Hypothèses!$B$22))))*11/12) -> 897.84 | N13: =L13*IF(B13=1,Hypothèses!$C$20,IF(B13=2,Hypothèses!$C$21,Hypothèses!$C$22))*IF(B13=1,Hypothèses!$D$20,IF(B13=2,Hypothèses!$D$21,Hypothèses!$D$22)) -> 7.2 | O13: =IF(A13=18,IF($B$2>=1,Hypothèses!$B$33,0),IF(AND(OR(A13=30,A13=34),$D$2>=1),Hypothèses!$B$34*MIN(1,$D$2/3),0)) -> 0 | P13: =M13+N13+O13 -> 905.04 | Q13: =P13/(1+Hypothèses!$B$6) -> 754.2 | R13: =Hypothèses!$B$3*(1+Hypothèses!$B$4)^INT((A13-1)/3) -> 760.4375 | S13: =0 -> 0 | T13: =S13*Hypothèses!$B$17 -> 0 | U13: =Q13*Hypothèses!$B$5 -> 7.542 | V13: =Q13-R13-T13-U13 -> -13.7795 | W13: =W12+V13 -> -40.17
A14: 11 | B14: =INT((A14-1)/12)+1 -> 1 | C14: =ROUND(IF(MOD($A14,12)=0,G14,(IF(14=4,0,C13))*(1-$K14)+IF((IF(14=4,0,C13))*(1-$K14)<G14,(G14-(IF(14=4,0,C13))*(1-$K14))*Hypothèses!$B$10,0)),1) -> 2.7 | D14: =ROUND(IF(MOD($A14,12)=0,H14,(IF(14=4,0,D13))*(1-$K14)+IF((IF(14=4,0,D13))*(1-$K14)<H14,(H14-(IF(14=4,0,D13))*(1-$K14))*Hypothèses!$B$10,0)),1) -> 5.3 | E14: =ROUND(IF(MOD($A14,12)=0,I14,(IF(14=4,0,E13))*(1-$K14)+IF((IF(14=4,0,E13))*(1-$K14)<I14,(I14-(IF(14=4,0,E13))*(1-$K14))*Hypothèses!$B$10,0)),1) -> 0 | F14: =ROUND(IF(MOD($A14,12)=0,J14,(IF(14=4,0,F13))*(1-$K14)+IF((IF(14=4,0,F13))*(1-$K14)<J14,(J14-(IF(14=4,0,F13))*(1-$K14))*Hypothèses!$B$10,0)),1) -> 0 | G14: =(IF(B14=1,0,IF(B14=2,Hypothèses!$B$26,IF(B14=3,Hypothèses!$C$26,Hypothèses!$D$26)))+(IF(B14=1,Hypothèses!$B$26,IF(B14=2,Hypothèses!$C$26,IF(B14=3,Hypothèses!$D$26,Hypothèses!$D$26)))-(IF(B14=1,0,IF(B14=2,Hypothèses!$B$26,IF(B14=3,Hypothèses!$C$26,Hypothèses!$D$26)))))*((A14)-INT((A14-1)/12)*12)/12)*$B$1 -> 3.2083333 | H14: =(IF(B14=1,0,IF(B14=2,Hypothèses!$B$27,IF(B14=3,Hypothèses!$C$27,Hypothèses!$D$27)))+(IF(B14=1,Hypothèses!$B$27,IF(B14=2,Hypothèses!$C$27,IF(B14=3,Hypothèses!$D$27,Hypothèses!$D$27)))-(IF(B14=1,0,IF(B14=2,Hypothèses!$B$27,IF(B14=3,Hypothèses!$C$27,Hypothèses!$D$27)))))*((A14)-INT((A14-1)/12)*12)/12)*$B$1 -> 6.4166667 | I14: =(IF(B14=1,0,IF(B14=2,Hypothèses!$B$28,IF(B14=3,Hypothèses!$C$28,Hypothèses!$D$28)))+(IF(B14=1,Hypothèses!$B$28,IF(B14=2,Hypothèses!$C$28,IF(B14=3,Hypothèses!$D$28,Hypothèses!$D$28)))-(IF(B14=1,0,IF(B14=2,Hypothèses!$B$28,IF(B14=3,Hypothèses!$C$28,Hypothèses!$D$28)))))*((A14)-INT((A14-1)/12)*12)/12)*$B$1 -> 0 | J14: =(IF(B14=1,0,IF(B14=2,Hypothèses!$B$29,IF(B14=3,Hypothèses!$C$29,Hypothèses!$D$29)))+(IF(B14=1,Hypothèses!$B$29,IF(B14=2,Hypothèses!$C$29,IF(B14=3,Hypothèses!$D$29,Hypothèses!$D$29)))-(IF(B14=1,0,IF(B14=2,Hypothèses!$B$29,IF(B14=3,Hypothèses!$C$29,Hypothèses!$D$29)))))*((A14)-INT((A14-1)/12)*12)/12)*$B$1 -> 0 | K14: =IF(A14<Hypothèses!$B$7,0,Hypothèses!$B$8*(1-Hypothèses!$B$9)^(A14-Hypothèses!$B$7)) -> 0.0405 | L14: =C14+D14+E14+F14 -> 8 | M14: =(C14*Hypothèses!$B$11+D14*Hypothèses!$B$12+E14*Hypothèses!$B$13+F14*Hypothèses!$B$14)*(IF(B14=1,Hypothèses!$B$20,IF(B14=2,Hypothèses!$B$21,Hypothèses!$B$22))+(1-(IF(B14=1,Hypothèses!$B$20,IF(B14=2,Hypothèses!$B$21,Hypothèses!$B$22))))*11/12) -> 995.66667 | N14: =L14*IF(B14=1,Hypothèses!$C$20,IF(B14=2,Hypothèses!$C$21,Hypothèses!$C$22))*IF(B14=1,Hypothèses!$D$20,IF(B14=2,Hypothèses!$D$21,Hypothèses!$D$22)) -> 8 | O14: =IF(A14=18,IF($B$2>=1,Hypothèses!$B$33,0),IF(AND(OR(A14=30,A14=34),$D$2>=1),Hypothèses!$B$34*MIN(1,$D$2/3),0)) -> 0 | P14: =M14+N14+O14 -> 1003.6667 | Q14: =P14/(1+Hypothèses!$B$6) -> 836.38889 | R14: =Hypothèses!$B$3*(1+Hypothèses!$B$4)^INT((A14-1)/3) -> 760.4375 | S14: =0 -> 0 | T14: =S14*Hypothèses!$B$17 -> 0 | U14: =Q14*Hypothèses!$B$5 -> 8.3638889 | V14: =Q14-R14-T14-U14 -> 67.5875 | W14: =W13+V14 -> 27.4175
A15: 12 | B15: =INT((A15-1)/12)+1 -> 1 | C15: =ROUND(IF(MOD($A15,12)=0,G15,(IF(15=4,0,C14))*(1-$K15)+IF((IF(15=4,0,C14))*(1-$K15)<G15,(G15-(IF(15=4,0,C14))*(1-$K15))*Hypothèses!$B$10,0)),1) -> 3.5 | D15: =ROUND(IF(MOD($A15,12)=0,H15,(IF(15=4,0,D14))*(1-$K15)+IF((IF(15=4,0,D14))*(1-$K15)<H15,(H15-(IF(15=4,0,D14))*(1-$K15))*Hypothèses!$B$10,0)),1) -> 7 | E15: =ROUND(IF(MOD($A15,12)=0,I15,(IF(15=4,0,E14))*(1-$K15)+IF((IF(15=4,0,E14))*(1-$K15)<I15,(I15-(IF(15=4,0,E14))*(1-$K15))*Hypothèses!$B$10,0)),1) -> 0 | F15: =ROUND(IF(MOD($A15,12)=0,J15,(IF(15=4,0,F14))*(1-$K15)+IF((IF(15=4,0,F14))*(1-$K15)<J15,(J15-(IF(15=4,0,F14))*(1-$K15))*Hypothèses!$B$10,0)),1) -> 0 | G15: =(IF(B15=1,0,IF(B15=2,Hypothèses!$B$26,IF(B15=3,Hypothèses!$C$26,Hypothèses!$D$26)))+(IF(B15=1,Hypothèses!$B$26,IF(B15=2,Hypothèses!$C$26,IF(B15=3,Hypothèses!$D$26,Hypothèses!$D$26)))-(IF(B15=1,0,IF(B15=2,Hypothèses!$B$26,IF(B15=3,Hypothèses!$C$26,Hypothèses!$D$26)))))*((A15)-INT((A15-1)/12)*12)/12)*$B$1 -> 3.5 | H15: =(IF(B15=1,0,IF(B15=2,Hypothèses!$B$27,IF(B15=3,Hypothèses!$C$27,Hypothèses!$D$27)))+(IF(B15=1,Hypothèses!$B$27,IF(B15=2,Hypothèses!$C$27,IF(B15=3,Hypothèses!$D$27,Hypothèses!$D$27)))-(IF(B15=1,0,IF(B15=2,Hypothèses!$B$27,IF(B15=3,Hypothèses!$C$27,Hypothèses!$D$27)))))*((A15)-INT((A15-1)/12)*12)/12)*$B$1 -> 7 | I15: =(IF(B15=1,0,IF(B15=2,Hypothèses!$B$28,IF(B15=3,Hypothèses!$C$28,Hypothèses!$D$28)))+(IF(B15=1,Hypothèses!$B$28,IF(B15=2,Hypothèses!$C$28,IF(B15=3,Hypothèses!$D$28,Hypothèses!$D$28)))-(IF(B15=1,0,IF(B15=2,Hypothèses!$B$28,IF(B15=3,Hypothèses!$C$28,Hypothèses!$D$28)))))*((A15)-INT((A15-1)/12)*12)/12)*$B$1 -> 0 | J15: =(IF(B15=1,0,IF(B15=2,Hypothèses!$B$29,IF(B15=3,Hypothèses!$C$29,Hypothèses!$D$29)))+(IF(B15=1,Hypothèses!$B$29,IF(B15=2,Hypothèses!$C$29,IF(B15=3,Hypothèses!$D$29,Hypothèses!$D$29)))-(IF(B15=1,0,IF(B15=2,Hypothèses!$B$29,IF(B15=3,Hypothèses!$C$29,Hypothèses!$D$29)))))*((A15)-INT((A15-1)/12)*12)/12)*$B$1 -> 0 | K15: =IF(A15<Hypothèses!$B$7,0,Hypothèses!$B$8*(1-Hypothèses!$B$9)^(A15-Hypothèses!$B$7)) -> 0.03645 | L15: =C15+D15+E15+F15 -> 10.5 | M15: =(C15*Hypothèses!$B$11+D15*Hypothèses!$B$12+E15*Hypothèses!$B$13+F15*Hypothèses!$B$14)*(IF(B15=1,Hypothèses!$B$20,IF(B15=2,Hypothèses!$B$21,Hypothèses!$B$22))+(1-(IF(B15=1,Hypothèses!$B$20,IF(B15=2,Hypothèses!$B$21,Hypothèses!$B$22))))*11/12) -> 1309.35 | N15: =L15*IF(B15=1,Hypothèses!$C$20,IF(B15=2,Hypothèses!$C$21,Hypothèses!$C$22))*IF(B15=1,Hypothèses!$D$20,IF(B15=2,Hypothèses!$D$21,Hypothèses!$D$22)) -> 10.5 | O15: =IF(A15=18,IF($B$2>=1,Hypothèses!$B$33,0),IF(AND(OR(A15=30,A15=34),$D$2>=1),Hypothèses!$B$34*MIN(1,$D$2/3),0)) -> 0 | P15: =M15+N15+O15 -> 1319.85 | Q15: =P15/(1+Hypothèses!$B$6) -> 1099.875 | R15: =Hypothèses!$B$3*(1+Hypothèses!$B$4)^INT((A15-1)/3) -> 760.4375 | S15: =0 -> 0 | T15: =S15*Hypothèses!$B$17 -> 0 | U15: =Q15*Hypothèses!$B$5 -> 10.99875 | V15: =Q15-R15-T15-U15 -> 328.43875 | W15: =W14+V15 -> 355.85625
A16: 13 | B16: =INT((A16-1)/12)+1 -> 2 | C16: =ROUND(IF(MOD($A16,12)=0,G16,(IF(16=4,0,C15))*(1-$K16)+IF((IF(16=4,0,C15))*(1-$K16)<G16,(G16-(IF(16=4,0,C15))*(1-$K16))*Hypothèses!$B$10,0)),1) -> 3.5 | D16: =ROUND(IF(MOD($A16,12)=0,H16,(IF(16=4,0,D15))*(1-$K16)+IF((IF(16=4,0,D15))*(1-$K16)<H16,(H16-(IF(16=4,0,D15))*(1-$K16))*Hypothèses!$B$10,0)),1) -> 7.4 | E16: =ROUND(IF(MOD($A16,12)=0,I16,(IF(16=4,0,E15))*(1-$K16)+IF((IF(16=4,0,E15))*(1-$K16)<I16,(I16-(IF(16=4,0,E15))*(1-$K16))*Hypothèses!$B$10,0)),1) -> 0 | F16: =ROUND(IF(MOD($A16,12)=0,J16,(IF(16=4,0,F15))*(1-$K16)+IF((IF(16=4,0,F15))*(1-$K16)<J16,(J16-(IF(16=4,0,F15))*(1-$K16))*Hypothèses!$B$10,0)),1) -> 0 | G16: =(IF(B16=1,0,IF(B16=2,Hypothèses!$B$26,IF(B16=3,Hypothèses!$C$26,Hypothèses!$D$26)))+(IF(B16=1,Hypothèses!$B$26,IF(B16=2,Hypothèses!$C$26,IF(B16=3,Hypothèses!$D$26,Hypothèses!$D$26)))-(IF(B16=1,0,IF(B16=2,Hypothèses!$B$26,IF(B16=3,Hypothèses!$C$26,Hypothèses!$D$26)))))*((A16)-INT((A16-1)/12)*12)/12)*$B$1 -> 3.7916667 | H16: =(IF(B16=1,0,IF(B16=2,Hypothèses!$B$27,IF(B16=3,Hypothèses!$C$27,Hypothèses!$D$27)))+(IF(B16=1,Hypothèses!$B$27,IF(B16=2,Hypothèses!$C$27,IF(B16=3,Hypothèses!$D$27,Hypothèses!$D$27)))-(IF(B16=1,0,IF(B16=2,Hypothèses!$B$27,IF(B16=3,Hypothèses!$C$27,Hypothèses!$D$27)))))*((A16)-INT((A16-1)/12)*12)/12)*$B$1 -> 8.4583333 | I16: =(IF(B16=1,0,IF(B16=2,Hypothèses!$B$28,IF(B16=3,Hypothèses!$C$28,Hypothèses!$D$28)))+(IF(B16=1,Hypothèses!$B$28,IF(B16=2,Hypothèses!$C$28,IF(B16=3,Hypothèses!$D$28,Hypothèses!$D$28)))-(IF(B16=1,0,IF(B16=2,Hypothèses!$B$28,IF(B16=3,Hypothèses!$C$28,Hypothèses!$D$28)))))*((A16)-INT((A16-1)/12)*12)/12)*$B$1 -> 0.058333333 | J16: =(IF(B16=1,0,IF(B16=2,Hypothèses!$B$29,IF(B16=3,Hypothèses!$C$29,Hypothèses!$D$29)))+(IF(B16=1,Hypothèses!$B$29,IF(B16=2,Hypothèses!$C$29,IF(B16=3,Hypothèses!$D$29,Hypothèses!$D$29)))-(IF(B16=1,0,IF(B16=2,Hypothèses!$B$29,IF(B16=3,Hypothèses!$C$29,Hypothèses!$D$29)))))*((A16)-INT((A16-1)/12)*12)/12)*$B$1 -> 0.058333333 | K16: =IF(A16<Hypothèses!$B$7,0,Hypothèses!$B$8*(1-Hypothèses!$B$9)^(A16-Hypothèses!$B$7)) -> 0.032805 | L16: =C16+D16+E16+F16 -> 10.9 | M16: =(C16*Hypothèses!$B$11+D16*Hypothèses!$B$12+E16*Hypothèses!$B$13+F16*Hypothèses!$B$14)*(IF(B16=1,Hypothèses!$B$20,IF(B16=2,Hypothèses!$B$21,Hypothèses!$B$22))+(1-(IF(B16=1,Hypothèses!$B$20,IF(B16=2,Hypothèses!$B$21,Hypothèses!$B$22))))*11/12) -> 1355.1792 | N16: =L16*IF(B16=1,Hypothèses!$C$20,IF(B16=2,Hypothèses!$C$21,Hypothèses!$C$22))*IF(B16=1,Hypothèses!$D$20,IF(B16=2,Hypothèses!$D$21,Hypothèses!$D$22)) -> 27.25 | O16: =IF(A16=18,IF($B$2>=1,Hypothèses!$B$33,0),IF(AND(OR(A16=30,A16=34),$D$2>=1),Hypothèses!$B$34*MIN(1,$D$2/3),0)) -> 0 | P16: =M16+N16+O16 -> 1382.4292 | Q16: =P16/(1+Hypothèses!$B$6) -> 1152.0243 | R16: =Hypothèses!$B$3*(1+Hypothèses!$B$4)^INT((A16-1)/3) -> 874.50312 | S16: =0 -> 0 | T16: =S16*Hypothèses!$B$17 -> 0 | U16: =Q16*Hypothèses!$B$5 -> 11.520243 | V16: =Q16-R16-T16-U16 -> 266.00094 | W16: =W15+V16 -> 621.85719
A17: 14 | B17: =INT((A17-1)/12)+1 -> 2 | C17: =ROUND(IF(MOD($A17,12)=0,G17,(IF(17=4,0,C16))*(1-$K17)+IF((IF(17=4,0,C16))*(1-$K17)<G17,(G17-(IF(17=4,0,C16))*(1-$K17))*Hypothèses!$B$10,0)),1) -> 3.7 | D17: =ROUND(IF(MOD($A17,12)=0,H17,(IF(17=4,0,D16))*(1-$K17)+IF((IF(17=4,0,D16))*(1-$K17)<H17,(H17-(IF(17=4,0,D16))*(1-$K17))*Hypothèses!$B$10,0)),1) -> 8.3 | E17: =ROUND(IF(MOD($A17,12)=0,I17,(IF(17=4,0,E16))*(1-$K17)+IF((IF(17=4,0,E16))*(1-$K17)<I17,(I17-(IF(17=4,0,E16))*(1-$K17))*Hypothèses!$B$10,0)),1) -> 0 | F17: =ROUND(IF(MOD($A17,12)=0,J17,(IF(17=4,0,F16))*(1-$K17)+IF((IF(17=4,0,F16))*(1-$K17)<J17,(J17-(IF(17=4,0,F16))*(1-$K17))*Hypothèses!$B$10,0)),1) -> 0 | G17: =(IF(B17=1,0,IF(B17=2,Hypothèses!$B$26,IF(B17=3,Hypothèses!$C$26,Hypothèses!$D$26)))+(IF(B17=1,Hypothèses!$B$26,IF(B17=2,Hypothèses!$C$26,IF(B17=3,Hypothèses!$D$26,Hypothèses!$D$26)))-(IF(B17=1,0,IF(B17=2,Hypothèses!$B$26,IF(B17=3,Hypothèses!$C$26,Hypothèses!$D$26)))))*((A17)-INT((A17-1)/12)*12)/12)*$B$1 -> 4.0833333 | H17: =(IF(B17=1,0,IF(B17=2,Hypothèses!$B$27,IF(B17=3,Hypothèses!$C$27,Hypothèses!$D$27)))+(IF(B17=1,Hypothèses!$B$27,IF(B17=2,Hypothèses!$C$27,IF(B17=3,Hypothèses!$D$27,Hypothèses!$D$27)))-(IF(B17=1,0,IF(B17=2,Hypothèses!$B$27,IF(B17=3,Hypothèses!$C$27,Hypothèses!$D$27)))))*((A17)-INT((A17-1)/12)*12)/12)*$B$1 -> 9.9166667 | I17: =(IF(B17=1,0,IF(B17=2,Hypothèses!$B$28,IF(B17=3,Hypothèses!$C$28,Hypothèses!$D$28)))+(IF(B17=1,Hypothèses!$B$28,IF(B17=2,Hypothèses!$C$28,IF(B17=3,Hypothèses!$D$28,Hypothèses!$D$28)))-(IF(B17=1,0,IF(B17=2,Hypothèses!$B$28,IF(B17=3,Hypothèses!$C$28,Hypothèses!$D$28)))))*((A17)-INT((A17-1)/12)*12)/12)*$B$1 -> 0.11666667 | J17: =(IF(B17=1,0,IF(B17=2,Hypothèses!$B$29,IF(B17=3,Hypothèses!$C$29,Hypothèses!$D$29)))+(IF(B17=1,Hypothèses!$B$29,IF(B17=2,Hypothèses!$C$29,IF(B17=3,Hypothèses!$D$29,Hypothèses!$D$29)))-(IF(B17=1,0,IF(B17=2,Hypothèses!$B$29,IF(B17=3,Hypothèses!$C$29,Hypothèses!$D$29)))))*((A17)-INT((A17-1)/12)*12)/12)*$B$1 -> 0.11666667 | K17: =IF(A17<Hypothèses!$B$7,0,Hypothèses!$B$8*(1-Hypothèses!$B$9)^(A17-Hypothèses!$B$7)) -> 0.0295245 | L17: =C17+D17+E17+F17 -> 12 | M17: =(C17*Hypothèses!$B$11+D17*Hypothèses!$B$12+E17*Hypothèses!$B$13+F17*Hypothèses!$B$14)*(IF(B17=1,Hypothèses!$B$20,IF(B17=2,Hypothèses!$B$21,Hypothèses!$B$22))+(1-(IF(B17=1,Hypothèses!$B$20,IF(B17=2,Hypothèses!$B$21,Hypothèses!$B$22))))*11/12) -> 1500.75 | N17: =L17*IF(B17=1,Hypothèses!$C$20,IF(B17=2,Hypothèses!$C$21,Hypothèses!$C$22))*IF(B17=1,Hypothèses!$D$20,IF(B17=2,Hypothèses!$D$21,Hypothèses!$D$22)) -> 30 | O17: =IF(A17=18,IF($B$2>=1,Hypothèses!$B$33,0),IF(AND(OR(A17=30,A17=34),$D$2>=1),Hypothèses!$B$34*MIN(1,$D$2/3),0)) -> 0 | P17: =M17+N17+O17 -> 1530.75 | Q17: =P17/(1+Hypothèses!$B$6) -> 1275.625 | R17: =Hypothèses!$B$3*(1+Hypothèses!$B$4)^INT((A17-1)/3) -> 874.50312 | S17: =0 -> 0 | T17: =S17*Hypothèses!$B$17 -> 0 | U17: =Q17*Hypothèses!$B$5 -> 12.75625 | V17: =Q17-R17-T17-U17 -> 388.36563 | W17: =W16+V17 -> 1010.2228
A18: 15 | B18: =INT((A18-1)/12)+1 -> 2 | C18: =ROUND(IF(MOD($A18,12)=0,G18,(IF(18=4,0,C17))*(1-$K18)+IF((IF(18=4,0,C17))*(1-$K18)<G18,(G18-(IF(18=4,0,C17))*(1-$K18))*Hypothèses!$B$10,0)),1) -> 3.9 | D18: =ROUND(IF(MOD($A18,12)=0,H18,(IF(18=4,0,D17))*(1-$K18)+IF((IF(18=4,0,D17))*(1-$K18)<H18,(H18-(IF(18=4,0,D17))*(1-$K18))*Hypothèses!$B$10,0)),1) -> 9.4 | E18: =ROUND(IF(MOD($A18,12)=0,I18,(IF(18=4,0,E17))*(1-$K18)+IF((IF(18=4,0,E17))*(1-$K18)<I18,(I18-(IF(18=4,0,E17))*(1-$K18))*Hypothèses!$B$10,0)),1) -> 0.1 | F18: =ROUND(IF(MOD($A18,12)=0,J18,(IF(18=4,0,F17))*(1-$K18)+IF((IF(18=4,0,F17))*(1-$K18)<J18,(J18-(IF(18=4,0,F17))*(1-$K18))*Hypothèses!$B$10,0)),1) -> 0.1 | G18: =(IF(B18=1,0,IF(B18=2,Hypothèses!$B$26,IF(B18=3,Hypothèses!$C$26,Hypothèses!$D$26)))+(IF(B18=1,Hypothèses!$B$26,IF(B18=2,Hypothèses!$C$26,IF(B18=3,Hypothèses!$D$26,Hypothèses!$D$26)))-(IF(B18=1,0,IF(B18=2,Hypothèses!$B$26,IF(B18=3,Hypothèses!$C$26,Hypothèses!$D$26)))))*((A18)-INT((A18-1)/12)*12)/12)*$B$1 -> 4.375 | H18: =(IF(B18=1,0,IF(B18=2,Hypothèses!$B$27,IF(B18=3,Hypothèses!$C$27,Hypothèses!$D$27)))+(IF(B18=1,Hypothèses!$B$27,IF(B18=2,Hypothèses!$C$27,IF(B18=3,Hypothèses!$D$27,Hypothèses!$D$27)))-(IF(B18=1,0,IF(B18=2,Hypothèses!$B$27,IF(B18=3,Hypothèses!$C$27,Hypothèses!$D$27)))))*((A18)-INT((A18-1)/12)*12)/12)*$B$1 -> 11.375 | I18: =(IF(B18=1,0,IF(B18=2,Hypothèses!$B$28,IF(B18=3,Hypothèses!$C$28,Hypothèses!$D$28)))+(IF(B18=1,Hypothèses!$B$28,IF(B18=2,Hypothèses!$C$28,IF(B18=3,Hypothèses!$D$28,Hypothèses!$D$28)))-(IF(B18=1,0,IF(B18=2,Hypothèses!$B$28,IF(B18=3,Hypothèses!$C$28,Hypothèses!$D$28)))))*((A18)-INT((A18-1)/12)*12)/12)*$B$1 -> 0.175 | J18: =(IF(B18=1,0,IF(B18=2,Hypothèses!$B$29,IF(B18=3,Hypothèses!$C$29,Hypothèses!$D$29)))+(IF(B18=1,Hypothèses!$B$29,IF(B18=2,Hypothèses!$C$29,IF(B18=3,Hypothèses!$D$29,Hypothèses!$D$29)))-(IF(B18=1,0,IF(B18=2,Hypothèses!$B$29,IF(B18=3,Hypothèses!$C$29,Hypothèses!$D$29)))))*((A18)-INT((A18-1)/12)*12)/12)*$B$1 -> 0.175 | K18: =IF(A18<Hypothèses!$B$7,0,Hypothèses!$B$8*(1-Hypothèses!$B$9)^(A18-Hypothèses!$B$7)) -> 0.02657205 | L18: =C18+D18+E18+F18 -> 13.5 | M18: =(C18*Hypothèses!$B$11+D18*Hypothèses!$B$12+E18*Hypothèses!$B$13+F18*Hypothèses!$B$14)*(IF(B18=1,Hypothèses!$B$20,IF(B18=2,Hypothèses!$B$21,Hypothèses!$B$22))+(1-(IF(B18=1,Hypothèses!$B$20,IF(B18=2,Hypothèses!$B$21,Hypothèses!$B$22))))*11/12) -> 1817.575 | N18: =L18*IF(B18=1,Hypothèses!$C$20,IF(B18=2,Hypothèses!$C$21,Hypothèses!$C$22))*IF(B18=1,Hypothèses!$D$20,IF(B18=2,Hypothèses!$D$21,Hypothèses!$D$22)) -> 33.75 | O18: =IF(A18=18,IF($B$2>=1,Hypothèses!$B$33,0),IF(AND(OR(A18=30,A18=34),$D$2>=1),Hypothèses!$B$34*MIN(1,$D$2/3),0)) -> 0 | P18: =M18+N18+O18 -> 1851.325 | Q18: =P18/(1+Hypothèses!$B$6) -> 1542.7708 | R18: =Hypothèses!$B$3*(1+Hypothèses!$B$4)^INT((A18-1)/3) -> 874.50312 | S18: =0 -> 0 | T18: =S18*Hypothèses!$B$17 -> 0 | U18: =Q18*Hypothèses!$B$5 -> 15.427708 | V18: =Q18-R18-T18-U18 -> 652.84 | W18: =W17+V18 -> 1663.0628
A19: 16 | B19: =INT((A19-1)/12)+1 -> 2 | C19: =ROUND(IF(MOD($A19,12)=0,G19,(IF(19=4,0,C18))*(1-$K19)+IF((IF(19=4,0,C18))*(1-$K19)<G19,(G19-(IF(19=4,0,C18))*(1-$K19))*Hypothèses!$B$10,0)),1) -> 4.2 | D19: =ROUND(IF(MOD($A19,12)=0,H19,(IF(19=4,0,D18))*(1-$K19)+IF((IF(19=4,0,D18))*(1-$K19)<H19,(H19-(IF(19=4,0,D18))*(1-$K19))*Hypothèses!$B$10,0)),1) -> 10.6 | E19: =ROUND(IF(MOD($A19,12)=0,I19,(IF(19=4,0,E18))*(1-$K19)+IF((IF(19=4,0,E18))*(1-$K19)<I19,(I19-(IF(19=4,0,E18))*(1-$K19))*Hypothèses!$B$10,0)),1) -> 0.2 | F19: =ROUND(IF(MOD($A19,12)=0,J19,(IF(19=4,0,F18))*(1-$K19)+IF((IF(19=4,0,F18))*(1-$K19)<J19,(J19-(IF(19=4,0,F18))*(1-$K19))*Hypothèses!$B$10,0)),1) -> 0.2 | G19: =(IF(B19=1,0,IF(B19=2,Hypothèses!$B$26,IF(B19=3,Hypothèses!$C$26,Hypothèses!$D$26)))+(IF(B19=1,Hypothèses!$B$26,IF(B19=2,Hypothèses!$C$26,IF(B19=3,Hypothèses!$D$26,Hypothèses!$D$26)))-(IF(B19=1,0,IF(B19=2,Hypothèses!$B$26,IF(B19=3,Hypothèses!$C$26,Hypothèses!$D$26)))))*((A19)-INT((A19-1)/12)*12)/12)*$B$1 -> 4.6666667 | H19: =(IF(B19=1,0,IF(B19=2,Hypothèses!$B$27,IF(B19=3,Hypothèses!$C$27,Hypothèses!$D$27)))+(IF(B19=1,Hypothèses!$B$27,IF(B19=2,Hypothèses!$C$27,IF(B19=3,Hypothèses!$D$27,Hypothèses!$D$27)))-(IF(B19=1,0,IF(B19=2,Hypothèses!$B$27,IF(B19=3,Hypothèses!$C$27,Hypothèses!$D$27)))))*((A19)-INT((A19-1)/12)*12)/12)*$B$1 -> 12.833333 | I19: =(IF(B19=1,0,IF(B19=2,Hypothèses!$B$28,IF(B19=3,Hypothèses!$C$28,Hypothèses!$D$28)))+(IF(B19=1,Hypothèses!$B$28,IF(B19=2,Hypothèses!$C$28,IF(B19=3,Hypothèses!$D$28,Hypothèses!$D$28)))-(IF(B19=1,0,IF(B19=2,Hypothèses!$B$28,IF(B19=3,Hypothèses!$C$28,Hypothèses!$D$28)))))*((A19)-INT((A19-1)/12)*12)/12)*$B$1 -> 0.23333333 | J19: =(IF(B19=1,0,IF(B19=2,Hypothèses!$B$29,IF(B19=3,Hypothèses!$C$29,Hypothèses!$D$29)))+(IF(B19=1,Hypothèses!$B$29,IF(B19=2,Hypothèses!$C$29,IF(B19=3,Hypothèses!$D$29,Hypothèses!$D$29)))-(IF(B19=1,0,IF(B19=2,Hypothèses!$B$29,IF(B19=3,Hypothèses!$C$29,Hypothèses!$D$29)))))*((A19)-INT((A19-1)/12)*12)/12)*$B$1 -> 0.23333333 | K19: =IF(A19<Hypothèses!$B$7,0,Hypothèses!$B$8*(1-Hypothèses!$B$9)^(A19-Hypothèses!$B$7)) -> 0.023914845 | L19: =C19+D19+E19+F19 -> 15.2 | M19: =(C19*Hypothèses!$B$11+D19*Hypothèses!$B$12+E19*Hypothèses!$B$13+F19*Hypothèses!$B$14)*(IF(B19=1,Hypothèses!$B$20,IF(B19=2,Hypothèses!$B$21,Hypothèses!$B$22))+(1-(IF(B19=1,Hypothèses!$B$20,IF(B19=2,Hypothèses!$B$21,Hypothèses!$B$22))))*11/12) -> 2157.2083 | N19: =L19*IF(B19=1,Hypothèses!$C$20,IF(B19=2,Hypothèses!$C$21,Hypothèses!$C$22))*IF(B19=1,Hypothèses!$D$20,IF(B19=2,Hypothèses!$D$21,Hypothèses!$D$22)) -> 38 | O19: =IF(A19=18,IF($B$2>=1,Hypothèses!$B$33,0),IF(AND(OR(A19=30,A19=34),$D$2>=1),Hypothèses!$B$34*MIN(1,$D$2/3),0)) -> 0 | P19: =M19+N19+O19 -> 2195.2083 | Q19: =P19/(1+Hypothèses!$B$6) -> 1829.3403 | R19: =Hypothèses!$B$3*(1+Hypothèses!$B$4)^INT((A19-1)/3) -> 1005.6786 | S19: =0 -> 0 | T19: =S19*Hypothèses!$B$17 -> 0 | U19: =Q19*Hypothèses!$B$5 -> 18.293403 | V19: =Q19-R19-T19-U19 -> 805.36828 | W19: =W18+V19 -> 2468.4311
A20: 17 | B20: =INT((A20-1)/12)+1 -> 2 | C20: =ROUND(IF(MOD($A20,12)=0,G20,(IF(20=4,0,C19))*(1-$K20)+IF((IF(20=4,0,C19))*(1-$K20)<G20,(G20-(IF(20=4,0,C19))*(1-$K20))*Hypothèses!$B$10,0)),1) -> 4.4 | D20: =ROUND(IF(MOD($A20,12)=0,H20,(IF(20=4,0,D19))*(1-$K20)+IF((IF(20=4,0,D19))*(1-$K20)<H20,(H20-(IF(20=4,0,D19))*(1-$K20))*Hypothèses!$B$10,0)),1) -> 11.9 | E20: =ROUND(IF(MOD($A20,12)=0,I20,(IF(20=4,0,E19))*(1-$K20)+IF((IF(20=4,0,E19))*(1-$K20)<I20,(I20-(IF(20=4,0,E19))*(1-$K20))*Hypothèses!$B$10,0)),1) -> 0.2 | F20: =ROUND(IF(MOD($A20,12)=0,J20,(IF(20=4,0,F19))*(1-$K20)+IF((IF(20=4,0,F19))*(1-$K20)<J20,(J20-(IF(20=4,0,F19))*(1-$K20))*Hypothèses!$B$10,0)),1) -> 0.2 | G20: =(IF(B20=1,0,IF(B20=2,Hypothèses!$B$26,IF(B20=3,Hypothèses!$C$26,Hypothèses!$D$26)))+(IF(B20=1,Hypothèses!$B$26,IF(B20=2,Hypothèses!$C$26,IF(B20=3,Hypothèses!$D$26,Hypothèses!$D$26)))-(IF(B20=1,0,IF(B20=2,Hypothèses!$B$26,IF(B20=3,Hypothèses!$C$26,Hypothèses!$D$26)))))*((A20)-INT((A20-1)/12)*12)/12)*$B$1 -> 4.9583333 | H20: =(IF(B20=1,0,IF(B20=2,Hypothèses!$B$27,IF(B20=3,Hypothèses!$C$27,Hypothèses!$D$27)))+(IF(B20=1,Hypothèses!$B$27,IF(B20=2,Hypothèses!$C$27,IF(B20=3,Hypothèses!$D$27,Hypothèses!$D$27)))-(IF(B20=1,0,IF(B20=2,Hypothèses!$B$27,IF(B20=3,Hypothèses!$C$27,Hypothèses!$D$27)))))*((A20)-INT((A20-1)/12)*12)/12)*$B$1 -> 14.291667 | I20: =(IF(B20=1,0,IF(B20=2,Hypothèses!$B$28,IF(B20=3,Hypothèses!$C$28,Hypothèses!$D$28)))+(IF(B20=1,Hypothèses!$B$28,IF(B20=2,Hypothèses!$C$28,IF(B20=3,Hypothèses!$D$28,Hypothèses!$D$28)))-(IF(B20=1,0,IF(B20=2,Hypothèses!$B$28,IF(B20=3,Hypothèses!$C$28,Hypothèses!$D$28)))))*((A20)-INT((A20-1)/12)*12)/12)*$B$1 -> 0.29166667 | J20: =(IF(B20=1,0,IF(B20=2,Hypothèses!$B$29,IF(B20=3,Hypothèses!$C$29,Hypothèses!$D$29)))+(IF(B20=1,Hypothèses!$B$29,IF(B20=2,Hypothèses!$C$29,IF(B20=3,Hypothèses!$D$29,Hypothèses!$D$29)))-(IF(B20=1,0,IF(B20=2,Hypothèses!$B$29,IF(B20=3,Hypothèses!$C$29,Hypothèses!$D$29)))))*((A20)-INT((A20-1)/12)*12)/12)*$B$1 -> 0.29166667 | K20: =IF(A20<Hypothèses!$B$7,0,Hypothèses!$B$8*(1-Hypothèses!$B$9)^(A20-Hypothèses!$B$7)) -> 0.021523361 | L20: =C20+D20+E20+F20 -> 16.7 | M20: =(C20*Hypothèses!$B$11+D20*Hypothèses!$B$12+E20*Hypothèses!$B$13+F20*Hypothèses!$B$14)*(IF(B20=1,Hypothèses!$B$20,IF(B20=2,Hypothèses!$B$21,Hypothèses!$B$22))+(1-(IF(B20=1,Hypothèses!$B$20,IF(B20=2,Hypothèses!$B$21,Hypothèses!$B$22))))*11/12) -> 2359.8958 | N20: =L20*IF(B20=1,Hypothèses!$C$20,IF(B20=2,Hypothèses!$C$21,Hypothèses!$C$22))*IF(B20=1,Hypothèses!$D$20,IF(B20=2,Hypothèses!$D$21,Hypothèses!$D$22)) -> 41.75 | O20: =IF(A20=18,IF($B$2>=1,Hypothèses!$B$33,0),IF(AND(OR(A20=30,A20=34),$D$2>=1),Hypothèses!$B$34*MIN(1,$D$2/3),0)) -> 0 | P20: =M20+N20+O20 -> 2401.6458 | Q20: =P20/(1+Hypothèses!$B$6) -> 2001.3715 | R20: =Hypothèses!$B$3*(1+Hypothèses!$B$4)^INT((A20-1)/3) -> 1005.6786 | S20: =0 -> 0 | T20: =S20*Hypothèses!$B$17 -> 0 | U20: =Q20*Hypothèses!$B$5 -> 20.013715 | V20: =Q20-R20-T20-U20 -> 975.67922 | W20: =W19+V20 -> 3444.1103
A21: 18 | B21: =INT((A21-1)/12)+1 -> 2 | C21: =ROUND(IF(MOD($A21,12)=0,G21,(IF(21=4,0,C20))*(1-$K21)+IF((IF(21=4,0,C20))*(1-$K21)<G21,(G21-(IF(21=4,0,C20))*(1-$K21))*Hypothèses!$B$10,0)),1) -> 4.7 | D21: =ROUND(IF(MOD($A21,12)=0,H21,(IF(21=4,0,D20))*(1-$K21)+IF((IF(21=4,0,D20))*(1-$K21)<H21,(H21-(IF(21=4,0,D20))*(1-$K21))*Hypothèses!$B$10,0)),1) -> 13.3 | E21: =ROUND(IF(MOD($A21,12)=0,I21,(IF(21=4,0,E20))*(1-$K21)+IF((IF(21=4,0,E20))*(1-$K21)<I21,(I21-(IF(21=4,0,E20))*(1-$K21))*Hypothèses!$B$10,0)),1) -> 0.3 | F21: =ROUND(IF(MOD($A21,12)=0,J21,(IF(21=4,0,F20))*(1-$K21)+IF((IF(21=4,0,F20))*(1-$K21)<J21,(J21-(IF(21=4,0,F20))*(1-$K21))*Hypothèses!$B$10,0)),1) -> 0.3 | G21: =(IF(B21=1,0,IF(B21=2,Hypothèses!$B$26,IF(B21=3,Hypothèses!$C$26,Hypothèses!$D$26)))+(IF(B21=1,Hypothèses!$B$26,IF(B21=2,Hypothèses!$C$26,IF(B21=3,Hypothèses!$D$26,Hypothèses!$D$26)))-(IF(B21=1,0,IF(B21=2,Hypothèses!$B$26,IF(B21=3,Hypothèses!$C$26,Hypothèses!$D$26)))))*((A21)-INT((A21-1)/12)*12)/12)*$B$1 -> 5.25 | H21: =(IF(B21=1,0,IF(B21=2,Hypothèses!$B$27,IF(B21=3,Hypothèses!$C$27,Hypothèses!$D$27)))+(IF(B21=1,Hypothèses!$B$27,IF(B21=2,Hypothèses!$C$27,IF(B21=3,Hypothèses!$D$27,Hypothèses!$D$27)))-(IF(B21=1,0,IF(B21=2,Hypothèses!$B$27,IF(B21=3,Hypothèses!$C$27,Hypothèses!$D$27)))))*((A21)-INT((A21-1)/12)*12)/12)*$B$1 -> 15.75 | I21: =(IF(B21=1,0,IF(B21=2,Hypothèses!$B$28,IF(B21=3,Hypothèses!$C$28,Hypothèses!$D$28)))+(IF(B21=1,Hypothèses!$B$28,IF(B21=2,Hypothèses!$C$28,IF(B21=3,Hypothèses!$D$28,Hypothèses!$D$28)))-(IF(B21=1,0,IF(B21=2,Hypothèses!$B$28,IF(B21=3,Hypothèses!$C$28,Hypothèses!$D$28)))))*((A21)-INT((A21-1)/12)*12)/12)*$B$1 -> 0.35 | J21: =(IF(B21=1,0,IF(B21=2,Hypothèses!$B$29,IF(B21=3,Hypothèses!$C$29,Hypothèses!$D$29)))+(IF(B21=1,Hypothèses!$B$29,IF(B21=2,Hypothèses!$C$29,IF(B21=3,Hypothèses!$D$29,Hypothèses!$D$29)))-(IF(B21=1,0,IF(B21=2,Hypothèses!$B$29,IF(B21=3,Hypothèses!$C$29,Hypothèses!$D$29)))))*((A21)-INT((A21-1)/12)*12)/12)*$B$1 -> 0.35 | K21: =IF(A21<Hypothèses!$B$7,0,Hypothèses!$B$8*(1-Hypothèses!$B$9)^(A21-Hypothèses!$B$7)) -> 0.019371024 | L21: =C21+D21+E21+F21 -> 18.6 | M21: =(C21*Hypothèses!$B$11+D21*Hypothèses!$B$12+E21*Hypothèses!$B$13+F21*Hypothèses!$B$14)*(IF(B21=1,Hypothèses!$B$20,IF(B21=2,Hypothèses!$B$21,Hypothèses!$B$22))+(1-(IF(B21=1,Hypothèses!$B$20,IF(B21=2,Hypothèses!$B$21,Hypothèses!$B$22))))*11/12) -> 2728.0875 | N21: =L21*IF(B21=1,Hypothèses!$C$20,IF(B21=2,Hypothèses!$C$21,Hypothèses!$C$22))*IF(B21=1,Hypothèses!$D$20,IF(B21=2,Hypothèses!$D$21,Hypothèses!$D$22)) -> 46.5 | O21: =IF(A21=18,IF($B$2>=1,Hypothèses!$B$33,0),IF(AND(OR(A21=30,A21=34),$D$2>=1),Hypothèses!$B$34*MIN(1,$D$2/3),0)) -> 15000 | P21: =M21+N21+O21 -> 17774.588 | Q21: =P21/(1+Hypothèses!$B$6) -> 14812.156 | R21: =Hypothèses!$B$3*(1+Hypothèses!$B$4)^INT((A21-1)/3) -> 1005.6786 | S21: =0 -> 0 | T21: =S21*Hypothèses!$B$17 -> 0 | U21: =Q21*Hypothèses!$B$5 -> 148.12156 | V21: =Q21-R21-T21-U21 -> 13658.356 | W21: =W20+V21 -> 17102.466
A22: 19 | B22: =INT((A22-1)/12)+1 -> 2 | C22: =ROUND(IF(MOD($A22,12)=0,G22,(IF(22=4,0,C21))*(1-$K22)+IF((IF(22=4,0,C21))*(1-$K22)<G22,(G22-(IF(22=4,0,C21))*(1-$K22))*Hypothèses!$B$10,0)),1) -> 5 | D22: =ROUND(IF(MOD($A22,12)=0,H22,(IF(22=4,0,D21))*(1-$K22)+IF((IF(22=4,0,D21))*(1-$K22)<H22,(H22-(IF(22=4,0,D21))*(1-$K22))*Hypothèses!$B$10,0)),1) -> 14.7 | E22: =ROUND(IF(MOD($A22,12)=0,I22,(IF(22=4,0,E21))*(1-$K22)+IF((IF(22=4,0,E21))*(1-$K22)<I22,(I22-(IF(22=4,0,E21))*(1-$K22))*Hypothèses!$B$10,0)),1) -> 0.3 | F22: =ROUND(IF(MOD($A22,12)=0,J22,(IF(22=4,0,F21))*(1-$K22)+IF((IF(22=4,0,F21))*(1-$K22)<J22,(J22-(IF(22=4,0,F21))*(1-$K22))*Hypothèses!$B$10,0)),1) -> 0.3 | G22: =(IF(B22=1,0,IF(B22=2,Hypothèses!$B$26,IF(B22=3,Hypothèses!$C$26,Hypothèses!$D$26)))+(IF(B22=1,Hypothèses!$B$26,IF(B22=2,Hypothèses!$C$26,IF(B22=3,Hypothèses!$D$26,Hypothèses!$D$26)))-(IF(B22=1,0,IF(B22=2,Hypothèses!$B$26,IF(B22=3,Hypothèses!$C$26,Hypothèses!$D$26)))))*((A22)-INT((A22-1)/12)*12)/12)*$B$1 -> 5.5416667 | H22: =(IF(B22=1,0,IF(B22=2,Hypothèses!$B$27,IF(B22=3,Hypothèses!$C$27,Hypothèses!$D$27)))+(IF(B22=1,Hypothèses!$B$27,IF(B22=2,Hypothèses!$C$27,IF(B22=3,Hypothèses!$D$27,Hypothèses!$D$27)))-(IF(B22=1,0,IF(B22=2,Hypothèses!$B$27,IF(B22=3,Hypothèses!$C$27,Hypothèses!$D$27)))))*((A22)-INT((A22-1)/12)*12)/12)*$B$1 -> 17.208333 | I22: =(IF(B22=1,0,IF(B22=2,Hypothèses!$B$28,IF(B22=3,Hypothèses!$C$28,Hypothèses!$D$28)))+(IF(B22=1,Hypothèses!$B$28,IF(B22=2,Hypothèses!$C$28,IF(B22=3,Hypothèses!$D$28,Hypothèses!$D$28)))-(IF(B22=1,0,IF(B22=2,Hypothèses!$B$28,IF(B22=3,Hypothèses!$C$28,Hypothèses!$D$28)))))*((A22)-INT((A22-1)/12)*12)/12)*$B$1 -> 0.40833333 | J22: =(IF(B22=1,0,IF(B22=2,Hypothèses!$B$29,IF(B22=3,Hypothèses!$C$29,Hypothèses!$D$29)))+(IF(B22=1,Hypothèses!$B$29,IF(B22=2,Hypothèses!$C$29,IF(B22=3,Hypothèses!$D$29,Hypothèses!$D$29)))-(IF(B22=1,0,IF(B22=2,Hypothèses!$B$29,IF(B22=3,Hypothèses!$C$29,Hypothèses!$D$29)))))*((A22)-INT((A22-1)/12)*12)/12)*$B$1 -> 0.40833333 | K22: =IF(A22<Hypothèses!$B$7,0,Hypothèses!$B$8*(1-Hypothèses!$B$9)^(A22-Hypothèses!$B$7)) -> 0.017433922 | L22: =C22+D22+E22+F22 -> 20.3 | M22: =(C22*Hypothèses!$B$11+D22*Hypothèses!$B$12+E22*Hypothèses!$B$13+F22*Hypothèses!$B$14)*(IF(B22=1,Hypothèses!$B$20,IF(B22=2,Hypothèses!$B$21,Hypothèses!$B$22))+(1-(IF(B22=1,Hypothèses!$B$20,IF(B22=2,Hypothèses!$B$21,Hypothèses!$B$22))))*11/12) -> 2953.5833 | N22: =L22*IF(B22=1,Hypothèses!$C$20,IF(B22=2,Hypothèses!$C$21,Hypothèses!$C$22))*IF(B22=1,Hypothèses!$D$20,IF(B22=2,Hypothèses!$D$21,Hypothèses!$D$22)) -> 50.75 | O22: =IF(A22=18,IF($B$2>=1,Hypothèses!$B$33,0),IF(AND(OR(A22=30,A22=34),$D$2>=1),Hypothèses!$B$34*MIN(1,$D$2/3),0)) -> 0 | P22: =M22+N22+O22 -> 3004.3333 | Q22: =P22/(1+Hypothèses!$B$6) -> 2503.6111 | R22: =Hypothèses!$B$3*(1+Hypothèses!$B$4)^INT((A22-1)/3) -> 1156.5304 | S22: =0 -> 0 | T22: =S22*Hypothèses!$B$17 -> 0 | U22: =Q22*Hypothèses!$B$5 -> 25.036111 | V22: =Q22-R22-T22-U22 -> 1322.0446 | W22: =W21+V22 -> 18424.511
A23: 20 | B23: =INT((A23-1)/12)+1 -> 2 | C23: =ROUND(IF(MOD($A23,12)=0,G23,(IF(23=4,0,C22))*(1-$K23)+IF((IF(23=4,0,C22))*(1-$K23)<G23,(G23-(IF(23=4,0,C22))*(1-$K23))*Hypothèses!$B$10,0)),1) -> 5.3 | D23: =ROUND(IF(MOD($A23,12)=0,H23,(IF(23=4,0,D22))*(1-$K23)+IF((IF(23=4,0,D22))*(1-$K23)<H23,(H23-(IF(23=4,0,D22))*(1-$K23))*Hypothèses!$B$10,0)),1) -> 16.1 | E23: =ROUND(IF(MOD($A23,12)=0,I23,(IF(23=4,0,E22))*(1-$K23)+IF((IF(23=4,0,E22))*(1-$K23)<I23,(I23-(IF(23=4,0,E22))*(1-$K23))*Hypothèses!$B$10,0)),1) -> 0.4 | F23: =ROUND(IF(MOD($A23,12)=0,J23,(IF(23=4,0,F22))*(1-$K23)+IF((IF(23=4,0,F22))*(1-$K23)<J23,(J23-(IF(23=4,0,F22))*(1-$K23))*Hypothèses!$B$10,0)),1) -> 0.4 | G23: =(IF(B23=1,0,IF(B23=2,Hypothèses!$B$26,IF(B23=3,Hypothèses!$C$26,Hypothèses!$D$26)))+(IF(B23=1,Hypothèses!$B$26,IF(B23=2,Hypothèses!$C$26,IF(B23=3,Hypothèses!$D$26,Hypothèses!$D$26)))-(IF(B23=1,0,IF(B23=2,Hypothèses!$B$26,IF(B23=3,Hypothèses!$C$26,Hypothèses!$D$26)))))*((A23)-INT((A23-1)/12)*12)/12)*$B$1 -> 5.8333333 | H23: =(IF(B23=1,0,IF(B23=2,Hypothèses!$B$27,IF(B23=3,Hypothèses!$C$27,Hypothèses!$D$27)))+(IF(B23=1,Hypothèses!$B$27,IF(B23=2,Hypothèses!$C$27,IF(B23=3,Hypothèses!$D$27,Hypothèses!$D$27)))-(IF(B23=1,0,IF(B23=2,Hypothèses!$B$27,IF(B23=3,Hypothèses!$C$27,Hypothèses!$D$27)))))*((A23)-INT((A23-1)/12)*12)/12)*$B$1 -> 18.666667 | I23: =(IF(B23=1,0,IF(B23=2,Hypothèses!$B$28,IF(B23=3,Hypothèses!$C$28,Hypothèses!$D$28)))+(IF(B23=1,Hypothèses!$B$28,IF(B23=2,Hypothèses!$C$28,IF(B23=3,Hypothèses!$D$28,Hypothèses!$D$28)))-(IF(B23=1,0,IF(B23=2,Hypothèses!$B$28,IF(B23=3,Hypothèses!$C$28,Hypothèses!$D$28)))))*((A23)-INT((A23-1)/12)*12)/12)*$B$1 -> 0.46666667 | J23: =(IF(B23=1,0,IF(B23=2,Hypothèses!$B$29,IF(B23=3,Hypothèses!$C$29,Hypothèses!$D$29)))+(IF(B23=1,Hypothèses!$B$29,IF(B23=2,Hypothèses!$C$29,IF(B23=3,Hypothèses!$D$29,Hypothèses!$D$29)))-(IF(B23=1,0,IF(B23=2,Hypothèses!$B$29,IF(B23=3,Hypothèses!$C$29,Hypothèses!$D$29)))))*((A23)-INT((A23-1)/12)*12)/12)*$B$1 -> 0.46666667 | K23: =IF(A23<Hypothèses!$B$7,0,Hypothèses!$B$8*(1-Hypothèses!$B$9)^(A23-Hypothèses!$B$7)) -> 0.01569053 | L23: =C23+D23+E23+F23 -> 22.2 | M23: =(C23*Hypothèses!$B$11+D23*Hypothèses!$B$12+E23*Hypothèses!$B$13+F23*Hypothèses!$B$14)*(IF(B23=1,Hypothèses!$B$20,IF(B23=2,Hypothèses!$B$21,Hypothèses!$B$22))+(1-(IF(B23=1,Hypothèses!$B$20,IF(B23=2,Hypothèses!$B$21,Hypothèses!$B$22))))*11/12) -> 3321.775 | N23: =L23*IF(B23=1,Hypothèses!$C$20,IF(B23=2,Hypothèses!$C$21,Hypothèses!$C$22))*IF(B23=1,Hypothèses!$D$20,IF(B23=2,Hypothèses!$D$21,Hypothèses!$D$22)) -> 55.5 | O23: =IF(A23=18,IF($B$2>=1,Hypothèses!$B$33,0),IF(AND(OR(A23=30,A23=34),$D$2>=1),Hypothèses!$B$34*MIN(1,$D$2/3),0)) -> 0 | P23: =M23+N23+O23 -> 3377.275 | Q23: =P23/(1+Hypothèses!$B$6) -> 2814.3958 | R23: =Hypothèses!$B$3*(1+Hypothèses!$B$4)^INT((A23-1)/3) -> 1156.5304 | S23: =0 -> 0 | T23: =S23*Hypothèses!$B$17 -> 0 | U23: =Q23*Hypothèses!$B$5 -> 28.143958 | V23: =Q23-R23-T23-U23 -> 1629.7215 | W23: =W22+V23 -> 20054.233
A24: 21 | B24: =INT((A24-1)/12)+1 -> 2 | C24: =ROUND(IF(MOD($A24,12)=0,G24,(IF(24=4,0,C23))*(1-$K24)+IF((IF(24=4,0,C23))*(1-$K24)<G24,(G24-(IF(24=4,0,C23))*(1-$K24))*Hypothèses!$B$10,0)),1) -> 5.6 | D24: =ROUND(IF(MOD($A24,12)=0,H24,(IF(24=4,0,D23))*(1-$K24)+IF((IF(24=4,0,D23))*(1-$K24)<H24,(H24-(IF(24=4,0,D23))*(1-$K24))*Hypothèses!$B$10,0)),1) -> 17.6 | E24: =ROUND(IF(MOD($A24,12)=0,I24,(IF(24=4,0,E23))*(1-$K24)+IF((IF(24=4,0,E23))*(1-$K24)<I24,(I24-(IF(24=4,0,E23))*(1-$K24))*Hypothèses!$B$10,0)),1) -> 0.4 | F24: =ROUND(IF(MOD($A24,12)=0,J24,(IF(24=4,0,F23))*(1-$K24)+IF((IF(24=4,0,F23))*(1-$K24)<J24,(J24-(IF(24=4,0,F23))*(1-$K24))*Hypothèses!$B$10,0)),1) -> 0.4 | G24: =(IF(B24=1,0,IF(B24=2,Hypothèses!$B$26,IF(B24=3,Hypothèses!$C$26,Hypothèses!$D$26)))+(IF(B24=1,Hypothèses!$B$26,IF(B24=2,Hypothèses!$C$26,IF(B24=3,Hypothèses!$D$26,Hypothèses!$D$26)))-(IF(B24=1,0,IF(B24=2,Hypothèses!$B$26,IF(B24=3,Hypothèses!$C$26,Hypothèses!$D$26)))))*((A24)-INT((A24-1)/12)*12)/12)*$B$1 -> 6.125 | H24: =(IF(B24=1,0,IF(B24=2,Hypothèses!$B$27,IF(B24=3,Hypothèses!$C$27,Hypothèses!$D$27)))+(IF(B24=1,Hypothèses!$B$27,IF(B24=2,Hypothèses!$C$27,IF(B24=3,Hypothèses!$D$27,Hypothèses!$D$27)))-(IF(B24=1,0,IF(B24=2,Hypothèses!$B$27,IF(B24=3,Hypothèses!$C$27,Hypothèses!$D$27)))))*((A24)-INT((A24-1)/12)*12)/12)*$B$1 -> 20.125 | I24: =(IF(B24=1,0,IF(B24=2,Hypothèses!$B$28,IF(B24=3,Hypothèses!$C$28,Hypothèses!$D$28)))+(IF(B24=1,Hypothèses!$B$28,IF(B24=2,Hypothèses!$C$28,IF(B24=3,Hypothèses!$D$28,Hypothèses!$D$28)))-(IF(B24=1,0,IF(B24=2,Hypothèses!$B$28,IF(B24=3,Hypothèses!$C$28,Hypothèses!$D$28)))))*((A24)-INT((A24-1)/12)*12)/12)*$B$1 -> 0.525 | J24: =(IF(B24=1,0,IF(B24=2,Hypothèses!$B$29,IF(B24=3,Hypothèses!$C$29,Hypothèses!$D$29)))+(IF(B24=1,Hypothèses!$B$29,IF(B24=2,Hypothèses!$C$29,IF(B24=3,Hypothèses!$D$29,Hypothèses!$D$29)))-(IF(B24=1,0,IF(B24=2,Hypothèses!$B$29,IF(B24=3,Hypothèses!$C$29,Hypothèses!$D$29)))))*((A24)-INT((A24-1)/12)*12)/12)*$B$1 -> 0.525 | K24: =IF(A24<Hypothèses!$B$7,0,Hypothèses!$B$8*(1-Hypothèses!$B$9)^(A24-Hypothèses!$B$7)) -> 0.014121477 | L24: =C24+D24+E24+F24 -> 24 | M24: =(C24*Hypothèses!$B$11+D24*Hypothèses!$B$12+E24*Hypothèses!$B$13+F24*Hypothèses!$B$14)*(IF(B24=1,Hypothèses!$B$20,IF(B24=2,Hypothèses!$B$21,Hypothèses!$B$22))+(1-(IF(B24=1,Hypothèses!$B$20,IF(B24=2,Hypothèses!$B$21,Hypothèses!$B$22))))*11/12) -> 3561.55 | N24: =L24*IF(B24=1,Hypothèses!$C$20,IF(B24=2,Hypothèses!$C$21,Hypothèses!$C$22))*IF(B24=1,Hypothèses!$D$20,IF(B24=2,Hypothèses!$D$21,Hypothèses!$D$22)) -> 60 | O24: =IF(A24=18,IF($B$2>=1,Hypothèses!$B$33,0),IF(AND(OR(A24=30,A24=34),$D$2>=1),Hypothèses!$B$34*MIN(1,$D$2/3),0)) -> 0 | P24: =M24+N24+O24 -> 3621.55 | Q24: =P24/(1+Hypothèses!$B$6) -> 3017.9583 | R24: =Hypothèses!$B$3*(1+Hypothèses!$B$4)^INT((A24-1)/3) -> 1156.5304 | S24: =0 -> 0 | T24: =S24*Hypothèses!$B$17 -> 0 | U24: =Q24*Hypothèses!$B$5 -> 30.179583 | V24: =Q24-R24-T24-U24 -> 1831.2484 | W24: =W23+V24 -> 21885.481
A25: 22 | B25: =INT((A25-1)/12)+1 -> 2 | C25: =ROUND(IF(MOD($A25,12)=0,G25,(IF(25=4,0,C24))*(1-$K25)+IF((IF(25=4,0,C24))*(1-$K25)<G25,(G25-(IF(25=4,0,C24))*(1-$K25))*Hypothèses!$B$10,0)),1) -> 5.9 | D25: =ROUND(IF(MOD($A25,12)=0,H25,(IF(25=4,0,D24))*(1-$K25)+IF((IF(25=4,0,D24))*(1-$K25)<H25,(H25-(IF(25=4,0,D24))*(1-$K25))*Hypothèses!$B$10,0)),1) -> 19.1 | E25: =ROUND(IF(MOD($A25,12)=0,I25,(IF(25=4,0,E24))*(1-$K25)+IF((IF(25=4,0,E24))*(1-$K25)<I25,(I25-(IF(25=4,0,E24))*(1-$K25))*Hypothèses!$B$10,0)),1) -> 0.5 | F25: =ROUND(IF(MOD($A25,12)=0,J25,(IF(25=4,0,F24))*(1-$K25)+IF((IF(25=4,0,F24))*(1-$K25)<J25,(J25-(IF(25=4,0,F24))*(1-$K25))*Hypothèses!$B$10,0)),1) -> 0.5 | G25: =(IF(B25=1,0,IF(B25=2,Hypothèses!$B$26,IF(B25=3,Hypothèses!$C$26,Hypothèses!$D$26)))+(IF(B25=1,Hypothèses!$B$26,IF(B25=2,Hypothèses!$C$26,IF(B25=3,Hypothèses!$D$26,Hypothèses!$D$26)))-(IF(B25=1,0,IF(B25=2,Hypothèses!$B$26,IF(B25=3,Hypothèses!$C$26,Hypothèses!$D$26)))))*((A25)-INT((A25-1)/12)*12)/12)*$B$1 -> 6.4166667 | H25: =(IF(B25=1,0,IF(B25=2,Hypothèses!$B$27,IF(B25=3,Hypothèses!$C$27,Hypothèses!$D$27)))+(IF(B25=1,Hypothèses!$B$27,IF(B25=2,Hypothèses!$C$27,IF(B25=3,Hypothèses!$D$27,Hypothèses!$D$27)))-(IF(B25=1,0,IF(B25=2,Hypothèses!$B$27,IF(B25=3,Hypothèses!$C$27,Hypothèses!$D$27)))))*((A25)-INT((A25-1)/12)*12)/12)*$B$1 -> 21.583333 | I25: =(IF(B25=1,0,IF(B25=2,Hypothèses!$B$28,IF(B25=3,Hypothèses!$C$28,Hypothèses!$D$28)))+(IF(B25=1,Hypothèses!$B$28,IF(B25=2,Hypothèses!$C$28,IF(B25=3,Hypothèses!$D$28,Hypothèses!$D$28)))-(IF(B25=1,0,IF(B25=2,Hypothèses!$B$28,IF(B25=3,Hypothèses!$C$28,Hypothèses!$D$28)))))*((A25)-INT((A25-1)/12)*12)/12)*$B$1 -> 0.58333333 | J25: =(IF(B25=1,0,IF(B25=2,Hypothèses!$B$29,IF(B25=3,Hypothèses!$C$29,Hypothèses!$D$29)))+(IF(B25=1,Hypothèses!$B$29,IF(B25=2,Hypothèses!$C$29,IF(B25=3,Hypothèses!$D$29,Hypothèses!$D$29)))-(IF(B25=1,0,IF(B25=2,Hypothèses!$B$29,IF(B25=3,Hypothèses!$C$29,Hypothèses!$D$29)))))*((A25)-INT((A25-1)/12)*12)/12)*$B$1 -> 0.58333333 | K25: =IF(A25<Hypothèses!$B$7,0,Hypothèses!$B$8*(1-Hypothèses!$B$9)^(A25-Hypothèses!$B$7)) -> 0.012709329 | L25: =C25+D25+E25+F25 -> 26 | M25: =(C25*Hypothèses!$B$11+D25*Hypothèses!$B$12+E25*Hypothèses!$B$13+F25*Hypothèses!$B$14)*(IF(B25=1,Hypothèses!$B$20,IF(B25=2,Hypothèses!$B$21,Hypothèses!$B$22))+(1-(IF(B25=1,Hypothèses!$B$20,IF(B25=2,Hypothèses!$B$21,Hypothèses!$B$22))))*11/12) -> 3944.0208 | N25: =L25*IF(B25=1,Hypothèses!$C$20,IF(B25=2,Hypothèses!$C$21,Hypothèses!$C$22))*IF(B25=1,Hypothèses!$D$20,IF(B25=2,Hypothèses!$D$21,Hypothèses!$D$22)) -> 65 | O25: =IF(A25=18,IF($B$2>=1,Hypothèses!$B$33,0),IF(AND(OR(A25=30,A25=34),$D$2>=1),Hypothèses!$B$34*MIN(1,$D$2/3),0)) -> 0 | P25: =M25+N25+O25 -> 4009.0208 | Q25: =P25/(1+Hypothèses!$B$6) -> 3340.8507 | R25: =Hypothèses!$B$3*(1+Hypothèses!$B$4)^INT((A25-1)/3) -> 1330.0099 | S25: =0 -> 0 | T25: =S25*Hypothèses!$B$17 -> 0 | U25: =Q25*Hypothèses!$B$5 -> 33.408507 | V25: =Q25-R25-T25-U25 -> 1977.4322 | W25: =W24+V25 -> 23862.913
A26: 23 | B26: =INT((A26-1)/12)+1 -> 2 | C26: =ROUND(IF(MOD($A26,12)=0,G26,(IF(26=4,0,C25))*(1-$K26)+IF((IF(26=4,0,C25))*(1-$K26)<G26,(G26-(IF(26=4,0,C25))*(1-$K26))*Hypothèses!$B$10,0)),1) -> 6.2 | D26: =ROUND(IF(MOD($A26,12)=0,H26,(IF(26=4,0,D25))*(1-$K26)+IF((IF(26=4,0,D25))*(1-$K26)<H26,(H26-(IF(26=4,0,D25))*(1-$K26))*Hypothèses!$B$10,0)),1) -> 20.5 | E26: =ROUND(IF(MOD($A26,12)=0,I26,(IF(26=4,0,E25))*(1-$K26)+IF((IF(26=4,0,E25))*(1-$K26)<I26,(I26-(IF(26=4,0,E25))*(1-$K26))*Hypothèses!$B$10,0)),1) -> 0.6 | F26: =ROUND(IF(MOD($A26,12)=0,J26,(IF(26=4,0,F25))*(1-$K26)+IF((IF(26=4,0,F25))*(1-$K26)<J26,(J26-(IF(26=4,0,F25))*(1-$K26))*Hypothèses!$B$10,0)),1) -> 0.6 | G26: =(IF(B26=1,0,IF(B26=2,Hypothèses!$B$26,IF(B26=3,Hypothèses!$C$26,Hypothèses!$D$26)))+(IF(B26=1,Hypothèses!$B$26,IF(B26=2,Hypothèses!$C$26,IF(B26=3,Hypothèses!$D$26,Hypothèses!$D$26)))-(IF(B26=1,0,IF(B26=2,Hypothèses!$B$26,IF(B26=3,Hypothèses!$C$26,Hypothèses!$D$26)))))*((A26)-INT((A26-1)/12)*12)/12)*$B$1 -> 6.7083333 | H26: =(IF(B26=1,0,IF(B26=2,Hypothèses!$B$27,IF(B26=3,Hypothèses!$C$27,Hypothèses!$D$27)))+(IF(B26=1,Hypothèses!$B$27,IF(B26=2,Hypothèses!$C$27,IF(B26=3,Hypothèses!$D$27,Hypothèses!$D$27)))-(IF(B26=1,0,IF(B26=2,Hypothèses!$B$27,IF(B26=3,Hypothèses!$C$27,Hypothèses!$D$27)))))*((A26)-INT((A26-1)/12)*12)/12)*$B$1 -> 23.041667 | I26: =(IF(B26=1,0,IF(B26=2,Hypothèses!$B$28,IF(B26=3,Hypothèses!$C$28,Hypothèses!$D$28)))+(IF(B26=1,Hypothèses!$B$28,IF(B26=2,Hypothèses!$C$28,IF(B26=3,Hypothèses!$D$28,Hypothèses!$D$28)))-(IF(B26=1,0,IF(B26=2,Hypothèses!$B$28,IF(B26=3,Hypothèses!$C$28,Hypothèses!$D$28)))))*((A26)-INT((A26-1)/12)*12)/12)*$B$1 -> 0.64166667 | J26: =(IF(B26=1,0,IF(B26=2,Hypothèses!$B$29,IF(B26=3,Hypothèses!$C$29,Hypothèses!$D$29)))+(IF(B26=1,Hypothèses!$B$29,IF(B26=2,Hypothèses!$C$29,IF(B26=3,Hypothèses!$D$29,Hypothèses!$D$29)))-(IF(B26=1,0,IF(B26=2,Hypothèses!$B$29,IF(B26=3,Hypothèses!$C$29,Hypothèses!$D$29)))))*((A26)-INT((A26-1)/12)*12)/12)*$B$1 -> 0.64166667 | K26: =IF(A26<Hypothèses!$B$7,0,Hypothèses!$B$8*(1-Hypothèses!$B$9)^(A26-Hypothèses!$B$7)) -> 0.011438396 | L26: =C26+D26+E26+F26 -> 27.9 | M26: =(C26*Hypothèses!$B$11+D26*Hypothèses!$B$12+E26*Hypothèses!$B$13+F26*Hypothèses!$B$14)*(IF(B26=1,Hypothèses!$B$20,IF(B26=2,Hypothèses!$B$21,Hypothèses!$B$22))+(1-(IF(B26=1,Hypothèses!$B$20,IF(B26=2,Hypothèses!$B$21,Hypothèses!$B$22))))*11/12) -> 4312.2125 | N26: =L26*IF(B26=1,Hypothèses!$C$20,IF(B26=2,Hypothèses!$C$21,Hypothèses!$C$22))*IF(B26=1,Hypothèses!$D$20,IF(B26=2,Hypothèses!$D$21,Hypothèses!$D$22)) -> 69.75 | O26: =IF(A26=18,IF($B$2>=1,Hypothèses!$B$33,0),IF(AND(OR(A26=30,A26=34),$D$2>=1),Hypothèses!$B$34*MIN(1,$D$2/3),0)) -> 0 | P26: =M26+N26+O26 -> 4381.9625 | Q26: =P26/(1+Hypothèses!$B$6) -> 3651.6354 | R26: =Hypothèses!$B$3*(1+Hypothèses!$B$4)^INT((A26-1)/3) -> 1330.0099 | S26: =0 -> 0 | T26: =S26*Hypothèses!$B$17 -> 0 | U26: =Q26*Hypothèses!$B$5 -> 36.516354 | V26: =Q26-R26-T26-U26 -> 2285.1091 | W26: =W25+V26 -> 26148.022
A27: 24 | B27: =INT((A27-1)/12)+1 -> 2 | C27: =ROUND(IF(MOD($A27,12)=0,G27,(IF(27=4,0,C26))*(1-$K27)+IF((IF(27=4,0,C26))*(1-$K27)<G27,(G27-(IF(27=4,0,C26))*(1-$K27))*Hypothèses!$B$10,0)),1) -> 7 | D27: =ROUND(IF(MOD($A27,12)=0,H27,(IF(27=4,0,D26))*(1-$K27)+IF((IF(27=4,0,D26))*(1-$K27)<H27,(H27-(IF(27=4,0,D26))*(1-$K27))*Hypothèses!$B$10,0)),1) -> 24.5 | E27: =ROUND(IF(MOD($A27,12)=0,I27,(IF(27=4,0,E26))*(1-$K27)+IF((IF(27=4,0,E26))*(1-$K27)<I27,(I27-(IF(27=4,0,E26))*(1-$K27))*Hypothèses!$B$10,0)),1) -> 0.7 | F27: =ROUND(IF(MOD($A27,12)=0,J27,(IF(27=4,0,F26))*(1-$K27)+IF((IF(27=4,0,F26))*(1-$K27)<J27,(J27-(IF(27=4,0,F26))*(1-$K27))*Hypothèses!$B$10,0)),1) -> 0.7 | G27: =(IF(B27=1,0,IF(B27=2,Hypothèses!$B$26,IF(B27=3,Hypothèses!$C$26,Hypothèses!$D$26)))+(IF(B27=1,Hypothèses!$B$26,IF(B27=2,Hypothèses!$C$26,IF(B27=3,Hypothèses!$D$26,Hypothèses!$D$26)))-(IF(B27=1,0,IF(B27=2,Hypothèses!$B$26,IF(B27=3,Hypothèses!$C$26,Hypothèses!$D$26)))))*((A27)-INT((A27-1)/12)*12)/12)*$B$1 -> 7 | H27: =(IF(B27=1,0,IF(B27=2,Hypothèses!$B$27,IF(B27=3,Hypothèses!$C$27,Hypothèses!$D$27)))+(IF(B27=1,Hypothèses!$B$27,IF(B27=2,Hypothèses!$C$27,IF(B27=3,Hypothèses!$D$27,Hypothèses!$D$27)))-(IF(B27=1,0,IF(B27=2,Hypothèses!$B$27,IF(B27=3,Hypothèses!$C$27,Hypothèses!$D$27)))))*((A27)-INT((A27-1)/12)*12)/12)*$B$1 -> 24.5 | I27: =(IF(B27=1,0,IF(B27=2,Hypothèses!$B$28,IF(B27=3,Hypothèses!$C$28,Hypothèses!$D$28)))+(IF(B27=1,Hypothèses!$B$28,IF(B27=2,Hypothèses!$C$28,IF(B27=3,Hypothèses!$D$28,Hypothèses!$D$28)))-(IF(B27=1,0,IF(B27=2,Hypothèses!$B$28,IF(B27=3,Hypothèses!$C$28,Hypothèses!$D$28)))))*((A27)-INT((A27-1)/12)*12)/12)*$B$1 -> 0.7 | J27: =(IF(B27=1,0,IF(B27=2,Hypothèses!$B$29,IF(B27=3,Hypothèses!$C$29,Hypothèses!$D$29)))+(IF(B27=1,Hypothèses!$B$29,IF(B27=2,Hypothèses!$C$29,IF(B27=3,Hypothèses!$D$29,Hypothèses!$D$29)))-(IF(B27=1,0,IF(B27=2,Hypothèses!$B$29,IF(B27=3,Hypothèses!$C$29,Hypothèses!$D$29)))))*((A27)-INT((A27-1)/12)*12)/12)*$B$1 -> 0.7 | K27: =IF(A27<Hypothèses!$B$7,0,Hypothèses!$B$8*(1-Hypothèses!$B$9)^(A27-Hypothèses!$B$7)) -> 0.010294557 | L27: =C27+D27+E27+F27 -> 32.9 | M27: =(C27*Hypothèses!$B$11+D27*Hypothèses!$B$12+E27*Hypothèses!$B$13+F27*Hypothèses!$B$14)*(IF(B27=1,Hypothèses!$B$20,IF(B27=2,Hypothèses!$B$21,Hypothèses!$B$22))+(1-(IF(B27=1,Hypothèses!$B$20,IF(B27=2,Hypothèses!$B$21,Hypothèses!$B$22))))*11/12) -> 5094.3083 | N27: =L27*IF(B27=1,Hypothèses!$C$20,IF(B27=2,Hypothèses!$C$21,Hypothèses!$C$22))*IF(B27=1,Hypothèses!$D$20,IF(B27=2,Hypothèses!$D$21,Hypothèses!$D$22)) -> 82.25 | O27: =IF(A27=18,IF($B$2>=1,Hypothèses!$B$33,0),IF(AND(OR(A27=30,A27=34),$D$2>=1),Hypothèses!$B$34*MIN(1,$D$2/3),0)) -> 0 | P27: =M27+N27+O27 -> 5176.5583 | Q27: =P27/(1+Hypothèses!$B$6) -> 4313.7986 | R27: =Hypothèses!$B$3*(1+Hypothèses!$B$4)^INT((A27-1)/3) -> 1330.0099 | S27: =0 -> 0 | T27: =S27*Hypothèses!$B$17 -> 0 | U27: =Q27*Hypothèses!$B$5 -> 43.137986 | V27: =Q27-R27-T27-U27 -> 2940.6507 | W27: =W26+V27 -> 29088.673
A28: 25 | B28: =INT((A28-1)/12)+1 -> 3 | C28: =ROUND(IF(MOD($A28,12)=0,G28,(IF(28=4,0,C27))*(1-$K28)+IF((IF(28=4,0,C27))*(1-$K28)<G28,(G28-(IF(28=4,0,C27))*(1-$K28))*Hypothèses!$B$10,0)),1) -> 7.2 | D28: =ROUND(IF(MOD($A28,12)=0,H28,(IF(28=4,0,D27))*(1-$K28)+IF((IF(28=4,0,D27))*(1-$K28)<H28,(H28-(IF(28=4,0,D27))*(1-$K28))*Hypothèses!$B$10,0)),1) -> 25.2 | E28: =ROUND(IF(MOD($A28,12)=0,I28,(IF(28=4,0,E27))*(1-$K28)+IF((IF(28=4,0,E27))*(1-$K28)<I28,(I28-(IF(28=4,0,E27))*(1-$K28))*Hypothèses!$B$10,0)),1) -> 0.7 | F28: =ROUND(IF(MOD($A28,12)=0,J28,(IF(28=4,0,F27))*(1-$K28)+IF((IF(28=4,0,F27))*(1-$K28)<J28,(J28-(IF(28=4,0,F27))*(1-$K28))*Hypothèses!$B$10,0)),1) -> 0.7 | G28: =(IF(B28=1,0,IF(B28=2,Hypothèses!$B$26,IF(B28=3,Hypothèses!$C$26,Hypothèses!$D$26)))+(IF(B28=1,Hypothèses!$B$26,IF(B28=2,Hypothèses!$C$26,IF(B28=3,Hypothèses!$D$26,Hypothèses!$D$26)))-(IF(B28=1,0,IF(B28=2,Hypothèses!$B$26,IF(B28=3,Hypothèses!$C$26,Hypothèses!$D$26)))))*((A28)-INT((A28-1)/12)*12)/12)*$B$1 -> 7.5833333 | H28: =(IF(B28=1,0,IF(B28=2,Hypothèses!$B$27,IF(B28=3,Hypothèses!$C$27,Hypothèses!$D$27)))+(IF(B28=1,Hypothèses!$B$27,IF(B28=2,Hypothèses!$C$27,IF(B28=3,Hypothèses!$D$27,Hypothèses!$D$27)))-(IF(B28=1,0,IF(B28=2,Hypothèses!$B$27,IF(B28=3,Hypothèses!$C$27,Hypothèses!$D$27)))))*((A28)-INT((A28-1)/12)*12)/12)*$B$1 -> 26.541667 | I28: =(IF(B28=1,0,IF(B28=2,Hypothèses!$B$28,IF(B28=3,Hypothèses!$C$28,Hypothèses!$D$28)))+(IF(B28=1,Hypothèses!$B$28,IF(B28=2,Hypothèses!$C$28,IF(B28=3,Hypothèses!$D$28,Hypothèses!$D$28)))-(IF(B28=1,0,IF(B28=2,Hypothèses!$B$28,IF(B28=3,Hypothèses!$C$28,Hypothèses!$D$28)))))*((A28)-INT((A28-1)/12)*12)/12)*$B$1 -> 0.81666667 | J28: =(IF(B28=1,0,IF(B28=2,Hypothèses!$B$29,IF(B28=3,Hypothèses!$C$29,Hypothèses!$D$29)))+(IF(B28=1,Hypothèses!$B$29,IF(B28=2,Hypothèses!$C$29,IF(B28=3,Hypothèses!$D$29,Hypothèses!$D$29)))-(IF(B28=1,0,IF(B28=2,Hypothèses!$B$29,IF(B28=3,Hypothèses!$C$29,Hypothèses!$D$29)))))*((A28)-INT((A28-1)/12)*12)/12)*$B$1 -> 0.75833333 | K28: =IF(A28<Hypothèses!$B$7,0,Hypothèses!$B$8*(1-Hypothèses!$B$9)^(A28-Hypothèses!$B$7)) -> 0.0092651009 | L28: =C28+D28+E28+F28 -> 33.8 | M28: =(C28*Hypothèses!$B$11+D28*Hypothèses!$B$12+E28*Hypothèses!$B$13+F28*Hypothèses!$B$14)*(IF(B28=1,Hypothèses!$B$20,IF(B28=2,Hypothèses!$B$21,Hypothèses!$B$22))+(1-(IF(B28=1,Hypothèses!$B$20,IF(B28=2,Hypothèses!$B$21,Hypothèses!$B$22))))*11/12) -> 5166.005 | N28: =L28*IF(B28=1,Hypothèses!$C$20,IF(B28=2,Hypothèses!$C$21,Hypothèses!$C$22))*IF(B28=1,Hypothèses!$D$20,IF(B28=2,Hypothèses!$D$21,Hypothèses!$D$22)) -> 121.68 | O28: =IF(A28=18,IF($B$2>=1,Hypothèses!$B$33,0),IF(AND(OR(A28=30,A28=34),$D$2>=1),Hypothèses!$B$34*MIN(1,$D$2/3),0)) -> 0 | P28: =M28+N28+O28 -> 5287.685 | Q28: =P28/(1+Hypothèses!$B$6) -> 4406.4042 | R28: =Hypothèses!$B$3*(1+Hypothèses!$B$4)^INT((A28-1)/3) -> 1529.5114 | S28: =0 -> 0 | T28: =S28*Hypothèses!$B$17 -> 0 | U28: =Q28*Hypothèses!$B$5 -> 44.064042 | V28: =Q28-R28-T28-U28 -> 2832.8287 | W28: =W27+V28 -> 31921.502
A29: 26 | B29: =INT((A29-1)/12)+1 -> 3 | C29: =ROUND(IF(MOD($A29,12)=0,G29,(IF(29=4,0,C28))*(1-$K29)+IF((IF(29=4,0,C28))*(1-$K29)<G29,(G29-(IF(29=4,0,C28))*(1-$K29))*Hypothèses!$B$10,0)),1) -> 7.6 | D29: =ROUND(IF(MOD($A29,12)=0,H29,(IF(29=4,0,D28))*(1-$K29)+IF((IF(29=4,0,D28))*(1-$K29)<H29,(H29-(IF(29=4,0,D28))*(1-$K29))*Hypothèses!$B$10,0)),1) -> 26.4 | E29: =ROUND(IF(MOD($A29,12)=0,I29,(IF(29=4,0,E28))*(1-$K29)+IF((IF(29=4,0,E28))*(1-$K29)<I29,(I29-(IF(29=4,0,E28))*(1-$K29))*Hypothèses!$B$10,0)),1) -> 0.8 | F29: =ROUND(IF(MOD($A29,12)=0,J29,(IF(29=4,0,F28))*(1-$K29)+IF((IF(29=4,0,F28))*(1-$K29)<J29,(J29-(IF(29=4,0,F28))*(1-$K29))*Hypothèses!$B$10,0)),1) -> 0.7 | G29: =(IF(B29=1,0,IF(B29=2,Hypothèses!$B$26,IF(B29=3,Hypothèses!$C$26,Hypothèses!$D$26)))+(IF(B29=1,Hypothèses!$B$26,IF(B29=2,Hypothèses!$C$26,IF(B29=3,Hypothèses!$D$26,Hypothèses!$D$26)))-(IF(B29=1,0,IF(B29=2,Hypothèses!$B$26,IF(B29=3,Hypothèses!$C$26,Hypothèses!$D$26)))))*((A29)-INT((A29-1)/12)*12)/12)*$B$1 -> 8.1666667 | H29: =(IF(B29=1,0,IF(B29=2,Hypothèses!$B$27,IF(B29=3,Hypothèses!$C$27,Hypothèses!$D$27)))+(IF(B29=1,Hypothèses!$B$27,IF(B29=2,Hypothèses!$C$27,IF(B29=3,Hypothèses!$D$27,Hypothèses!$D$27)))-(IF(B29=1,0,IF(B29=2,Hypothèses!$B$27,IF(B29=3,Hypothèses!$C$27,Hypothèses!$D$27)))))*((A29)-INT((A29-1)/12)*12)/12)*$B$1 -> 28.583333 | I29: =(IF(B29=1,0,IF(B29=2,Hypothèses!$B$28,IF(B29=3,Hypothèses!$C$28,Hypothèses!$D$28)))+(IF(B29=1,Hypothèses!$B$28,IF(B29=2,Hypothèses!$C$28,IF(B29=3,Hypothèses!$D$28,Hypothèses!$D$28)))-(IF(B29=1,0,IF(B29=2,Hypothèses!$B$28,IF(B29=3,Hypothèses!$C$28,Hypothèses!$D$28)))))*((A29)-INT((A29-1)/12)*12)/12)*$B$1 -> 0.93333333 | J29: =(IF(B29=1,0,IF(B29=2,Hypothèses!$B$29,IF(B29=3,Hypothèses!$C$29,Hypothèses!$D$29)))+(IF(B29=1,Hypothèses!$B$29,IF(B29=2,Hypothèses!$C$29,IF(B29=3,Hypothèses!$D$29,Hypothèses!$D$29)))-(IF(B29=1,0,IF(B29=2,Hypothèses!$B$29,IF(B29=3,Hypothèses!$C$29,Hypothèses!$D$29)))))*((A29)-INT((A29-1)/12)*12)/12)*$B$1 -> 0.81666667 | K29: =IF(A29<Hypothèses!$B$7,0,Hypothèses!$B$8*(1-Hypothèses!$B$9)^(A29-Hypothèses!$B$7)) -> 0.0083385908 | L29: =C29+D29+E29+F29 -> 35.5 | M29: =(C29*Hypothèses!$B$11+D29*Hypothèses!$B$12+E29*Hypothèses!$B$13+F29*Hypothèses!$B$14)*(IF(B29=1,Hypothèses!$B$20,IF(B29=2,Hypothèses!$B$21,Hypothèses!$B$22))+(1-(IF(B29=1,Hypothèses!$B$20,IF(B29=2,Hypothèses!$B$21,Hypothèses!$B$22))))*11/12) -> 5417.09 | N29: =L29*IF(B29=1,Hypothèses!$C$20,IF(B29=2,Hypothèses!$C$21,Hypothèses!$C$22))*IF(B29=1,Hypothèses!$D$20,IF(B29=2,Hypothèses!$D$21,Hypothèses!$D$22)) -> 127.8 | O29: =IF(A29=18,IF($B$2>=1,Hypothèses!$B$33,0),IF(AND(OR(A29=30,A29=34),$D$2>=1),Hypothèses!$B$34*MIN(1,$D$2/3),0)) -> 0 | P29: =M29+N29+O29 -> 5544.89 | Q29: =P29/(1+Hypothèses!$B$6) -> 4620.7417 | R29: =Hypothèses!$B$3*(1+Hypothèses!$B$4)^INT((A29-1)/3) -> 1529.5114 | S29: =0 -> 0 | T29: =S29*Hypothèses!$B$17 -> 0 | U29: =Q29*Hypothèses!$B$5 -> 46.207417 | V29: =Q29-R29-T29-U29 -> 3045.0228 | W29: =W28+V29 -> 34966.524
A30: 27 | B30: =INT((A30-1)/12)+1 -> 3 | C30: =ROUND(IF(MOD($A30,12)=0,G30,(IF(30=4,0,C29))*(1-$K30)+IF((IF(30=4,0,C29))*(1-$K30)<G30,(G30-(IF(30=4,0,C29))*(1-$K30))*Hypothèses!$B$10,0)),1) -> 8 | D30: =ROUND(IF(MOD($A30,12)=0,H30,(IF(30=4,0,D29))*(1-$K30)+IF((IF(30=4,0,D29))*(1-$K30)<H30,(H30-(IF(30=4,0,D29))*(1-$K30))*Hypothèses!$B$10,0)),1) -> 28 | E30: =ROUND(IF(MOD($A30,12)=0,I30,(IF(30=4,0,E29))*(1-$K30)+IF((IF(30=4,0,E29))*(1-$K30)<I30,(I30-(IF(30=4,0,E29))*(1-$K30))*Hypothèses!$B$10,0)),1) -> 0.9 | F30: =ROUND(IF(MOD($A30,12)=0,J30,(IF(30=4,0,F29))*(1-$K30)+IF((IF(30=4,0,F29))*(1-$K30)<J30,(J30-(IF(30=4,0,F29))*(1-$K30))*Hypothèses!$B$10,0)),1) -> 0.8 | G30: =(IF(B30=1,0,IF(B30=2,Hypothèses!$B$26,IF(B30=3,Hypothèses!$C$26,Hypothèses!$D$26)))+(IF(B30=1,Hypothèses!$B$26,IF(B30=2,Hypothèses!$C$26,IF(B30=3,Hypothèses!$D$26,Hypothèses!$D$26)))-(IF(B30=1,0,IF(B30=2,Hypothèses!$B$26,IF(B30=3,Hypothèses!$C$26,Hypothèses!$D$26)))))*((A30)-INT((A30-1)/12)*12)/12)*$B$1 -> 8.75 | H30: =(IF(B30=1,0,IF(B30=2,Hypothèses!$B$27,IF(B30=3,Hypothèses!$C$27,Hypothèses!$D$27)))+(IF(B30=1,Hypothèses!$B$27,IF(B30=2,Hypothèses!$C$27,IF(B30=3,Hypothèses!$D$27,Hypothèses!$D$27)))-(IF(B30=1,0,IF(B30=2,Hypothèses!$B$27,IF(B30=3,Hypothèses!$C$27,Hypothèses!$D$27)))))*((A30)-INT((A30-1)/12)*12)/12)*$B$1 -> 30.625 | I30: =(IF(B30=1,0,IF(B30=2,Hypothèses!$B$28,IF(B30=3,Hypothèses!$C$28,Hypothèses!$D$28)))+(IF(B30=1,Hypothèses!$B$28,IF(B30=2,Hypothèses!$C$28,IF(B30=3,Hypothèses!$D$28,Hypothèses!$D$28)))-(IF(B30=1,0,IF(B30=2,Hypothèses!$B$28,IF(B30=3,Hypothèses!$C$28,Hypothèses!$D$28)))))*((A30)-INT((A30-1)/12)*12)/12)*$B$1 -> 1.05 | J30: =(IF(B30=1,0,IF(B30=2,Hypothèses!$B$29,IF(B30=3,Hypothèses!$C$29,Hypothèses!$D$29)))+(IF(B30=1,Hypothèses!$B$29,IF(B30=2,Hypothèses!$C$29,IF(B30=3,Hypothèses!$D$29,Hypothèses!$D$29)))-(IF(B30=1,0,IF(B30=2,Hypothèses!$B$29,IF(B30=3,Hypothèses!$C$29,Hypothèses!$D$29)))))*((A30)-INT((A30-1)/12)*12)/12)*$B$1 -> 0.875 | K30: =IF(A30<Hypothèses!$B$7,0,Hypothèses!$B$8*(1-Hypothèses!$B$9)^(A30-Hypothèses!$B$7)) -> 0.0075047318 | L30: =C30+D30+E30+F30 -> 37.7 | M30: =(C30*Hypothèses!$B$11+D30*Hypothèses!$B$12+E30*Hypothèses!$B$13+F30*Hypothèses!$B$14)*(IF(B30=1,Hypothèses!$B$20,IF(B30=2,Hypothèses!$B$21,Hypothèses!$B$22))+(1-(IF(B30=1,Hypothèses!$B$20,IF(B30=2,Hypothèses!$B$21,Hypothèses!$B$22))))*11/12) -> 5818.845 | N30: =L30*IF(B30=1,Hypothèses!$C$20,IF(B30=2,Hypothèses!$C$21,Hypothèses!$C$22))*IF(B30=1,Hypothèses!$D$20,IF(B30=2,Hypothèses!$D$21,Hypothèses!$D$22)) -> 135.72 | O30: =IF(A30=18,IF($B$2>=1,Hypothèses!$B$33,0),IF(AND(OR(A30=30,A30=34),$D$2>=1),Hypothèses!$B$34*MIN(1,$D$2/3),0)) -> 0 | P30: =M30+N30+O30 -> 5954.565 | Q30: =P30/(1+Hypothèses!$B$6) -> 4962.1375 | R30: =Hypothèses!$B$3*(1+Hypothèses!$B$4)^INT((A30-1)/3) -> 1529.5114 | S30: =0 -> 0 | T30: =S30*Hypothèses!$B$17 -> 0 | U30: =Q30*Hypothèses!$B$5 -> 49.621375 | V30: =Q30-R30-T30-U30 -> 3383.0047 | W30: =W29+V30 -> 38349.529
A31: 28 | B31: =INT((A31-1)/12)+1 -> 3 | C31: =ROUND(IF(MOD($A31,12)=0,G31,(IF(31=4,0,C30))*(1-$K31)+IF((IF(31=4,0,C30))*(1-$K31)<G31,(G31-(IF(31=4,0,C30))*(1-$K31))*Hypothèses!$B$10,0)),1) -> 8.5 | D31: =ROUND(IF(MOD($A31,12)=0,H31,(IF(31=4,0,D30))*(1-$K31)+IF((IF(31=4,0,D30))*(1-$K31)<H31,(H31-(IF(31=4,0,D30))*(1-$K31))*Hypothèses!$B$10,0)),1) -> 29.8 | E31: =ROUND(IF(MOD($A31,12)=0,I31,(IF(31=4,0,E30))*(1-$K31)+IF((IF(31=4,0,E30))*(1-$K31)<I31,(I31-(IF(31=4,0,E30))*(1-$K31))*Hypothèses!$B$10,0)),1) -> 1 | F31: =ROUND(IF(MOD($A31,12)=0,J31,(IF(31=4,0,F30))*(1-$K31)+IF((IF(31=4,0,F30))*(1-$K31)<J31,(J31-(IF(31=4,0,F30))*(1-$K31))*Hypothèses!$B$10,0)),1) -> 0.9 | G31: =(IF(B31=1,0,IF(B31=2,Hypothèses!$B$26,IF(B31=3,Hypothèses!$C$26,Hypothèses!$D$26)))+(IF(B31=1,Hypothèses!$B$26,IF(B31=2,Hypothèses!$C$26,IF(B31=3,Hypothèses!$D$26,Hypothèses!$D$26)))-(IF(B31=1,0,IF(B31=2,Hypothèses!$B$26,IF(B31=3,Hypothèses!$C$26,Hypothèses!$D$26)))))*((A31)-INT((A31-1)/12)*12)/12)*$B$1 -> 9.3333333 | H31: =(IF(B31=1,0,IF(B31=2,Hypothèses!$B$27,IF(B31=3,Hypothèses!$C$27,Hypothèses!$D$27)))+(IF(B31=1,Hypothèses!$B$27,IF(B31=2,Hypothèses!$C$27,IF(B31=3,Hypothèses!$D$27,Hypothèses!$D$27)))-(IF(B31=1,0,IF(B31=2,Hypothèses!$B$27,IF(B31=3,Hypothèses!$C$27,Hypothèses!$D$27)))))*((A31)-INT((A31-1)/12)*12)/12)*$B$1 -> 32.666667 | I31: =(IF(B31=1,0,IF(B31=2,Hypothèses!$B$28,IF(B31=3,Hypothèses!$C$28,Hypothèses!$D$28)))+(IF(B31=1,Hypothèses!$B$28,IF(B31=2,Hypothèses!$C$28,IF(B31=3,Hypothèses!$D$28,Hypothèses!$D$28)))-(IF(B31=1,0,IF(B31=2,Hypothèses!$B$28,IF(B31=3,Hypothèses!$C$28,Hypothèses!$D$28)))))*((A31)-INT((A31-1)/12)*12)/12)*$B$1 -> 1.1666667 | J31: =(IF(B31=1,0,IF(B31=2,Hypothèses!$B$29,IF(B31=3,Hypothèses!$C$29,Hypothèses!$D$29)))+(IF(B31=1,Hypothèses!$B$29,IF(B31=2,Hypothèses!$C$29,IF(B31=3,Hypothèses!$D$29,Hypothèses!$D$29)))-(IF(B31=1,0,IF(B31=2,Hypothèses!$B$29,IF(B31=3,Hypothèses!$C$29,Hypothèses!$D$29)))))*((A31)-INT((A31-1)/12)*12)/12)*$B$1 -> 0.93333333 | K31: =IF(A31<Hypothèses!$B$7,0,Hypothèses!$B$8*(1-Hypothèses!$B$9)^(A31-Hypothèses!$B$7)) -> 0.0067542586 | L31: =C31+D31+E31+F31 -> 40.2 | M31: =(C31*Hypothèses!$B$11+D31*Hypothèses!$B$12+E31*Hypothèses!$B$13+F31*Hypothèses!$B$14)*(IF(B31=1,Hypothèses!$B$20,IF(B31=2,Hypothèses!$B$21,Hypothèses!$B$22))+(1-(IF(B31=1,Hypothèses!$B$20,IF(B31=2,Hypothèses!$B$21,Hypothèses!$B$22))))*11/12) -> 6257.365 | N31: =L31*IF(B31=1,Hypothèses!$C$20,IF(B31=2,Hypothèses!$C$21,Hypothèses!$C$22))*IF(B31=1,Hypothèses!$D$20,IF(B31=2,Hypothèses!$D$21,Hypothèses!$D$22)) -> 144.72 | O31: =IF(A31=18,IF($B$2>=1,Hypothèses!$B$33,0),IF(AND(OR(A31=30,A31=34),$D$2>=1),Hypothèses!$B$34*MIN(1,$D$2/3),0)) -> 0 | P31: =M31+N31+O31 -> 6402.085 | Q31: =P31/(1+Hypothèses!$B$6) -> 5335.0708 | R31: =Hypothèses!$B$3*(1+Hypothèses!$B$4)^INT((A31-1)/3) -> 1758.9381 | S31: =0 -> 0 | T31: =S31*Hypothèses!$B$17 -> 0 | U31: =Q31*Hypothèses!$B$5 -> 53.350708 | V31: =Q31-R31-T31-U31 -> 3522.782 | W31: =W30+V31 -> 41872.311
A32: 29 | B32: =INT((A32-1)/12)+1 -> 3 | C32: =ROUND(IF(MOD($A32,12)=0,G32,(IF(32=4,0,C31))*(1-$K32)+IF((IF(32=4,0,C31))*(1-$K32)<G32,(G32-(IF(32=4,0,C31))*(1-$K32))*Hypothèses!$B$10,0)),1) -> 9 | D32: =ROUND(IF(MOD($A32,12)=0,H32,(IF(32=4,0,D31))*(1-$K32)+IF((IF(32=4,0,D31))*(1-$K32)<H32,(H32-(IF(32=4,0,D31))*(1-$K32))*Hypothèses!$B$10,0)),1) -> 31.7 | E32: =ROUND(IF(MOD($A32,12)=0,I32,(IF(32=4,0,E31))*(1-$K32)+IF((IF(32=4,0,E31))*(1-$K32)<I32,(I32-(IF(32=4,0,E31))*(1-$K32))*Hypothèses!$B$10,0)),1) -> 1.1 | F32: =ROUND(IF(MOD($A32,12)=0,J32,(IF(32=4,0,F31))*(1-$K32)+IF((IF(32=4,0,F31))*(1-$K32)<J32,(J32-(IF(32=4,0,F31))*(1-$K32))*Hypothèses!$B$10,0)),1) -> 0.9 | G32: =(IF(B32=1,0,IF(B32=2,Hypothèses!$B$26,IF(B32=3,Hypothèses!$C$26,Hypothèses!$D$26)))+(IF(B32=1,Hypothèses!$B$26,IF(B32=2,Hypothèses!$C$26,IF(B32=3,Hypothèses!$D$26,Hypothèses!$D$26)))-(IF(B32=1,0,IF(B32=2,Hypothèses!$B$26,IF(B32=3,Hypothèses!$C$26,Hypothèses!$D$26)))))*((A32)-INT((A32-1)/12)*12)/12)*$B$1 -> 9.9166667 | H32: =(IF(B32=1,0,IF(B32=2,Hypothèses!$B$27,IF(B32=3,Hypothèses!$C$27,Hypothèses!$D$27)))+(IF(B32=1,Hypothèses!$B$27,IF(B32=2,Hypothèses!$C$27,IF(B32=3,Hypothèses!$D$27,Hypothèses!$D$27)))-(IF(B32=1,0,IF(B32=2,Hypothèses!$B$27,IF(B32=3,Hypothèses!$C$27,Hypothèses!$D$27)))))*((A32)-INT((A32-1)/12)*12)/12)*$B$1 -> 34.708333 | I32: =(IF(B32=1,0,IF(B32=2,Hypothèses!$B$28,IF(B32=3,Hypothèses!$C$28,Hypothèses!$D$28)))+(IF(B32=1,Hypothèses!$B$28,IF(B32=2,Hypothèses!$C$28,IF(B32=3,Hypothèses!$D$28,Hypothèses!$D$28)))-(IF(B32=1,0,IF(B32=2,Hypothèses!$B$28,IF(B32=3,Hypothèses!$C$28,Hypothèses!$D$28)))))*((A32)-INT((A32-1)/12)*12)/12)*$B$1 -> 1.2833333 | J32: =(IF(B32=1,0,IF(B32=2,Hypothèses!$B$29,IF(B32=3,Hypothèses!$C$29,Hypothèses!$D$29)))+(IF(B32=1,Hypothèses!$B$29,IF(B32=2,Hypothèses!$C$29,IF(B32=3,Hypothèses!$D$29,Hypothèses!$D$29)))-(IF(B32=1,0,IF(B32=2,Hypothèses!$B$29,IF(B32=3,Hypothèses!$C$29,Hypothèses!$D$29)))))*((A32)-INT((A32-1)/12)*12)/12)*$B$1 -> 0.99166667 | K32: =IF(A32<Hypothèses!$B$7,0,Hypothèses!$B$8*(1-Hypothèses!$B$9)^(A32-Hypothèses!$B$7)) -> 0.0060788327 | L32: =C32+D32+E32+F32 -> 42.7 | M32: =(C32*Hypothèses!$B$11+D32*Hypothèses!$B$12+E32*Hypothèses!$B$13+F32*Hypothèses!$B$14)*(IF(B32=1,Hypothèses!$B$20,IF(B32=2,Hypothèses!$B$21,Hypothèses!$B$22))+(1-(IF(B32=1,Hypothèses!$B$20,IF(B32=2,Hypothèses!$B$21,Hypothèses!$B$22))))*11/12) -> 6615.99 | N32: =L32*IF(B32=1,Hypothèses!$C$20,IF(B32=2,Hypothèses!$C$21,Hypothèses!$C$22))*IF(B32=1,Hypothèses!$D$20,IF(B32=2,Hypothèses!$D$21,Hypothèses!$D$22)) -> 153.72 | O32: =IF(A32=18,IF($B$2>=1,Hypothèses!$B$33,0),IF(AND(OR(A32=30,A32=34),$D$2>=1),Hypothèses!$B$34*MIN(1,$D$2/3),0)) -> 0 | P32: =M32+N32+O32 -> 6769.71 | Q32: =P32/(1+Hypothèses!$B$6) -> 5641.425 | R32: =Hypothèses!$B$3*(1+Hypothèses!$B$4)^INT((A32-1)/3) -> 1758.9381 | S32: =0 -> 0 | T32: =S32*Hypothèses!$B$17 -> 0 | U32: =Q32*Hypothèses!$B$5 -> 56.41425 | V32: =Q32-R32-T32-U32 -> 3826.0726 | W32: =W31+V32 -> 45698.384
A33: 30 | B33: =INT((A33-1)/12)+1 -> 3 | C33: =ROUND(IF(MOD($A33,12)=0,G33,(IF(33=4,0,C32))*(1-$K33)+IF((IF(33=4,0,C32))*(1-$K33)<G33,(G33-(IF(33=4,0,C32))*(1-$K33))*Hypothèses!$B$10,0)),1) -> 9.6 | D33: =ROUND(IF(MOD($A33,12)=0,H33,(IF(33=4,0,D32))*(1-$K33)+IF((IF(33=4,0,D32))*(1-$K33)<H33,(H33-(IF(33=4,0,D32))*(1-$K33))*Hypothèses!$B$10,0)),1) -> 33.6 | E33: =ROUND(IF(MOD($A33,12)=0,I33,(IF(33=4,0,E32))*(1-$K33)+IF((IF(33=4,0,E32))*(1-$K33)<I33,(I33-(IF(33=4,0,E32))*(1-$K33))*Hypothèses!$B$10,0)),1) -> 1.2 | F33: =ROUND(IF(MOD($A33,12)=0,J33,(IF(33=4,0,F32))*(1-$K33)+IF((IF(33=4,0,F32))*(1-$K33)<J33,(J33-(IF(33=4,0,F32))*(1-$K33))*Hypothèses!$B$10,0)),1) -> 1 | G33: =(IF(B33=1,0,IF(B33=2,Hypothèses!$B$26,IF(B33=3,Hypothèses!$C$26,Hypothèses!$D$26)))+(IF(B33=1,Hypothèses!$B$26,IF(B33=2,Hypothèses!$C$26,IF(B33=3,Hypothèses!$D$26,Hypothèses!$D$26)))-(IF(B33=1,0,IF(B33=2,Hypothèses!$B$26,IF(B33=3,Hypothèses!$C$26,Hypothèses!$D$26)))))*((A33)-INT((A33-1)/12)*12)/12)*$B$1 -> 10.5 | H33: =(IF(B33=1,0,IF(B33=2,Hypothèses!$B$27,IF(B33=3,Hypothèses!$C$27,Hypothèses!$D$27)))+(IF(B33=1,Hypothèses!$B$27,IF(B33=2,Hypothèses!$C$27,IF(B33=3,Hypothèses!$D$27,Hypothèses!$D$27)))-(IF(B33=1,0,IF(B33=2,Hypothèses!$B$27,IF(B33=3,Hypothèses!$C$27,Hypothèses!$D$27)))))*((A33)-INT((A33-1)/12)*12)/12)*$B$1 -> 36.75 | I33: =(IF(B33=1,0,IF(B33=2,Hypothèses!$B$28,IF(B33=3,Hypothèses!$C$28,Hypothèses!$D$28)))+(IF(B33=1,Hypothèses!$B$28,IF(B33=2,Hypothèses!$C$28,IF(B33=3,Hypothèses!$D$28,Hypothèses!$D$28)))-(IF(B33=1,0,IF(B33=2,Hypothèses!$B$28,IF(B33=3,Hypothèses!$C$28,Hypothèses!$D$28)))))*((A33)-INT((A33-1)/12)*12)/12)*$B$1 -> 1.4 | J33: =(IF(B33=1,0,IF(B33=2,Hypothèses!$B$29,IF(B33=3,Hypothèses!$C$29,Hypothèses!$D$29)))+(IF(B33=1,Hypothèses!$B$29,IF(B33=2,Hypothèses!$C$29,IF(B33=3,Hypothèses!$D$29,Hypothèses!$D$29)))-(IF(B33=1,0,IF(B33=2,Hypothèses!$B$29,IF(B33=3,Hypothèses!$C$29,Hypothèses!$D$29)))))*((A33)-INT((A33-1)/12)*12)/12)*$B$1 -> 1.05 | K33: =IF(A33<Hypothèses!$B$7,0,Hypothèses!$B$8*(1-Hypothèses!$B$9)^(A33-Hypothèses!$B$7)) -> 0.0054709495 | L33: =C33+D33+E33+F33 -> 45.4 | M33: =(C33*Hypothèses!$B$11+D33*Hypothèses!$B$12+E33*Hypothèses!$B$13+F33*Hypothèses!$B$14)*(IF(B33=1,Hypothèses!$B$20,IF(B33=2,Hypothèses!$B$21,Hypothèses!$B$22))+(1-(IF(B33=1,Hypothèses!$B$20,IF(B33=2,Hypothèses!$B$21,Hypothèses!$B$22))))*11/12) -> 7077.12 | N33: =L33*IF(B33=1,Hypothèses!$C$20,IF(B33=2,Hypothèses!$C$21,Hypothèses!$C$22))*IF(B33=1,Hypothèses!$D$20,IF(B33=2,Hypothèses!$D$21,Hypothèses!$D$22)) -> 163.44 | O33: =IF(A33=18,IF($B$2>=1,Hypothèses!$B$33,0),IF(AND(OR(A33=30,A33=34),$D$2>=1),Hypothèses!$B$34*MIN(1,$D$2/3),0)) -> 11333.333 | P33: =M33+N33+O33 -> 18573.893 | Q33: =P33/(1+Hypothèses!$B$6) -> 15478.244 | R33: =Hypothèses!$B$3*(1+Hypothèses!$B$4)^INT((A33-1)/3) -> 1758.9381 | S33: =0 -> 0 | T33: =S33*Hypothèses!$B$17 -> 0 | U33: =Q33*Hypothèses!$B$5 -> 154.78244 | V33: =Q33-R33-T33-U33 -> 13564.524 | W33: =W32+V33 -> 59262.908
A34: 31 | B34: =INT((A34-1)/12)+1 -> 3 | C34: =ROUND(IF(MOD($A34,12)=0,G34,(IF(34=4,0,C33))*(1-$K34)+IF((IF(34=4,0,C33))*(1-$K34)<G34,(G34-(IF(34=4,0,C33))*(1-$K34))*Hypothèses!$B$10,0)),1) -> 10.2 | D34: =ROUND(IF(MOD($A34,12)=0,H34,(IF(34=4,0,D33))*(1-$K34)+IF((IF(34=4,0,D33))*(1-$K34)<H34,(H34-(IF(34=4,0,D33))*(1-$K34))*Hypothèses!$B$10,0)),1) -> 35.6 | E34: =ROUND(IF(MOD($A34,12)=0,I34,(IF(34=4,0,E33))*(1-$K34)+IF((IF(34=4,0,E33))*(1-$K34)<I34,(I34-(IF(34=4,0,E33))*(1-$K34))*Hypothèses!$B$10,0)),1) -> 1.3 | F34: =ROUND(IF(MOD($A34,12)=0,J34,(IF(34=4,0,F33))*(1-$K34)+IF((IF(34=4,0,F33))*(1-$K34)<J34,(J34-(IF(34=4,0,F33))*(1-$K34))*Hypothèses!$B$10,0)),1) -> 1 | G34: =(IF(B34=1,0,IF(B34=2,Hypothèses!$B$26,IF(B34=3,Hypothèses!$C$26,Hypothèses!$D$26)))+(IF(B34=1,Hypothèses!$B$26,IF(B34=2,Hypothèses!$C$26,IF(B34=3,Hypothèses!$D$26,Hypothèses!$D$26)))-(IF(B34=1,0,IF(B34=2,Hypothèses!$B$26,IF(B34=3,Hypothèses!$C$26,Hypothèses!$D$26)))))*((A34)-INT((A34-1)/12)*12)/12)*$B$1 -> 11.083333 | H34: =(IF(B34=1,0,IF(B34=2,Hypothèses!$B$27,IF(B34=3,Hypothèses!$C$27,Hypothèses!$D$27)))+(IF(B34=1,Hypothèses!$B$27,IF(B34=2,Hypothèses!$C$27,IF(B34=3,Hypothèses!$D$27,Hypothèses!$D$27)))-(IF(B34=1,0,IF(B34=2,Hypothèses!$B$27,IF(B34=3,Hypothèses!$C$27,Hypothèses!$D$27)))))*((A34)-INT((A34-1)/12)*12)/12)*$B$1 -> 38.791667 | I34: =(IF(B34=1,0,IF(B34=2,Hypothèses!$B$28,IF(B34=3,Hypothèses!$C$28,Hypothèses!$D$28)))+(IF(B34=1,Hypothèses!$B$28,IF(B34=2,Hypothèses!$C$28,IF(B34=3,Hypothèses!$D$28,Hypothèses!$D$28)))-(IF(B34=1,0,IF(B34=2,Hypothèses!$B$28,IF(B34=3,Hypothèses!$C$28,Hypothèses!$D$28)))))*((A34)-INT((A34-1)/12)*12)/12)*$B$1 -> 1.5166667 | J34: =(IF(B34=1,0,IF(B34=2,Hypothèses!$B$29,IF(B34=3,Hypothèses!$C$29,Hypothèses!$D$29)))+(IF(B34=1,Hypothèses!$B$29,IF(B34=2,Hypothèses!$C$29,IF(B34=3,Hypothèses!$D$29,Hypothèses!$D$29)))-(IF(B34=1,0,IF(B34=2,Hypothèses!$B$29,IF(B34=3,Hypothèses!$C$29,Hypothèses!$D$29)))))*((A34)-INT((A34-1)/12)*12)/12)*$B$1 -> 1.1083333 | K34: =IF(A34<Hypothèses!$B$7,0,Hypothèses!$B$8*(1-Hypothèses!$B$9)^(A34-Hypothèses!$B$7)) -> 0.0049238545 | L34: =C34+D34+E34+F34 -> 48.1 | M34: =(C34*Hypothèses!$B$11+D34*Hypothèses!$B$12+E34*Hypothèses!$B$13+F34*Hypothèses!$B$14)*(IF(B34=1,Hypothèses!$B$20,IF(B34=2,Hypothèses!$B$21,Hypothèses!$B$22))+(1-(IF(B34=1,Hypothèses!$B$20,IF(B34=2,Hypothèses!$B$21,Hypothèses!$B$22))))*11/12) -> 7458.355 | N34: =L34*IF(B34=1,Hypothèses!$C$20,IF(B34=2,Hypothèses!$C$21,Hypothèses!$C$22))*IF(B34=1,Hypothèses!$D$20,IF(B34=2,Hypothèses!$D$21,Hypothèses!$D$22)) -> 173.16 | O34: =IF(A34=18,IF($B$2>=1,Hypothèses!$B$33,0),IF(AND(OR(A34=30,A34=34),$D$2>=1),Hypothèses!$B$34*MIN(1,$D$2/3),0)) -> 0 | P34: =M34+N34+O34 -> 7631.515 | Q34: =P34/(1+Hypothèses!$B$6) -> 6359.5958 | R34: =Hypothèses!$B$3*(1+Hypothèses!$B$4)^INT((A34-1)/3) -> 2022.7789 | S34: =0 -> 0 | T34: =S34*Hypothèses!$B$17 -> 0 | U34: =Q34*Hypothèses!$B$5 -> 63.595958 | V34: =Q34-R34-T34-U34 -> 4273.221 | W34: =W33+V34 -> 63536.129
A35: 32 | B35: =INT((A35-1)/12)+1 -> 3 | C35: =ROUND(IF(MOD($A35,12)=0,G35,(IF(35=4,0,C34))*(1-$K35)+IF((IF(35=4,0,C34))*(1-$K35)<G35,(G35-(IF(35=4,0,C34))*(1-$K35))*Hypothèses!$B$10,0)),1) -> 10.8 | D35: =ROUND(IF(MOD($A35,12)=0,H35,(IF(35=4,0,D34))*(1-$K35)+IF((IF(35=4,0,D34))*(1-$K35)<H35,(H35-(IF(35=4,0,D34))*(1-$K35))*Hypothèses!$B$10,0)),1) -> 37.6 | E35: =ROUND(IF(MOD($A35,12)=0,I35,(IF(35=4,0,E34))*(1-$K35)+IF((IF(35=4,0,E34))*(1-$K35)<I35,(I35-(IF(35=4,0,E34))*(1-$K35))*Hypothèses!$B$10,0)),1) -> 1.4 | F35: =ROUND(IF(MOD($A35,12)=0,J35,(IF(35=4,0,F34))*(1-$K35)+IF((IF(35=4,0,F34))*(1-$K35)<J35,(J35-(IF(35=4,0,F34))*(1-$K35))*Hypothèses!$B$10,0)),1) -> 1.1 | G35: =(IF(B35=1,0,IF(B35=2,Hypothèses!$B$26,IF(B35=3,Hypothèses!$C$26,Hypothèses!$D$26)))+(IF(B35=1,Hypothèses!$B$26,IF(B35=2,Hypothèses!$C$26,IF(B35=3,Hypothèses!$D$26,Hypothèses!$D$26)))-(IF(B35=1,0,IF(B35=2,Hypothèses!$B$26,IF(B35=3,Hypothèses!$C$26,Hypothèses!$D$26)))))*((A35)-INT((A35-1)/12)*12)/12)*$B$1 -> 11.666667 | H35: =(IF(B35=1,0,IF(B35=2,Hypothèses!$B$27,IF(B35=3,Hypothèses!$C$27,Hypothèses!$D$27)))+(IF(B35=1,Hypothèses!$B$27,IF(B35=2,Hypothèses!$C$27,IF(B35=3,Hypothèses!$D$27,Hypothèses!$D$27)))-(IF(B35=1,0,IF(B35=2,Hypothèses!$B$27,IF(B35=3,Hypothèses!$C$27,Hypothèses!$D$27)))))*((A35)-INT((A35-1)/12)*12)/12)*$B$1 -> 40.833333 | I35: =(IF(B35=1,0,IF(B35=2,Hypothèses!$B$28,IF(B35=3,Hypothèses!$C$28,Hypothèses!$D$28)))+(IF(B35=1,Hypothèses!$B$28,IF(B35=2,Hypothèses!$C$28,IF(B35=3,Hypothèses!$D$28,Hypothèses!$D$28)))-(IF(B35=1,0,IF(B35=2,Hypothèses!$B$28,IF(B35=3,Hypothèses!$C$28,Hypothèses!$D$28)))))*((A35)-INT((A35-1)/12)*12)/12)*$B$1 -> 1.6333333 | J35: =(IF(B35=1,0,IF(B35=2,Hypothèses!$B$29,IF(B35=3,Hypothèses!$C$29,Hypothèses!$D$29)))+(IF(B35=1,Hypothèses!$B$29,IF(B35=2,Hypothèses!$C$29,IF(B35=3,Hypothèses!$D$29,Hypothèses!$D$29)))-(IF(B35=1,0,IF(B35=2,Hypothèses!$B$29,IF(B35=3,Hypothèses!$C$29,Hypothèses!$D$29)))))*((A35)-INT((A35-1)/12)*12)/12)*$B$1 -> 1.1666667 | K35: =IF(A35<Hypothèses!$B$7,0,Hypothèses!$B$8*(1-Hypothèses!$B$9)^(A35-Hypothèses!$B$7)) -> 0.0044314691 | L35: =C35+D35+E35+F35 -> 50.9 | M35: =(C35*Hypothèses!$B$11+D35*Hypothèses!$B$12+E35*Hypothèses!$B$13+F35*Hypothèses!$B$14)*(IF(B35=1,Hypothèses!$B$20,IF(B35=2,Hypothèses!$B$21,Hypothèses!$B$22))+(1-(IF(B35=1,Hypothèses!$B$20,IF(B35=2,Hypothèses!$B$21,Hypothèses!$B$22))))*11/12) -> 7933.64 | N35: =L35*IF(B35=1,Hypothèses!$C$20,IF(B35=2,Hypothèses!$C$21,Hypothèses!$C$22))*IF(B35=1,Hypothèses!$D$20,IF(B35=2,Hypothèses!$D$21,Hypothèses!$D$22)) -> 183.24 | O35: =IF(A35=18,IF($B$2>=1,Hypothèses!$B$33,0),IF(AND(OR(A35=30,A35=34),$D$2>=1),Hypothèses!$B$34*MIN(1,$D$2/3),0)) -> 0 | P35: =M35+N35+O35 -> 8116.88 | Q35: =P35/(1+Hypothèses!$B$6) -> 6764.0667 | R35: =Hypothèses!$B$3*(1+Hypothèses!$B$4)^INT((A35-1)/3) -> 2022.7789 | S35: =0 -> 0 | T35: =S35*Hypothèses!$B$17 -> 0 | U35: =Q35*Hypothèses!$B$5 -> 67.640667 | V35: =Q35-R35-T35-U35 -> 4673.6471 | W35: =W34+V35 -> 68209.776
A36: 33 | B36: =INT((A36-1)/12)+1 -> 3 | C36: =ROUND(IF(MOD($A36,12)=0,G36,(IF(36=4,0,C35))*(1-$K36)+IF((IF(36=4,0,C35))*(1-$K36)<G36,(G36-(IF(36=4,0,C35))*(1-$K36))*Hypothèses!$B$10,0)),1) -> 11.4 | D36: =ROUND(IF(MOD($A36,12)=0,H36,(IF(36=4,0,D35))*(1-$K36)+IF((IF(36=4,0,D35))*(1-$K36)<H36,(H36-(IF(36=4,0,D35))*(1-$K36))*Hypothèses!$B$10,0)),1) -> 39.6 | E36: =ROUND(IF(MOD($A36,12)=0,I36,(IF(36=4,0,E35))*(1-$K36)+IF((IF(36=4,0,E35))*(1-$K36)<I36,(I36-(IF(36=4,0,E35))*(1-$K36))*Hypothèses!$B$10,0)),1) -> 1.5 | F36: =ROUND(IF(MOD($A36,12)=0,J36,(IF(36=4,0,F35))*(1-$K36)+IF((IF(36=4,0,F35))*(1-$K36)<J36,(J36-(IF(36=4,0,F35))*(1-$K36))*Hypothèses!$B$10,0)),1) -> 1.1 | G36: =(IF(B36=1,0,IF(B36=2,Hypothèses!$B$26,IF(B36=3,Hypothèses!$C$26,Hypothèses!$D$26)))+(IF(B36=1,Hypothèses!$B$26,IF(B36=2,Hypothèses!$C$26,IF(B36=3,Hypothèses!$D$26,Hypothèses!$D$26)))-(IF(B36=1,0,IF(B36=2,Hypothèses!$B$26,IF(B36=3,Hypothèses!$C$26,Hypothèses!$D$26)))))*((A36)-INT((A36-1)/12)*12)/12)*$B$1 -> 12.25 | H36: =(IF(B36=1,0,IF(B36=2,Hypothèses!$B$27,IF(B36=3,Hypothèses!$C$27,Hypothèses!$D$27)))+(IF(B36=1,Hypothèses!$B$27,IF(B36=2,Hypothèses!$C$27,IF(B36=3,Hypothèses!$D$27,Hypothèses!$D$27)))-(IF(B36=1,0,IF(B36=2,Hypothèses!$B$27,IF(B36=3,Hypothèses!$C$27,Hypothèses!$D$27)))))*((A36)-INT((A36-1)/12)*12)/12)*$B$1 -> 42.875 | I36: =(IF(B36=1,0,IF(B36=2,Hypothèses!$B$28,IF(B36=3,Hypothèses!$C$28,Hypothèses!$D$28)))+(IF(B36=1,Hypothèses!$B$28,IF(B36=2,Hypothèses!$C$28,IF(B36=3,Hypothèses!$D$28,Hypothèses!$D$28)))-(IF(B36=1,0,IF(B36=2,Hypothèses!$B$28,IF(B36=3,Hypothèses!$C$28,Hypothèses!$D$28)))))*((A36)-INT((A36-1)/12)*12)/12)*$B$1 -> 1.75 | J36: =(IF(B36=1,0,IF(B36=2,Hypothèses!$B$29,IF(B36=3,Hypothèses!$C$29,Hypothèses!$D$29)))+(IF(B36=1,Hypothèses!$B$29,IF(B36=2,Hypothèses!$C$29,IF(B36=3,Hypothèses!$D$29,Hypothèses!$D$29)))-(IF(B36=1,0,IF(B36=2,Hypothèses!$B$29,IF(B36=3,Hypothèses!$C$29,Hypothèses!$D$29)))))*((A36)-INT((A36-1)/12)*12)/12)*$B$1 -> 1.225 | K36: =IF(A36<Hypothèses!$B$7,0,Hypothèses!$B$8*(1-Hypothèses!$B$9)^(A36-Hypothèses!$B$7)) -> 0.0039883222 | L36: =C36+D36+E36+F36 -> 53.6 | M36: =(C36*Hypothèses!$B$11+D36*Hypothèses!$B$12+E36*Hypothèses!$B$13+F36*Hypothèses!$B$14)*(IF(B36=1,Hypothèses!$B$20,IF(B36=2,Hypothèses!$B$21,Hypothèses!$B$22))+(1-(IF(B36=1,Hypothèses!$B$20,IF(B36=2,Hypothèses!$B$21,Hypothèses!$B$22))))*11/12) -> 8314.875 | N36: =L36*IF(B36=1,Hypothèses!$C$20,IF(B36=2,Hypothèses!$C$21,Hypothèses!$C$22))*IF(B36=1,Hypothèses!$D$20,IF(B36=2,Hypothèses!$D$21,Hypothèses!$D$22)) -> 192.96 | O36: =IF(A36=18,IF($B$2>=1,Hypothèses!$B$33,0),IF(AND(OR(A36=30,A36=34),$D$2>=1),Hypothèses!$B$34*MIN(1,$D$2/3),0)) -> 0 | P36: =M36+N36+O36 -> 8507.835 | Q36: =P36/(1+Hypothèses!$B$6) -> 7089.8625 | R36: =Hypothèses!$B$3*(1+Hypothèses!$B$4)^INT((A36-1)/3) -> 2022.7789 | S36: =0 -> 0 | T36: =S36*Hypothèses!$B$17 -> 0 | U36: =Q36*Hypothèses!$B$5 -> 70.898625 | V36: =Q36-R36-T36-U36 -> 4996.185 | W36: =W35+V36 -> 73205.961
A37: 34 | B37: =INT((A37-1)/12)+1 -> 3 | C37: =ROUND(IF(MOD($A37,12)=0,G37,(IF(37=4,0,C36))*(1-$K37)+IF((IF(37=4,0,C36))*(1-$K37)<G37,(G37-(IF(37=4,0,C36))*(1-$K37))*Hypothèses!$B$10,0)),1) -> 11.9 | D37: =ROUND(IF(MOD($A37,12)=0,H37,(IF(37=4,0,D36))*(1-$K37)+IF((IF(37=4,0,D36))*(1-$K37)<H37,(H37-(IF(37=4,0,D36))*(1-$K37))*Hypothèses!$B$10,0)),1) -> 41.6 | E37: =ROUND(IF(MOD($A37,12)=0,I37,(IF(37=4,0,E36))*(1-$K37)+IF((IF(37=4,0,E36))*(1-$K37)<I37,(I37-(IF(37=4,0,E36))*(1-$K37))*Hypothèses!$B$10,0)),1) -> 1.6 | F37: =ROUND(IF(MOD($A37,12)=0,J37,(IF(37=4,0,F36))*(1-$K37)+IF((IF(37=4,0,F36))*(1-$K37)<J37,(J37-(IF(37=4,0,F36))*(1-$K37))*Hypothèses!$B$10,0)),1) -> 1.2 | G37: =(IF(B37=1,0,IF(B37=2,Hypothèses!$B$26,IF(B37=3,Hypothèses!$C$26,Hypothèses!$D$26)))+(IF(B37=1,Hypothèses!$B$26,IF(B37=2,Hypothèses!$C$26,IF(B37=3,Hypothèses!$D$26,Hypothèses!$D$26)))-(IF(B37=1,0,IF(B37=2,Hypothèses!$B$26,IF(B37=3,Hypothèses!$C$26,Hypothèses!$D$26)))))*((A37)-INT((A37-1)/12)*12)/12)*$B$1 -> 12.833333 | H37: =(IF(B37=1,0,IF(B37=2,Hypothèses!$B$27,IF(B37=3,Hypothèses!$C$27,Hypothèses!$D$27)))+(IF(B37=1,Hypothèses!$B$27,IF(B37=2,Hypothèses!$C$27,IF(B37=3,Hypothèses!$D$27,Hypothèses!$D$27)))-(IF(B37=1,0,IF(B37=2,Hypothèses!$B$27,IF(B37=3,Hypothèses!$C$27,Hypothèses!$D$27)))))*((A37)-INT((A37-1)/12)*12)/12)*$B$1 -> 44.916667 | I37: =(IF(B37=1,0,IF(B37=2,Hypothèses!$B$28,IF(B37=3,Hypothèses!$C$28,Hypothèses!$D$28)))+(IF(B37=1,Hypothèses!$B$28,IF(B37=2,Hypothèses!$C$28,IF(B37=3,Hypothèses!$D$28,Hypothèses!$D$28)))-(IF(B37=1,0,IF(B37=2,Hypothèses!$B$28,IF(B37=3,Hypothèses!$C$28,Hypothèses!$D$28)))))*((A37)-INT((A37-1)/12)*12)/12)*$B$1 -> 1.8666667 | J37: =(IF(B37=1,0,IF(B37=2,Hypothèses!$B$29,IF(B37=3,Hypothèses!$C$29,Hypothèses!$D$29)))+(IF(B37=1,Hypothèses!$B$29,IF(B37=2,Hypothèses!$C$29,IF(B37=3,Hypothèses!$D$29,Hypothèses!$D$29)))-(IF(B37=1,0,IF(B37=2,Hypothèses!$B$29,IF(B37=3,Hypothèses!$C$29,Hypothèses!$D$29)))))*((A37)-INT((A37-1)/12)*12)/12)*$B$1 -> 1.2833333 | K37: =IF(A37<Hypothèses!$B$7,0,Hypothèses!$B$8*(1-Hypothèses!$B$9)^(A37-Hypothèses!$B$7)) -> 0.0035894899 | L37: =C37+D37+E37+F37 -> 56.3 | M37: =(C37*Hypothèses!$B$11+D37*Hypothèses!$B$12+E37*Hypothèses!$B$13+F37*Hypothèses!$B$14)*(IF(B37=1,Hypothèses!$B$20,IF(B37=2,Hypothèses!$B$21,Hypothèses!$B$22))+(1-(IF(B37=1,Hypothèses!$B$20,IF(B37=2,Hypothèses!$B$21,Hypothèses!$B$22))))*11/12) -> 8781.705 | N37: =L37*IF(B37=1,Hypothèses!$C$20,IF(B37=2,Hypothèses!$C$21,Hypothèses!$C$22))*IF(B37=1,Hypothèses!$D$20,IF(B37=2,Hypothèses!$D$21,Hypothèses!$D$22)) -> 202.68 | O37: =IF(A37=18,IF($B$2>=1,Hypothèses!$B$33,0),IF(AND(OR(A37=30,A37=34),$D$2>=1),Hypothèses!$B$34*MIN(1,$D$2/3),0)) -> 11333.333 | P37: =M37+N37+O37 -> 20317.718 | Q37: =P37/(1+Hypothèses!$B$6) -> 16931.432 | R37: =Hypothèses!$B$3*(1+Hypothèses!$B$4)^INT((A37-1)/3) -> 2326.1957 | S37: =0 -> 0 | T37: =S37*Hypothèses!$B$17 -> 0 | U37: =Q37*Hypothèses!$B$5 -> 169.31432 | V37: =Q37-R37-T37-U37 -> 14435.922 | W37: =W36+V37 -> 87641.883
A38: 35 | B38: =INT((A38-1)/12)+1 -> 3 | C38: =ROUND(IF(MOD($A38,12)=0,G38,(IF(38=4,0,C37))*(1-$K38)+IF((IF(38=4,0,C37))*(1-$K38)<G38,(G38-(IF(38=4,0,C37))*(1-$K38))*Hypothèses!$B$10,0)),1) -> 12.5 | D38: =ROUND(IF(MOD($A38,12)=0,H38,(IF(38=4,0,D37))*(1-$K38)+IF((IF(38=4,0,D37))*(1-$K38)<H38,(H38-(IF(38=4,0,D37))*(1-$K38))*Hypothèses!$B$10,0)),1) -> 43.7 | E38: =ROUND(IF(MOD($A38,12)=0,I38,(IF(38=4,0,E37))*(1-$K38)+IF((IF(38=4,0,E37))*(1-$K38)<I38,(I38-(IF(38=4,0,E37))*(1-$K38))*Hypothèses!$B$10,0)),1) -> 1.8 | F38: =ROUND(IF(MOD($A38,12)=0,J38,(IF(38=4,0,F37))*(1-$K38)+IF((IF(38=4,0,F37))*(1-$K38)<J38,(J38-(IF(38=4,0,F37))*(1-$K38))*Hypothèses!$B$10,0)),1) -> 1.3 | G38: =(IF(B38=1,0,IF(B38=2,Hypothèses!$B$26,IF(B38=3,Hypothèses!$C$26,Hypothèses!$D$26)))+(IF(B38=1,Hypothèses!$B$26,IF(B38=2,Hypothèses!$C$26,IF(B38=3,Hypothèses!$D$26,Hypothèses!$D$26)))-(IF(B38=1,0,IF(B38=2,Hypothèses!$B$26,IF(B38=3,Hypothèses!$C$26,Hypothèses!$D$26)))))*((A38)-INT((A38-1)/12)*12)/12)*$B$1 -> 13.416667 | H38: =(IF(B38=1,0,IF(B38=2,Hypothèses!$B$27,IF(B38=3,Hypothèses!$C$27,Hypothèses!$D$27)))+(IF(B38=1,Hypothèses!$B$27,IF(B38=2,Hypothèses!$C$27,IF(B38=3,Hypothèses!$D$27,Hypothèses!$D$27)))-(IF(B38=1,0,IF(B38=2,Hypothèses!$B$27,IF(B38=3,Hypothèses!$C$27,Hypothèses!$D$27)))))*((A38)-INT((A38-1)/12)*12)/12)*$B$1 -> 46.958333 | I38: =(IF(B38=1,0,IF(B38=2,Hypothèses!$B$28,IF(B38=3,Hypothèses!$C$28,Hypothèses!$D$28)))+(IF(B38=1,Hypothèses!$B$28,IF(B38=2,Hypothèses!$C$28,IF(B38=3,Hypothèses!$D$28,Hypothèses!$D$28)))-(IF(B38=1,0,IF(B38=2,Hypothèses!$B$28,IF(B38=3,Hypothèses!$C$28,Hypothèses!$D$28)))))*((A38)-INT((A38-1)/12)*12)/12)*$B$1 -> 1.9833333 | J38: =(IF(B38=1,0,IF(B38=2,Hypothèses!$B$29,IF(B38=3,Hypothèses!$C$29,Hypothèses!$D$29)))+(IF(B38=1,Hypothèses!$B$29,IF(B38=2,Hypothèses!$C$29,IF(B38=3,Hypothèses!$D$29,Hypothèses!$D$29)))-(IF(B38=1,0,IF(B38=2,Hypothèses!$B$29,IF(B38=3,Hypothèses!$C$29,Hypothèses!$D$29)))))*((A38)-INT((A38-1)/12)*12)/12)*$B$1 -> 1.3416667 | K38: =IF(A38<Hypothèses!$B$7,0,Hypothèses!$B$8*(1-Hypothèses!$B$9)^(A38-Hypothèses!$B$7)) -> 0.0032305409 | L38: =C38+D38+E38+F38 -> 59.3 | M38: =(C38*Hypothèses!$B$11+D38*Hypothèses!$B$12+E38*Hypothèses!$B$13+F38*Hypothèses!$B$14)*(IF(B38=1,Hypothèses!$B$20,IF(B38=2,Hypothèses!$B$21,Hypothèses!$B$22))+(1-(IF(B38=1,Hypothèses!$B$20,IF(B38=2,Hypothèses!$B$21,Hypothèses!$B$22))))*11/12) -> 9318.55 | N38: =L38*IF(B38=1,Hypothèses!$C$20,IF(B38=2,Hypothèses!$C$21,Hypothèses!$C$22))*IF(B38=1,Hypothèses!$D$20,IF(B38=2,Hypothèses!$D$21,Hypothèses!$D$22)) -> 213.48 | O38: =IF(A38=18,IF($B$2>=1,Hypothèses!$B$33,0),IF(AND(OR(A38=30,A38=34),$D$2>=1),Hypothèses!$B$34*MIN(1,$D$2/3),0)) -> 0 | P38: =M38+N38+O38 -> 9532.03 | Q38: =P38/(1+Hypothèses!$B$6) -> 7943.3583 | R38: =Hypothèses!$B$3*(1+Hypothèses!$B$4)^INT((A38-1)/3) -> 2326.1957 | S38: =0 -> 0 | T38: =S38*Hypothèses!$B$17 -> 0 | U38: =Q38*Hypothèses!$B$5 -> 79.433583 | V38: =Q38-R38-T38-U38 -> 5537.7291 | W38: =W37+V38 -> 93179.612
A39: 36 | B39: =INT((A39-1)/12)+1 -> 3 | C39: =ROUND(IF(MOD($A39,12)=0,G39,(IF(39=4,0,C38))*(1-$K39)+IF((IF(39=4,0,C38))*(1-$K39)<G39,(G39-(IF(39=4,0,C38))*(1-$K39))*Hypothèses!$B$10,0)),1) -> 14 | D39: =ROUND(IF(MOD($A39,12)=0,H39,(IF(39=4,0,D38))*(1-$K39)+IF((IF(39=4,0,D38))*(1-$K39)<H39,(H39-(IF(39=4,0,D38))*(1-$K39))*Hypothèses!$B$10,0)),1) -> 49 | E39: =ROUND(IF(MOD($A39,12)=0,I39,(IF(39=4,0,E38))*(1-$K39)+IF((IF(39=4,0,E38))*(1-$K39)<I39,(I39-(IF(39=4,0,E38))*(1-$K39))*Hypothèses!$B$10,0)),1) -> 2.1 | F39: =ROUND(IF(MOD($A39,12)=0,J39,(IF(39=4,0,F38))*(1-$K39)+IF((IF(39=4,0,F38))*(1-$K39)<J39,(J39-(IF(39=4,0,F38))*(1-$K39))*Hypothèses!$B$10,0)),1) -> 1.4 | G39: =(IF(B39=1,0,IF(B39=2,Hypothèses!$B$26,IF(B39=3,Hypothèses!$C$26,Hypothèses!$D$26)))+(IF(B39=1,Hypothèses!$B$26,IF(B39=2,Hypothèses!$C$26,IF(B39=3,Hypothèses!$D$26,Hypothèses!$D$26)))-(IF(B39=1,0,IF(B39=2,Hypothèses!$B$26,IF(B39=3,Hypothèses!$C$26,Hypothèses!$D$26)))))*((A39)-INT((A39-1)/12)*12)/12)*$B$1 -> 14 | H39: =(IF(B39=1,0,IF(B39=2,Hypothèses!$B$27,IF(B39=3,Hypothèses!$C$27,Hypothèses!$D$27)))+(IF(B39=1,Hypothèses!$B$27,IF(B39=2,Hypothèses!$C$27,IF(B39=3,Hypothèses!$D$27,Hypothèses!$D$27)))-(IF(B39=1,0,IF(B39=2,Hypothèses!$B$27,IF(B39=3,Hypothèses!$C$27,Hypothèses!$D$27)))))*((A39)-INT((A39-1)/12)*12)/12)*$B$1 -> 49 | I39: =(IF(B39=1,0,IF(B39=2,Hypothèses!$B$28,IF(B39=3,Hypothèses!$C$28,Hypothèses!$D$28)))+(IF(B39=1,Hypothèses!$B$28,IF(B39=2,Hypothèses!$C$28,IF(B39=3,Hypothèses!$D$28,Hypothèses!$D$28)))-(IF(B39=1,0,IF(B39=2,Hypothèses!$B$28,IF(B39=3,Hypothèses!$C$28,Hypothèses!$D$28)))))*((A39)-INT((A39-1)/12)*12)/12)*$B$1 -> 2.1 | J39: =(IF(B39=1,0,IF(B39=2,Hypothèses!$B$29,IF(B39=3,Hypothèses!$C$29,Hypothèses!$D$29)))+(IF(B39=1,Hypothèses!$B$29,IF(B39=2,Hypothèses!$C$29,IF(B39=3,Hypothèses!$D$29,Hypothèses!$D$29)))-(IF(B39=1,0,IF(B39=2,Hypothèses!$B$29,IF(B39=3,Hypothèses!$C$29,Hypothèses!$D$29)))))*((A39)-INT((A39-1)/12)*12)/12)*$B$1 -> 1.4 | K39: =IF(A39<Hypothèses!$B$7,0,Hypothèses!$B$8*(1-Hypothèses!$B$9)^(A39-Hypothèses!$B$7)) -> 0.0029074869 | L39: =C39+D39+E39+F39 -> 66.5 | M39: =(C39*Hypothèses!$B$11+D39*Hypothèses!$B$12+E39*Hypothèses!$B$13+F39*Hypothèses!$B$14)*(IF(B39=1,Hypothèses!$B$20,IF(B39=2,Hypothèses!$B$21,Hypothèses!$B$22))+(1-(IF(B39=1,Hypothèses!$B$20,IF(B39=2,Hypothèses!$B$21,Hypothèses!$B$22))))*11/12) -> 10431.855 | N39: =L39*IF(B39=1,Hypothèses!$C$20,IF(B39=2,Hypothèses!$C$21,Hypothèses!$C$22))*IF(B39=1,Hypothèses!$D$20,IF(B39=2,Hypothèses!$D$21,Hypothèses!$D$22)) -> 239.4 | O39: =IF(A39=18,IF($B$2>=1,Hypothèses!$B$33,0),IF(AND(OR(A39=30,A39=34),$D$2>=1),Hypothèses!$B$34*MIN(1,$D$2/3),0)) -> 0 | P39: =M39+N39+O39 -> 10671.255 | Q39: =P39/(1+Hypothèses!$B$6) -> 8892.7125 | R39: =Hypothèses!$B$3*(1+Hypothèses!$B$4)^INT((A39-1)/3) -> 2326.1957 | S39: =0 -> 0 | T39: =S39*Hypothèses!$B$17 -> 0 | U39: =Q39*Hypothèses!$B$5 -> 88.927125 | V39: =Q39-R39-T39-U39 -> 6477.5897 | W39: =W38+V39 -> 99657.201
A41: Synthèse annuelle
A42: Année | B42: CA HT | C42: EBITDA | D42: Sous-traitance dev | E42: Trésorerie fin
A43: A1 | B43: =SUMIF($B$4:$B$39,1,$Q$4:$Q$39) -> 5803.9583 | C43: =SUMIF($B$4:$B$39,1,$V$4:$V$39) -> -1744.1437 | D43: =SUMIF($B$4:$B$39,1,$T$4:$T$39) -> 0 | E43: =W15 -> 355.85625
A44: A2 | B44: =SUMIF($B$4:$B$39,2,$Q$4:$Q$39) -> 42255.538 | C44: =SUMIF($B$4:$B$39,2,$V$4:$V$39) -> 28732.817 | D44: =SUMIF($B$4:$B$39,2,$T$4:$T$39) -> 0 | E44: =W27 -> 29088.673
A45: A3 | B45: =SUMIF($B$4:$B$39,3,$Q$4:$Q$39) -> 94425.051 | C45: =SUMIF($B$4:$B$39,3,$V$4:$V$39) -> 70568.528 | D45: =SUMIF($B$4:$B$39,3,$T$4:$T$39) -> 0 | E45: =W39 -> 99657.201
A47: Effectifs fin A3 (cible × facteur)
A48: =ROUND(Hypothèses!$D$26*$B$1,0)&" Atelier · "&ROUND(Hypothèses!$D$27*$B$1,0)&" Horizon · "&ROUND(Hypothèses!$D$28*$B$1,0)&" Enverg. · "&ROUND(Hypothèses!$D$29*$B$1,0)&" Rayonn." -> 14 Atelier · 49 Horizon · 2 Enverg. · 1 Rayonn.

Sheet Base
A1: Facteur clients (scénario) | B1: 1
A2: Zénith fin A2 (cible) | B2: =ROUND(Hypothèses!$C$30*$B$1,0) -> 1 | C2: Zénith fin A3 (cible) | D2: =ROUND(Hypothèses!$D$30*$B$1,0) -> 3
A3: Mois | B3: Année | C3: Atelier | D3: Horizon | E3: Envergure | F3: Rayonnement | G3: Cible Atelier | H3: Cible Horizon | I3: Cible Enverg. | J3: Cible Rayonn. | K3: Taux churn | L3: Clients payants | M3: MRR abo TTC | N3: Options TTC | O3: Zénith TTC | P3: CA TTC | Q3: CA HT | R3: Frais fixes infra | S3: Nb développeurs | T3: Sous-traitance dev (HT) | U3: Frais variables 1% | V3: EBITDA | W3: Trésorerie
A4: 1 | B4: =INT((A4-1)/12)+1 -> 1 | C4: =ROUND(IF(MOD($A4,12)=0,G4,(IF(4=4,0,C3))*(1-$K4)+IF((IF(4=4,0,C3))*(1-$K4)<G4,(G4-(IF(4=4,0,C3))*(1-$K4))*Hypothèses!$B$10,0)),1) -> 0.2 | D4: =ROUND(IF(MOD($A4,12)=0,H4,(IF(4=4,0,D3))*(1-$K4)+IF((IF(4=4,0,D3))*(1-$K4)<H4,(H4-(IF(4=4,0,D3))*(1-$K4))*Hypothèses!$B$10,0)),1) -> 0.3 | E4: =ROUND(IF(MOD($A4,12)=0,I4,(IF(4=4,0,E3))*(1-$K4)+IF((IF(4=4,0,E3))*(1-$K4)<I4,(I4-(IF(4=4,0,E3))*(1-$K4))*Hypothèses!$B$10,0)),1) -> 0 | F4: =ROUND(IF(MOD($A4,12)=0,J4,(IF(4=4,0,F3))*(1-$K4)+IF((IF(4=4,0,F3))*(1-$K4)<J4,(J4-(IF(4=4,0,F3))*(1-$K4))*Hypothèses!$B$10,0)),1) -> 0 | G4: =(IF(B4=1,0,IF(B4=2,Hypothèses!$B$26,IF(B4=3,Hypothèses!$C$26,Hypothèses!$D$26)))+(IF(B4=1,Hypothèses!$B$26,IF(B4=2,Hypothèses!$C$26,IF(B4=3,Hypothèses!$D$26,Hypothèses!$D$26)))-(IF(B4=1,0,IF(B4=2,Hypothèses!$B$26,IF(B4=3,Hypothèses!$C$26,Hypothèses!$D$26)))))*((A4)-INT((A4-1)/12)*12)/12)*$B$1 -> 0.41666667 | H4: =(IF(B4=1,0,IF(B4=2,Hypothèses!$B$27,IF(B4=3,Hypothèses!$C$27,Hypothèses!$D$27)))+(IF(B4=1,Hypothèses!$B$27,IF(B4=2,Hypothèses!$C$27,IF(B4=3,Hypothèses!$D$27,Hypothèses!$D$27)))-(IF(B4=1,0,IF(B4=2,Hypothèses!$B$27,IF(B4=3,Hypothèses!$C$27,Hypothèses!$D$27)))))*((A4)-INT((A4-1)/12)*12)/12)*$B$1 -> 0.83333333 | I4: =(IF(B4=1,0,IF(B4=2,Hypothèses!$B$28,IF(B4=3,Hypothèses!$C$28,Hypothèses!$D$28)))+(IF(B4=1,Hypothèses!$B$28,IF(B4=2,Hypothèses!$C$28,IF(B4=3,Hypothèses!$D$28,Hypothèses!$D$28)))-(IF(B4=1,0,IF(B4=2,Hypothèses!$B$28,IF(B4=3,Hypothèses!$C$28,Hypothèses!$D$28)))))*((A4)-INT((A4-1)/12)*12)/12)*$B$1 -> 0 | J4: =(IF(B4=1,0,IF(B4=2,Hypothèses!$B$29,IF(B4=3,Hypothèses!$C$29,Hypothèses!$D$29)))+(IF(B4=1,Hypothèses!$B$29,IF(B4=2,Hypothèses!$C$29,IF(B4=3,Hypothèses!$D$29,Hypothèses!$D$29)))-(IF(B4=1,0,IF(B4=2,Hypothèses!$B$29,IF(B4=3,Hypothèses!$C$29,Hypothèses!$D$29)))))*((A4)-INT((A4-1)/12)*12)/12)*$B$1 -> 0 | K4: =IF(A4<Hypothèses!$B$7,0,Hypothèses!$B$8*(1-Hypothèses!$B$9)^(A4-Hypothèses!$B$7)) -> 0 | L4: =C4+D4+E4+F4 -> 0.5 | M4: =(C4*Hypothèses!$B$11+D4*Hypothèses!$B$12+E4*Hypothèses!$B$13+F4*Hypothèses!$B$14)*(IF(B4=1,Hypothèses!$B$20,IF(B4=2,Hypothèses!$B$21,Hypothèses!$B$22))+(1-(IF(B4=1,Hypothèses!$B$20,IF(B4=2,Hypothèses!$B$21,Hypothèses!$B$22))))*11/12) -> 60.416667 | N4: =L4*IF(B4=1,Hypothèses!$C$20,IF(B4=2,Hypothèses!$C$21,Hypothèses!$C$22))*IF(B4=1,Hypothèses!$D$20,IF(B4=2,Hypothèses!$D$21,Hypothèses!$D$22)) -> 0.5 | O4: =IF(A4=18,IF($B$2>=1,Hypothèses!$B$33,0),IF(AND(OR(A4=30,A4=34),$D$2>=1),Hypothèses!$B$34*MIN(1,$D$2/3),0)) -> 0 | P4: =M4+N4+O4 -> 60.916667 | Q4: =P4/(1+Hypothèses!$B$6) -> 50.763889 | R4: =Hypothèses!$B$3*(1+Hypothèses!$B$4)^INT((A4-1)/3) -> 500 | S4: =IF($A4>=13,1,0) -> 0 | T4: =S4*Hypothèses!$B$17 -> 0 | U4: =Q4*Hypothèses!$B$5 -> 0.50763889 | V4: =Q4-R4-T4-U4 -> -449.74375 | W4: =Hypothèses!$B$2+V4 -> 1650.2562
A5: 2 | B5: =INT((A5-1)/12)+1 -> 1 | C5: =ROUND(IF(MOD($A5,12)=0,G5,(IF(5=4,0,C4))*(1-$K5)+IF((IF(5=4,0,C4))*(1-$K5)<G5,(G5-(IF(5=4,0,C4))*(1-$K5))*Hypothèses!$B$10,0)),1) -> 0.5 | D5: =ROUND(IF(MOD($A5,12)=0,H5,(IF(5=4,0,D4))*(1-$K5)+IF((IF(5=4,0,D4))*(1-$K5)<H5,(H5-(IF(5=4,0,D4))*(1-$K5))*Hypothèses!$B$10,0)),1) -> 0.8 | E5: =ROUND(IF(MOD($A5,12)=0,I5,(IF(5=4,0,E4))*(1-$K5)+IF((IF(5=4,0,E4))*(1-$K5)<I5,(I5-(IF(5=4,0,E4))*(1-$K5))*Hypothèses!$B$10,0)),1) -> 0 | F5: =ROUND(IF(MOD($A5,12)=0,J5,(IF(5=4,0,F4))*(1-$K5)+IF((IF(5=4,0,F4))*(1-$K5)<J5,(J5-(IF(5=4,0,F4))*(1-$K5))*Hypothèses!$B$10,0)),1) -> 0 | G5: =(IF(B5=1,0,IF(B5=2,Hypothèses!$B$26,IF(B5=3,Hypothèses!$C$26,Hypothèses!$D$26)))+(IF(B5=1,Hypothèses!$B$26,IF(B5=2,Hypothèses!$C$26,IF(B5=3,Hypothèses!$D$26,Hypothèses!$D$26)))-(IF(B5=1,0,IF(B5=2,Hypothèses!$B$26,IF(B5=3,Hypothèses!$C$26,Hypothèses!$D$26)))))*((A5)-INT((A5-1)/12)*12)/12)*$B$1 -> 0.83333333 | H5: =(IF(B5=1,0,IF(B5=2,Hypothèses!$B$27,IF(B5=3,Hypothèses!$C$27,Hypothèses!$D$27)))+(IF(B5=1,Hypothèses!$B$27,IF(B5=2,Hypothèses!$C$27,IF(B5=3,Hypothèses!$D$27,Hypothèses!$D$27)))-(IF(B5=1,0,IF(B5=2,Hypothèses!$B$27,IF(B5=3,Hypothèses!$C$27,Hypothèses!$D$27)))))*((A5)-INT((A5-1)/12)*12)/12)*$B$1 -> 1.6666667 | I5: =(IF(B5=1,0,IF(B5=2,Hypothèses!$B$28,IF(B5=3,Hypothèses!$C$28,Hypothèses!$D$28)))+(IF(B5=1,Hypothèses!$B$28,IF(B5=2,Hypothèses!$C$28,IF(B5=3,Hypothèses!$D$28,Hypothèses!$D$28)))-(IF(B5=1,0,IF(B5=2,Hypothèses!$B$28,IF(B5=3,Hypothèses!$C$28,Hypothèses!$D$28)))))*((A5)-INT((A5-1)/12)*12)/12)*$B$1 -> 0 | J5: =(IF(B5=1,0,IF(B5=2,Hypothèses!$B$29,IF(B5=3,Hypothèses!$C$29,Hypothèses!$D$29)))+(IF(B5=1,Hypothèses!$B$29,IF(B5=2,Hypothèses!$C$29,IF(B5=3,Hypothèses!$D$29,Hypothèses!$D$29)))-(IF(B5=1,0,IF(B5=2,Hypothèses!$B$29,IF(B5=3,Hypothèses!$C$29,Hypothèses!$D$29)))))*((A5)-INT((A5-1)/12)*12)/12)*$B$1 -> 0 | K5: =IF(A5<Hypothèses!$B$7,0,Hypothèses!$B$8*(1-Hypothèses!$B$9)^(A5-Hypothèses!$B$7)) -> 0 | L5: =C5+D5+E5+F5 -> 1.3 | M5: =(C5*Hypothèses!$B$11+D5*Hypothèses!$B$12+E5*Hypothèses!$B$13+F5*Hypothèses!$B$14)*(IF(B5=1,Hypothèses!$B$20,IF(B5=2,Hypothèses!$B$21,Hypothèses!$B$22))+(1-(IF(B5=1,Hypothèses!$B$20,IF(B5=2,Hypothèses!$B$21,Hypothèses!$B$22))))*11/12) -> 158.24333 | N5: =L5*IF(B5=1,Hypothèses!$C$20,IF(B5=2,Hypothèses!$C$21,Hypothèses!$C$22))*IF(B5=1,Hypothèses!$D$20,IF(B5=2,Hypothèses!$D$21,Hypothèses!$D$22)) -> 1.3 | O5: =IF(A5=18,IF($B$2>=1,Hypothèses!$B$33,0),IF(AND(OR(A5=30,A5=34),$D$2>=1),Hypothèses!$B$34*MIN(1,$D$2/3),0)) -> 0 | P5: =M5+N5+O5 -> 159.54333 | Q5: =P5/(1+Hypothèses!$B$6) -> 132.95278 | R5: =Hypothèses!$B$3*(1+Hypothèses!$B$4)^INT((A5-1)/3) -> 500 | S5: =IF($A5>=13,1,0) -> 0 | T5: =S5*Hypothèses!$B$17 -> 0 | U5: =Q5*Hypothèses!$B$5 -> 1.3295278 | V5: =Q5-R5-T5-U5 -> -368.37675 | W5: =W4+V5 -> 1281.8795
A6: 3 | B6: =INT((A6-1)/12)+1 -> 1 | C6: =ROUND(IF(MOD($A6,12)=0,G6,(IF(6=4,0,C5))*(1-$K6)+IF((IF(6=4,0,C5))*(1-$K6)<G6,(G6-(IF(6=4,0,C5))*(1-$K6))*Hypothèses!$B$10,0)),1) -> 0.8 | D6: =ROUND(IF(MOD($A6,12)=0,H6,(IF(6=4,0,D5))*(1-$K6)+IF((IF(6=4,0,D5))*(1-$K6)<H6,(H6-(IF(6=4,0,D5))*(1-$K6))*Hypothèses!$B$10,0)),1) -> 1.5 | E6: =ROUND(IF(MOD($A6,12)=0,I6,(IF(6=4,0,E5))*(1-$K6)+IF((IF(6=4,0,E5))*(1-$K6)<I6,(I6-(IF(6=4,0,E5))*(1-$K6))*Hypothèses!$B$10,0)),1) -> 0 | F6: =ROUND(IF(MOD($A6,12)=0,J6,(IF(6=4,0,F5))*(1-$K6)+IF((IF(6=4,0,F5))*(1-$K6)<J6,(J6-(IF(6=4,0,F5))*(1-$K6))*Hypothèses!$B$10,0)),1) -> 0 | G6: =(IF(B6=1,0,IF(B6=2,Hypothèses!$B$26,IF(B6=3,Hypothèses!$C$26,Hypothèses!$D$26)))+(IF(B6=1,Hypothèses!$B$26,IF(B6=2,Hypothèses!$C$26,IF(B6=3,Hypothèses!$D$26,Hypothèses!$D$26)))-(IF(B6=1,0,IF(B6=2,Hypothèses!$B$26,IF(B6=3,Hypothèses!$C$26,Hypothèses!$D$26)))))*((A6)-INT((A6-1)/12)*12)/12)*$B$1 -> 1.25 | H6: =(IF(B6=1,0,IF(B6=2,Hypothèses!$B$27,IF(B6=3,Hypothèses!$C$27,Hypothèses!$D$27)))+(IF(B6=1,Hypothèses!$B$27,IF(B6=2,Hypothèses!$C$27,IF(B6=3,Hypothèses!$D$27,Hypothèses!$D$27)))-(IF(B6=1,0,IF(B6=2,Hypothèses!$B$27,IF(B6=3,Hypothèses!$C$27,Hypothèses!$D$27)))))*((A6)-INT((A6-1)/12)*12)/12)*$B$1 -> 2.5 | I6: =(IF(B6=1,0,IF(B6=2,Hypothèses!$B$28,IF(B6=3,Hypothèses!$C$28,Hypothèses!$D$28)))+(IF(B6=1,Hypothèses!$B$28,IF(B6=2,Hypothèses!$C$28,IF(B6=3,Hypothèses!$D$28,Hypothèses!$D$28)))-(IF(B6=1,0,IF(B6=2,Hypothèses!$B$28,IF(B6=3,Hypothèses!$C$28,Hypothèses!$D$28)))))*((A6)-INT((A6-1)/12)*12)/12)*$B$1 -> 0 | J6: =(IF(B6=1,0,IF(B6=2,Hypothèses!$B$29,IF(B6=3,Hypothèses!$C$29,Hypothèses!$D$29)))+(IF(B6=1,Hypothèses!$B$29,IF(B6=2,Hypothèses!$C$29,IF(B6=3,Hypothèses!$D$29,Hypothèses!$D$29)))-(IF(B6=1,0,IF(B6=2,Hypothèses!$B$29,IF(B6=3,Hypothèses!$C$29,Hypothèses!$D$29)))))*((A6)-INT((A6-1)/12)*12)/12)*$B$1 -> 0 | K6: =IF(A6<Hypothèses!$B$7,0,Hypothèses!$B$8*(1-Hypothèses!$B$9)^(A6-Hypothèses!$B$7)) -> 0 | L6: =C6+D6+E6+F6 -> 2.3 | M6: =(C6*Hypothèses!$B$11+D6*Hypothèses!$B$12+E6*Hypothèses!$B$13+F6*Hypothèses!$B$14)*(IF(B6=1,Hypothèses!$B$20,IF(B6=2,Hypothèses!$B$21,Hypothèses!$B$22))+(1-(IF(B6=1,Hypothèses!$B$20,IF(B6=2,Hypothèses!$B$21,Hypothèses!$B$22))))*11/12) -> 284.87667 | N6: =L6*IF(B6=1,Hypothèses!$C$20,IF(B6=2,Hypothèses!$C$21,Hypothèses!$C$22))*IF(B6=1,Hypothèses!$D$20,IF(B6=2,Hypothèses!$D$21,Hypothèses!$D$22)) -> 2.3 | O6: =IF(A6=18,IF($B$2>=1,Hypothèses!$B$33,0),IF(AND(OR(A6=30,A6=34),$D$2>=1),Hypothèses!$B$34*MIN(1,$D$2/3),0)) -> 0 | P6: =M6+N6+O6 -> 287.17667 | Q6: =P6/(1+Hypothèses!$B$6) -> 239.31389 | R6: =Hypothèses!$B$3*(1+Hypothèses!$B$4)^INT((A6-1)/3) -> 500 | S6: =IF($A6>=13,1,0) -> 0 | T6: =S6*Hypothèses!$B$17 -> 0 | U6: =Q6*Hypothèses!$B$5 -> 2.3931389 | V6: =Q6-R6-T6-U6 -> -263.07925 | W6: =W5+V6 -> 1018.8003
A7: 4 | B7: =INT((A7-1)/12)+1 -> 1 | C7: =ROUND(IF(MOD($A7,12)=0,G7,(IF(7=4,0,C6))*(1-$K7)+IF((IF(7=4,0,C6))*(1-$K7)<G7,(G7-(IF(7=4,0,C6))*(1-$K7))*Hypothèses!$B$10,0)),1) -> 1.1 | D7: =ROUND(IF(MOD($A7,12)=0,H7,(IF(7=4,0,D6))*(1-$K7)+IF((IF(7=4,0,D6))*(1-$K7)<H7,(H7-(IF(7=4,0,D6))*(1-$K7))*Hypothèses!$B$10,0)),1) -> 2.2 | E7: =ROUND(IF(MOD($A7,12)=0,I7,(IF(7=4,0,E6))*(1-$K7)+IF((IF(7=4,0,E6))*(1-$K7)<I7,(I7-(IF(7=4,0,E6))*(1-$K7))*Hypothèses!$B$10,0)),1) -> 0 | F7: =ROUND(IF(MOD($A7,12)=0,J7,(IF(7=4,0,F6))*(1-$K7)+IF((IF(7=4,0,F6))*(1-$K7)<J7,(J7-(IF(7=4,0,F6))*(1-$K7))*Hypothèses!$B$10,0)),1) -> 0 | G7: =(IF(B7=1,0,IF(B7=2,Hypothèses!$B$26,IF(B7=3,Hypothèses!$C$26,Hypothèses!$D$26)))+(IF(B7=1,Hypothèses!$B$26,IF(B7=2,Hypothèses!$C$26,IF(B7=3,Hypothèses!$D$26,Hypothèses!$D$26)))-(IF(B7=1,0,IF(B7=2,Hypothèses!$B$26,IF(B7=3,Hypothèses!$C$26,Hypothèses!$D$26)))))*((A7)-INT((A7-1)/12)*12)/12)*$B$1 -> 1.6666667 | H7: =(IF(B7=1,0,IF(B7=2,Hypothèses!$B$27,IF(B7=3,Hypothèses!$C$27,Hypothèses!$D$27)))+(IF(B7=1,Hypothèses!$B$27,IF(B7=2,Hypothèses!$C$27,IF(B7=3,Hypothèses!$D$27,Hypothèses!$D$27)))-(IF(B7=1,0,IF(B7=2,Hypothèses!$B$27,IF(B7=3,Hypothèses!$C$27,Hypothèses!$D$27)))))*((A7)-INT((A7-1)/12)*12)/12)*$B$1 -> 3.3333333 | I7: =(IF(B7=1,0,IF(B7=2,Hypothèses!$B$28,IF(B7=3,Hypothèses!$C$28,Hypothèses!$D$28)))+(IF(B7=1,Hypothèses!$B$28,IF(B7=2,Hypothèses!$C$28,IF(B7=3,Hypothèses!$D$28,Hypothèses!$D$28)))-(IF(B7=1,0,IF(B7=2,Hypothèses!$B$28,IF(B7=3,Hypothèses!$C$28,Hypothèses!$D$28)))))*((A7)-INT((A7-1)/12)*12)/12)*$B$1 -> 0 | J7: =(IF(B7=1,0,IF(B7=2,Hypothèses!$B$29,IF(B7=3,Hypothèses!$C$29,Hypothèses!$D$29)))+(IF(B7=1,Hypothèses!$B$29,IF(B7=2,Hypothèses!$C$29,IF(B7=3,Hypothèses!$D$29,Hypothèses!$D$29)))-(IF(B7=1,0,IF(B7=2,Hypothèses!$B$29,IF(B7=3,Hypothèses!$C$29,Hypothèses!$D$29)))))*((A7)-INT((A7-1)/12)*12)/12)*$B$1 -> 0 | K7: =IF(A7<Hypothèses!$B$7,0,Hypothèses!$B$8*(1-Hypothèses!$B$9)^(A7-Hypothèses!$B$7)) -> 0 | L7: =C7+D7+E7+F7 -> 3.3 | M7: =(C7*Hypothèses!$B$11+D7*Hypothèses!$B$12+E7*Hypothèses!$B$13+F7*Hypothèses!$B$14)*(IF(B7=1,Hypothèses!$B$20,IF(B7=2,Hypothèses!$B$21,Hypothèses!$B$22))+(1-(IF(B7=1,Hypothèses!$B$20,IF(B7=2,Hypothèses!$B$21,Hypothèses!$B$22))))*11/12) -> 411.51 | N7: =L7*IF(B7=1,Hypothèses!$C$20,IF(B7=2,Hypothèses!$C$21,Hypothèses!$C$22))*IF(B7=1,Hypothèses!$D$20,IF(B7=2,Hypothèses!$D$21,Hypothèses!$D$22)) -> 3.3 | O7: =IF(A7=18,IF($B$2>=1,Hypothèses!$B$33,0),IF(AND(OR(A7=30,A7=34),$D$2>=1),Hypothèses!$B$34*MIN(1,$D$2/3),0)) -> 0 | P7: =M7+N7+O7 -> 414.81 | Q7: =P7/(1+Hypothèses!$B$6) -> 345.675 | R7: =Hypothèses!$B$3*(1+Hypothèses!$B$4)^INT((A7-1)/3) -> 575 | S7: =IF($A7>=13,1,0) -> 0 | T7: =S7*Hypothèses!$B$17 -> 0 | U7: =Q7*Hypothèses!$B$5 -> 3.45675 | V7: =Q7-R7-T7-U7 -> -232.78175 | W7: =W6+V7 -> 786.0185
A8: 5 | B8: =INT((A8-1)/12)+1 -> 1 | C8: =ROUND(IF(MOD($A8,12)=0,G8,(IF(8=4,0,C7))*(1-$K8)+IF((IF(8=4,0,C7))*(1-$K8)<G8,(G8-(IF(8=4,0,C7))*(1-$K8))*Hypothèses!$B$10,0)),1) -> 1.5 | D8: =ROUND(IF(MOD($A8,12)=0,H8,(IF(8=4,0,D7))*(1-$K8)+IF((IF(8=4,0,D7))*(1-$K8)<H8,(H8-(IF(8=4,0,D7))*(1-$K8))*Hypothèses!$B$10,0)),1) -> 3 | E8: =ROUND(IF(MOD($A8,12)=0,I8,(IF(8=4,0,E7))*(1-$K8)+IF((IF(8=4,0,E7))*(1-$K8)<I8,(I8-(IF(8=4,0,E7))*(1-$K8))*Hypothèses!$B$10,0)),1) -> 0 | F8: =ROUND(IF(MOD($A8,12)=0,J8,(IF(8=4,0,F7))*(1-$K8)+IF((IF(8=4,0,F7))*(1-$K8)<J8,(J8-(IF(8=4,0,F7))*(1-$K8))*Hypothèses!$B$10,0)),1) -> 0 | G8: =(IF(B8=1,0,IF(B8=2,Hypothèses!$B$26,IF(B8=3,Hypothèses!$C$26,Hypothèses!$D$26)))+(IF(B8=1,Hypothèses!$B$26,IF(B8=2,Hypothèses!$C$26,IF(B8=3,Hypothèses!$D$26,Hypothèses!$D$26)))-(IF(B8=1,0,IF(B8=2,Hypothèses!$B$26,IF(B8=3,Hypothèses!$C$26,Hypothèses!$D$26)))))*((A8)-INT((A8-1)/12)*12)/12)*$B$1 -> 2.0833333 | H8: =(IF(B8=1,0,IF(B8=2,Hypothèses!$B$27,IF(B8=3,Hypothèses!$C$27,Hypothèses!$D$27)))+(IF(B8=1,Hypothèses!$B$27,IF(B8=2,Hypothèses!$C$27,IF(B8=3,Hypothèses!$D$27,Hypothèses!$D$27)))-(IF(B8=1,0,IF(B8=2,Hypothèses!$B$27,IF(B8=3,Hypothèses!$C$27,Hypothèses!$D$27)))))*((A8)-INT((A8-1)/12)*12)/12)*$B$1 -> 4.1666667 | I8: =(IF(B8=1,0,IF(B8=2,Hypothèses!$B$28,IF(B8=3,Hypothèses!$C$28,Hypothèses!$D$28)))+(IF(B8=1,Hypothèses!$B$28,IF(B8=2,Hypothèses!$C$28,IF(B8=3,Hypothèses!$D$28,Hypothèses!$D$28)))-(IF(B8=1,0,IF(B8=2,Hypothèses!$B$28,IF(B8=3,Hypothèses!$C$28,Hypothèses!$D$28)))))*((A8)-INT((A8-1)/12)*12)/12)*$B$1 -> 0 | J8: =(IF(B8=1,0,IF(B8=2,Hypothèses!$B$29,IF(B8=3,Hypothèses!$C$29,Hypothèses!$D$29)))+(IF(B8=1,Hypothèses!$B$29,IF(B8=2,Hypothèses!$C$29,IF(B8=3,Hypothèses!$D$29,Hypothèses!$D$29)))-(IF(B8=1,0,IF(B8=2,Hypothèses!$B$29,IF(B8=3,Hypothèses!$C$29,Hypothèses!$D$29)))))*((A8)-INT((A8-1)/12)*12)/12)*$B$1 -> 0 | K8: =IF(A8<Hypothèses!$B$7,0,Hypothèses!$B$8*(1-Hypothèses!$B$9)^(A8-Hypothèses!$B$7)) -> 0 | L8: =C8+D8+E8+F8 -> 4.5 | M8: =(C8*Hypothèses!$B$11+D8*Hypothèses!$B$12+E8*Hypothèses!$B$13+F8*Hypothèses!$B$14)*(IF(B8=1,Hypothèses!$B$20,IF(B8=2,Hypothèses!$B$21,Hypothèses!$B$22))+(1-(IF(B8=1,Hypothèses!$B$20,IF(B8=2,Hypothèses!$B$21,Hypothèses!$B$22))))*11/12) -> 561.15 | N8: =L8*IF(B8=1,Hypothèses!$C$20,IF(B8=2,Hypothèses!$C$21,Hypothèses!$C$22))*IF(B8=1,Hypothèses!$D$20,IF(B8=2,Hypothèses!$D$21,Hypothèses!$D$22)) -> 4.5 | O8: =IF(A8=18,IF($B$2>=1,Hypothèses!$B$33,0),IF(AND(OR(A8=30,A8=34),$D$2>=1),Hypothèses!$B$34*MIN(1,$D$2/3),0)) -> 0 | P8: =M8+N8+O8 -> 565.65 | Q8: =P8/(1+Hypothèses!$B$6) -> 471.375 | R8: =Hypothèses!$B$3*(1+Hypothèses!$B$4)^INT((A8-1)/3) -> 575 | S8: =IF($A8>=13,1,0) -> 0 | T8: =S8*Hypothèses!$B$17 -> 0 | U8: =Q8*Hypothèses!$B$5 -> 4.71375 | V8: =Q8-R8-T8-U8 -> -108.33875 | W8: =W7+V8 -> 677.67975
A9: 6 | B9: =INT((A9-1)/12)+1 -> 1 | C9: =ROUND(IF(MOD($A9,12)=0,G9,(IF(9=4,0,C8))*(1-$K9)+IF((IF(9=4,0,C8))*(1-$K9)<G9,(G9-(IF(9=4,0,C8))*(1-$K9))*Hypothèses!$B$10,0)),1) -> 1.9 | D9: =ROUND(IF(MOD($A9,12)=0,H9,(IF(9=4,0,D8))*(1-$K9)+IF((IF(9=4,0,D8))*(1-$K9)<H9,(H9-(IF(9=4,0,D8))*(1-$K9))*Hypothèses!$B$10,0)),1) -> 3.8 | E9: =ROUND(IF(MOD($A9,12)=0,I9,(IF(9=4,0,E8))*(1-$K9)+IF((IF(9=4,0,E8))*(1-$K9)<I9,(I9-(IF(9=4,0,E8))*(1-$K9))*Hypothèses!$B$10,0)),1) -> 0 | F9: =ROUND(IF(MOD($A9,12)=0,J9,(IF(9=4,0,F8))*(1-$K9)+IF((IF(9=4,0,F8))*(1-$K9)<J9,(J9-(IF(9=4,0,F8))*(1-$K9))*Hypothèses!$B$10,0)),1) -> 0 | G9: =(IF(B9=1,0,IF(B9=2,Hypothèses!$B$26,IF(B9=3,Hypothèses!$C$26,Hypothèses!$D$26)))+(IF(B9=1,Hypothèses!$B$26,IF(B9=2,Hypothèses!$C$26,IF(B9=3,Hypothèses!$D$26,Hypothèses!$D$26)))-(IF(B9=1,0,IF(B9=2,Hypothèses!$B$26,IF(B9=3,Hypothèses!$C$26,Hypothèses!$D$26)))))*((A9)-INT((A9-1)/12)*12)/12)*$B$1 -> 2.5 | H9: =(IF(B9=1,0,IF(B9=2,Hypothèses!$B$27,IF(B9=3,Hypothèses!$C$27,Hypothèses!$D$27)))+(IF(B9=1,Hypothèses!$B$27,IF(B9=2,Hypothèses!$C$27,IF(B9=3,Hypothèses!$D$27,Hypothèses!$D$27)))-(IF(B9=1,0,IF(B9=2,Hypothèses!$B$27,IF(B9=3,Hypothèses!$C$27,Hypothèses!$D$27)))))*((A9)-INT((A9-1)/12)*12)/12)*$B$1 -> 5 | I9: =(IF(B9=1,0,IF(B9=2,Hypothèses!$B$28,IF(B9=3,Hypothèses!$C$28,Hypothèses!$D$28)))+(IF(B9=1,Hypothèses!$B$28,IF(B9=2,Hypothèses!$C$28,IF(B9=3,Hypothèses!$D$28,Hypothèses!$D$28)))-(IF(B9=1,0,IF(B9=2,Hypothèses!$B$28,IF(B9=3,Hypothèses!$C$28,Hypothèses!$D$28)))))*((A9)-INT((A9-1)/12)*12)/12)*$B$1 -> 0 | J9: =(IF(B9=1,0,IF(B9=2,Hypothèses!$B$29,IF(B9=3,Hypothèses!$C$29,Hypothèses!$D$29)))+(IF(B9=1,Hypothèses!$B$29,IF(B9=2,Hypothèses!$C$29,IF(B9=3,Hypothèses!$D$29,Hypothèses!$D$29)))-(IF(B9=1,0,IF(B9=2,Hypothèses!$B$29,IF(B9=3,Hypothèses!$C$29,Hypothèses!$D$29)))))*((A9)-INT((A9-1)/12)*12)/12)*$B$1 -> 0 | K9: =IF(A9<Hypothèses!$B$7,0,Hypothèses!$B$8*(1-Hypothèses!$B$9)^(A9-Hypothèses!$B$7)) -> 0 | L9: =C9+D9+E9+F9 -> 5.7 | M9: =(C9*Hypothèses!$B$11+D9*Hypothèses!$B$12+E9*Hypothèses!$B$13+F9*Hypothèses!$B$14)*(IF(B9=1,Hypothèses!$B$20,IF(B9=2,Hypothèses!$B$21,Hypothèses!$B$22))+(1-(IF(B9=1,Hypothèses!$B$20,IF(B9=2,Hypothèses!$B$21,Hypothèses!$B$22))))*11/12) -> 710.79 | N9: =L9*IF(B9=1,Hypothèses!$C$20,IF(B9=2,Hypothèses!$C$21,Hypothèses!$C$22))*IF(B9=1,Hypothèses!$D$20,IF(B9=2,Hypothèses!$D$21,Hypothèses!$D$22)) -> 5.7 | O9: =IF(A9=18,IF($B$2>=1,Hypothèses!$B$33,0),IF(AND(OR(A9=30,A9=34),$D$2>=1),Hypothèses!$B$34*MIN(1,$D$2/3),0)) -> 0 | P9: =M9+N9+O9 -> 716.49 | Q9: =P9/(1+Hypothèses!$B$6) -> 597.075 | R9: =Hypothèses!$B$3*(1+Hypothèses!$B$4)^INT((A9-1)/3) -> 575 | S9: =IF($A9>=13,1,0) -> 0 | T9: =S9*Hypothèses!$B$17 -> 0 | U9: =Q9*Hypothèses!$B$5 -> 5.97075 | V9: =Q9-R9-T9-U9 -> 16.10425 | W9: =W8+V9 -> 693.784
A10: 7 | B10: =INT((A10-1)/12)+1 -> 1 | C10: =ROUND(IF(MOD($A10,12)=0,G10,(IF(10=4,0,C9))*(1-$K10)+IF((IF(10=4,0,C9))*(1-$K10)<G10,(G10-(IF(10=4,0,C9))*(1-$K10))*Hypothèses!$B$10,0)),1) -> 2.3 | D10: =ROUND(IF(MOD($A10,12)=0,H10,(IF(10=4,0,D9))*(1-$K10)+IF((IF(10=4,0,D9))*(1-$K10)<H10,(H10-(IF(10=4,0,D9))*(1-$K10))*Hypothèses!$B$10,0)),1) -> 4.6 | E10: =ROUND(IF(MOD($A10,12)=0,I10,(IF(10=4,0,E9))*(1-$K10)+IF((IF(10=4,0,E9))*(1-$K10)<I10,(I10-(IF(10=4,0,E9))*(1-$K10))*Hypothèses!$B$10,0)),1) -> 0 | F10: =ROUND(IF(MOD($A10,12)=0,J10,(IF(10=4,0,F9))*(1-$K10)+IF((IF(10=4,0,F9))*(1-$K10)<J10,(J10-(IF(10=4,0,F9))*(1-$K10))*Hypothèses!$B$10,0)),1) -> 0 | G10: =(IF(B10=1,0,IF(B10=2,Hypothèses!$B$26,IF(B10=3,Hypothèses!$C$26,Hypothèses!$D$26)))+(IF(B10=1,Hypothèses!$B$26,IF(B10=2,Hypothèses!$C$26,IF(B10=3,Hypothèses!$D$26,Hypothèses!$D$26)))-(IF(B10=1,0,IF(B10=2,Hypothèses!$B$26,IF(B10=3,Hypothèses!$C$26,Hypothèses!$D$26)))))*((A10)-INT((A10-1)/12)*12)/12)*$B$1 -> 2.9166667 | H10: =(IF(B10=1,0,IF(B10=2,Hypothèses!$B$27,IF(B10=3,Hypothèses!$C$27,Hypothèses!$D$27)))+(IF(B10=1,Hypothèses!$B$27,IF(B10=2,Hypothèses!$C$27,IF(B10=3,Hypothèses!$D$27,Hypothèses!$D$27)))-(IF(B10=1,0,IF(B10=2,Hypothèses!$B$27,IF(B10=3,Hypothèses!$C$27,Hypothèses!$D$27)))))*((A10)-INT((A10-1)/12)*12)/12)*$B$1 -> 5.8333333 | I10: =(IF(B10=1,0,IF(B10=2,Hypothèses!$B$28,IF(B10=3,Hypothèses!$C$28,Hypothèses!$D$28)))+(IF(B10=1,Hypothèses!$B$28,IF(B10=2,Hypothèses!$C$28,IF(B10=3,Hypothèses!$D$28,Hypothèses!$D$28)))-(IF(B10=1,0,IF(B10=2,Hypothèses!$B$28,IF(B10=3,Hypothèses!$C$28,Hypothèses!$D$28)))))*((A10)-INT((A10-1)/12)*12)/12)*$B$1 -> 0 | J10: =(IF(B10=1,0,IF(B10=2,Hypothèses!$B$29,IF(B10=3,Hypothèses!$C$29,Hypothèses!$D$29)))+(IF(B10=1,Hypothèses!$B$29,IF(B10=2,Hypothèses!$C$29,IF(B10=3,Hypothèses!$D$29,Hypothèses!$D$29)))-(IF(B10=1,0,IF(B10=2,Hypothèses!$B$29,IF(B10=3,Hypothèses!$C$29,Hypothèses!$D$29)))))*((A10)-INT((A10-1)/12)*12)/12)*$B$1 -> 0 | K10: =IF(A10<Hypothèses!$B$7,0,Hypothèses!$B$8*(1-Hypothèses!$B$9)^(A10-Hypothèses!$B$7)) -> 0 | L10: =C10+D10+E10+F10 -> 6.9 | M10: =(C10*Hypothèses!$B$11+D10*Hypothèses!$B$12+E10*Hypothèses!$B$13+F10*Hypothèses!$B$14)*(IF(B10=1,Hypothèses!$B$20,IF(B10=2,Hypothèses!$B$21,Hypothèses!$B$22))+(1-(IF(B10=1,Hypothèses!$B$20,IF(B10=2,Hypothèses!$B$21,Hypothèses!$B$22))))*11/12) -> 860.43 | N10: =L10*IF(B10=1,Hypothèses!$C$20,IF(B10=2,Hypothèses!$C$21,Hypothèses!$C$22))*IF(B10=1,Hypothèses!$D$20,IF(B10=2,Hypothèses!$D$21,Hypothèses!$D$22)) -> 6.9 | O10: =IF(A10=18,IF($B$2>=1,Hypothèses!$B$33,0),IF(AND(OR(A10=30,A10=34),$D$2>=1),Hypothèses!$B$34*MIN(1,$D$2/3),0)) -> 0 | P10: =M10+N10+O10 -> 867.33 | Q10: =P10/(1+Hypothèses!$B$6) -> 722.775 | R10: =Hypothèses!$B$3*(1+Hypothèses!$B$4)^INT((A10-1)/3) -> 661.25 | S10: =IF($A10>=13,1,0) -> 0 | T10: =S10*Hypothèses!$B$17 -> 0 | U10: =Q10*Hypothèses!$B$5 -> 7.22775 | V10: =Q10-R10-T10-U10 -> 54.29725 | W10: =W9+V10 -> 748.08125
A11: 8 | B11: =INT((A11-1)/12)+1 -> 1 | C11: =ROUND(IF(MOD($A11,12)=0,G11,(IF(11=4,0,C10))*(1-$K11)+IF((IF(11=4,0,C10))*(1-$K11)<G11,(G11-(IF(11=4,0,C10))*(1-$K11))*Hypothèses!$B$10,0)),1) -> 2.7 | D11: =ROUND(IF(MOD($A11,12)=0,H11,(IF(11=4,0,D10))*(1-$K11)+IF((IF(11=4,0,D10))*(1-$K11)<H11,(H11-(IF(11=4,0,D10))*(1-$K11))*Hypothèses!$B$10,0)),1) -> 5.4 | E11: =ROUND(IF(MOD($A11,12)=0,I11,(IF(11=4,0,E10))*(1-$K11)+IF((IF(11=4,0,E10))*(1-$K11)<I11,(I11-(IF(11=4,0,E10))*(1-$K11))*Hypothèses!$B$10,0)),1) -> 0 | F11: =ROUND(IF(MOD($A11,12)=0,J11,(IF(11=4,0,F10))*(1-$K11)+IF((IF(11=4,0,F10))*(1-$K11)<J11,(J11-(IF(11=4,0,F10))*(1-$K11))*Hypothèses!$B$10,0)),1) -> 0 | G11: =(IF(B11=1,0,IF(B11=2,Hypothèses!$B$26,IF(B11=3,Hypothèses!$C$26,Hypothèses!$D$26)))+(IF(B11=1,Hypothèses!$B$26,IF(B11=2,Hypothèses!$C$26,IF(B11=3,Hypothèses!$D$26,Hypothèses!$D$26)))-(IF(B11=1,0,IF(B11=2,Hypothèses!$B$26,IF(B11=3,Hypothèses!$C$26,Hypothèses!$D$26)))))*((A11)-INT((A11-1)/12)*12)/12)*$B$1 -> 3.3333333 | H11: =(IF(B11=1,0,IF(B11=2,Hypothèses!$B$27,IF(B11=3,Hypothèses!$C$27,Hypothèses!$D$27)))+(IF(B11=1,Hypothèses!$B$27,IF(B11=2,Hypothèses!$C$27,IF(B11=3,Hypothèses!$D$27,Hypothèses!$D$27)))-(IF(B11=1,0,IF(B11=2,Hypothèses!$B$27,IF(B11=3,Hypothèses!$C$27,Hypothèses!$D$27)))))*((A11)-INT((A11-1)/12)*12)/12)*$B$1 -> 6.6666667 | I11: =(IF(B11=1,0,IF(B11=2,Hypothèses!$B$28,IF(B11=3,Hypothèses!$C$28,Hypothèses!$D$28)))+(IF(B11=1,Hypothèses!$B$28,IF(B11=2,Hypothèses!$C$28,IF(B11=3,Hypothèses!$D$28,Hypothèses!$D$28)))-(IF(B11=1,0,IF(B11=2,Hypothèses!$B$28,IF(B11=3,Hypothèses!$C$28,Hypothèses!$D$28)))))*((A11)-INT((A11-1)/12)*12)/12)*$B$1 -> 0 | J11: =(IF(B11=1,0,IF(B11=2,Hypothèses!$B$29,IF(B11=3,Hypothèses!$C$29,Hypothèses!$D$29)))+(IF(B11=1,Hypothèses!$B$29,IF(B11=2,Hypothèses!$C$29,IF(B11=3,Hypothèses!$D$29,Hypothèses!$D$29)))-(IF(B11=1,0,IF(B11=2,Hypothèses!$B$29,IF(B11=3,Hypothèses!$C$29,Hypothèses!$D$29)))))*((A11)-INT((A11-1)/12)*12)/12)*$B$1 -> 0 | K11: =IF(A11<Hypothèses!$B$7,0,Hypothèses!$B$8*(1-Hypothèses!$B$9)^(A11-Hypothèses!$B$7)) -> 0 | L11: =C11+D11+E11+F11 -> 8.1 | M11: =(C11*Hypothèses!$B$11+D11*Hypothèses!$B$12+E11*Hypothèses!$B$13+F11*Hypothèses!$B$14)*(IF(B11=1,Hypothèses!$B$20,IF(B11=2,Hypothèses!$B$21,Hypothèses!$B$22))+(1-(IF(B11=1,Hypothèses!$B$20,IF(B11=2,Hypothèses!$B$21,Hypothèses!$B$22))))*11/12) -> 1010.07 | N11: =L11*IF(B11=1,Hypothèses!$C$20,IF(B11=2,Hypothèses!$C$21,Hypothèses!$C$22))*IF(B11=1,Hypothèses!$D$20,IF(B11=2,Hypothèses!$D$21,Hypothèses!$D$22)) -> 8.1 | O11: =IF(A11=18,IF($B$2>=1,Hypothèses!$B$33,0),IF(AND(OR(A11=30,A11=34),$D$2>=1),Hypothèses!$B$34*MIN(1,$D$2/3),0)) -> 0 | P11: =M11+N11+O11 -> 1018.17 | Q11: =P11/(1+Hypothèses!$B$6) -> 848.475 | R11: =Hypothèses!$B$3*(1+Hypothèses!$B$4)^INT((A11-1)/3) -> 661.25 | S11: =IF($A11>=13,1,0) -> 0 | T11: =S11*Hypothèses!$B$17 -> 0 | U11: =Q11*Hypothèses!$B$5 -> 8.48475 | V11: =Q11-R11-T11-U11 -> 178.74025 | W11: =W10+V11 -> 926.8215
A12: 9 | B12: =INT((A12-1)/12)+1 -> 1 | C12: =ROUND(IF(MOD($A12,12)=0,G12,(IF(12=4,0,C11))*(1-$K12)+IF((IF(12=4,0,C11))*(1-$K12)<G12,(G12-(IF(12=4,0,C11))*(1-$K12))*Hypothèses!$B$10,0)),1) -> 3 | D12: =ROUND(IF(MOD($A12,12)=0,H12,(IF(12=4,0,D11))*(1-$K12)+IF((IF(12=4,0,D11))*(1-$K12)<H12,(H12-(IF(12=4,0,D11))*(1-$K12))*Hypothèses!$B$10,0)),1) -> 6.1 | E12: =ROUND(IF(MOD($A12,12)=0,I12,(IF(12=4,0,E11))*(1-$K12)+IF((IF(12=4,0,E11))*(1-$K12)<I12,(I12-(IF(12=4,0,E11))*(1-$K12))*Hypothèses!$B$10,0)),1) -> 0 | F12: =ROUND(IF(MOD($A12,12)=0,J12,(IF(12=4,0,F11))*(1-$K12)+IF((IF(12=4,0,F11))*(1-$K12)<J12,(J12-(IF(12=4,0,F11))*(1-$K12))*Hypothèses!$B$10,0)),1) -> 0 | G12: =(IF(B12=1,0,IF(B12=2,Hypothèses!$B$26,IF(B12=3,Hypothèses!$C$26,Hypothèses!$D$26)))+(IF(B12=1,Hypothèses!$B$26,IF(B12=2,Hypothèses!$C$26,IF(B12=3,Hypothèses!$D$26,Hypothèses!$D$26)))-(IF(B12=1,0,IF(B12=2,Hypothèses!$B$26,IF(B12=3,Hypothèses!$C$26,Hypothèses!$D$26)))))*((A12)-INT((A12-1)/12)*12)/12)*$B$1 -> 3.75 | H12: =(IF(B12=1,0,IF(B12=2,Hypothèses!$B$27,IF(B12=3,Hypothèses!$C$27,Hypothèses!$D$27)))+(IF(B12=1,Hypothèses!$B$27,IF(B12=2,Hypothèses!$C$27,IF(B12=3,Hypothèses!$D$27,Hypothèses!$D$27)))-(IF(B12=1,0,IF(B12=2,Hypothèses!$B$27,IF(B12=3,Hypothèses!$C$27,Hypothèses!$D$27)))))*((A12)-INT((A12-1)/12)*12)/12)*$B$1 -> 7.5 | I12: =(IF(B12=1,0,IF(B12=2,Hypothèses!$B$28,IF(B12=3,Hypothèses!$C$28,Hypothèses!$D$28)))+(IF(B12=1,Hypothèses!$B$28,IF(B12=2,Hypothèses!$C$28,IF(B12=3,Hypothèses!$D$28,Hypothèses!$D$28)))-(IF(B12=1,0,IF(B12=2,Hypothèses!$B$28,IF(B12=3,Hypothèses!$C$28,Hypothèses!$D$28)))))*((A12)-INT((A12-1)/12)*12)/12)*$B$1 -> 0 | J12: =(IF(B12=1,0,IF(B12=2,Hypothèses!$B$29,IF(B12=3,Hypothèses!$C$29,Hypothèses!$D$29)))+(IF(B12=1,Hypothèses!$B$29,IF(B12=2,Hypothèses!$C$29,IF(B12=3,Hypothèses!$D$29,Hypothèses!$D$29)))-(IF(B12=1,0,IF(B12=2,Hypothèses!$B$29,IF(B12=3,Hypothèses!$C$29,Hypothèses!$D$29)))))*((A12)-INT((A12-1)/12)*12)/12)*$B$1 -> 0 | K12: =IF(A12<Hypothèses!$B$7,0,Hypothèses!$B$8*(1-Hypothèses!$B$9)^(A12-Hypothèses!$B$7)) -> 0.05 | L12: =C12+D12+E12+F12 -> 9.1 | M12: =(C12*Hypothèses!$B$11+D12*Hypothèses!$B$12+E12*Hypothèses!$B$13+F12*Hypothèses!$B$14)*(IF(B12=1,Hypothèses!$B$20,IF(B12=2,Hypothèses!$B$21,Hypothèses!$B$22))+(1-(IF(B12=1,Hypothèses!$B$20,IF(B12=2,Hypothèses!$B$21,Hypothèses!$B$22))))*11/12) -> 1136.7033 | N12: =L12*IF(B12=1,Hypothèses!$C$20,IF(B12=2,Hypothèses!$C$21,Hypothèses!$C$22))*IF(B12=1,Hypothèses!$D$20,IF(B12=2,Hypothèses!$D$21,Hypothèses!$D$22)) -> 9.1 | O12: =IF(A12=18,IF($B$2>=1,Hypothèses!$B$33,0),IF(AND(OR(A12=30,A12=34),$D$2>=1),Hypothèses!$B$34*MIN(1,$D$2/3),0)) -> 0 | P12: =M12+N12+O12 -> 1145.8033 | Q12: =P12/(1+Hypothèses!$B$6) -> 954.83611 | R12: =Hypothèses!$B$3*(1+Hypothèses!$B$4)^INT((A12-1)/3) -> 661.25 | S12: =IF($A12>=13,1,0) -> 0 | T12: =S12*Hypothèses!$B$17 -> 0 | U12: =Q12*Hypothèses!$B$5 -> 9.5483611 | V12: =Q12-R12-T12-U12 -> 284.03775 | W12: =W11+V12 -> 1210.8593
A13: 10 | B13: =INT((A13-1)/12)+1 -> 1 | C13: =ROUND(IF(MOD($A13,12)=0,G13,(IF(13=4,0,C12))*(1-$K13)+IF((IF(13=4,0,C12))*(1-$K13)<G13,(G13-(IF(13=4,0,C12))*(1-$K13))*Hypothèses!$B$10,0)),1) -> 3.4 | D13: =ROUND(IF(MOD($A13,12)=0,H13,(IF(13=4,0,D12))*(1-$K13)+IF((IF(13=4,0,D12))*(1-$K13)<H13,(H13-(IF(13=4,0,D12))*(1-$K13))*Hypothèses!$B$10,0)),1) -> 6.8 | E13: =ROUND(IF(MOD($A13,12)=0,I13,(IF(13=4,0,E12))*(1-$K13)+IF((IF(13=4,0,E12))*(1-$K13)<I13,(I13-(IF(13=4,0,E12))*(1-$K13))*Hypothèses!$B$10,0)),1) -> 0 | F13: =ROUND(IF(MOD($A13,12)=0,J13,(IF(13=4,0,F12))*(1-$K13)+IF((IF(13=4,0,F12))*(1-$K13)<J13,(J13-(IF(13=4,0,F12))*(1-$K13))*Hypothèses!$B$10,0)),1) -> 0 | G13: =(IF(B13=1,0,IF(B13=2,Hypothèses!$B$26,IF(B13=3,Hypothèses!$C$26,Hypothèses!$D$26)))+(IF(B13=1,Hypothèses!$B$26,IF(B13=2,Hypothèses!$C$26,IF(B13=3,Hypothèses!$D$26,Hypothèses!$D$26)))-(IF(B13=1,0,IF(B13=2,Hypothèses!$B$26,IF(B13=3,Hypothèses!$C$26,Hypothèses!$D$26)))))*((A13)-INT((A13-1)/12)*12)/12)*$B$1 -> 4.1666667 | H13: =(IF(B13=1,0,IF(B13=2,Hypothèses!$B$27,IF(B13=3,Hypothèses!$C$27,Hypothèses!$D$27)))+(IF(B13=1,Hypothèses!$B$27,IF(B13=2,Hypothèses!$C$27,IF(B13=3,Hypothèses!$D$27,Hypothèses!$D$27)))-(IF(B13=1,0,IF(B13=2,Hypothèses!$B$27,IF(B13=3,Hypothèses!$C$27,Hypothèses!$D$27)))))*((A13)-INT((A13-1)/12)*12)/12)*$B$1 -> 8.3333333 | I13: =(IF(B13=1,0,IF(B13=2,Hypothèses!$B$28,IF(B13=3,Hypothèses!$C$28,Hypothèses!$D$28)))+(IF(B13=1,Hypothèses!$B$28,IF(B13=2,Hypothèses!$C$28,IF(B13=3,Hypothèses!$D$28,Hypothèses!$D$28)))-(IF(B13=1,0,IF(B13=2,Hypothèses!$B$28,IF(B13=3,Hypothèses!$C$28,Hypothèses!$D$28)))))*((A13)-INT((A13-1)/12)*12)/12)*$B$1 -> 0 | J13: =(IF(B13=1,0,IF(B13=2,Hypothèses!$B$29,IF(B13=3,Hypothèses!$C$29,Hypothèses!$D$29)))+(IF(B13=1,Hypothèses!$B$29,IF(B13=2,Hypothèses!$C$29,IF(B13=3,Hypothèses!$D$29,Hypothèses!$D$29)))-(IF(B13=1,0,IF(B13=2,Hypothèses!$B$29,IF(B13=3,Hypothèses!$C$29,Hypothèses!$D$29)))))*((A13)-INT((A13-1)/12)*12)/12)*$B$1 -> 0 | K13: =IF(A13<Hypothèses!$B$7,0,Hypothèses!$B$8*(1-Hypothèses!$B$9)^(A13-Hypothèses!$B$7)) -> 0.045 | L13: =C13+D13+E13+F13 -> 10.2 | M13: =(C13*Hypothèses!$B$11+D13*Hypothèses!$B$12+E13*Hypothèses!$B$13+F13*Hypothèses!$B$14)*(IF(B13=1,Hypothèses!$B$20,IF(B13=2,Hypothèses!$B$21,Hypothèses!$B$22))+(1-(IF(B13=1,Hypothèses!$B$20,IF(B13=2,Hypothèses!$B$21,Hypothèses!$B$22))))*11/12) -> 1271.94 | N13: =L13*IF(B13=1,Hypothèses!$C$20,IF(B13=2,Hypothèses!$C$21,Hypothèses!$C$22))*IF(B13=1,Hypothèses!$D$20,IF(B13=2,Hypothèses!$D$21,Hypothèses!$D$22)) -> 10.2 | O13: =IF(A13=18,IF($B$2>=1,Hypothèses!$B$33,0),IF(AND(OR(A13=30,A13=34),$D$2>=1),Hypothèses!$B$34*MIN(1,$D$2/3),0)) -> 0 | P13: =M13+N13+O13 -> 1282.14 | Q13: =P13/(1+Hypothèses!$B$6) -> 1068.45 | R13: =Hypothèses!$B$3*(1+Hypothèses!$B$4)^INT((A13-1)/3) -> 760.4375 | S13: =IF($A13>=13,1,0) -> 0 | T13: =S13*Hypothèses!$B$17 -> 0 | U13: =Q13*Hypothèses!$B$5 -> 10.6845 | V13: =Q13-R13-T13-U13 -> 297.328 | W13: =W12+V13 -> 1508.1873
A14: 11 | B14: =INT((A14-1)/12)+1 -> 1 | C14: =ROUND(IF(MOD($A14,12)=0,G14,(IF(14=4,0,C13))*(1-$K14)+IF((IF(14=4,0,C13))*(1-$K14)<G14,(G14-(IF(14=4,0,C13))*(1-$K14))*Hypothèses!$B$10,0)),1) -> 3.8 | D14: =ROUND(IF(MOD($A14,12)=0,H14,(IF(14=4,0,D13))*(1-$K14)+IF((IF(14=4,0,D13))*(1-$K14)<H14,(H14-(IF(14=4,0,D13))*(1-$K14))*Hypothèses!$B$10,0)),1) -> 7.6 | E14: =ROUND(IF(MOD($A14,12)=0,I14,(IF(14=4,0,E13))*(1-$K14)+IF((IF(14=4,0,E13))*(1-$K14)<I14,(I14-(IF(14=4,0,E13))*(1-$K14))*Hypothèses!$B$10,0)),1) -> 0 | F14: =ROUND(IF(MOD($A14,12)=0,J14,(IF(14=4,0,F13))*(1-$K14)+IF((IF(14=4,0,F13))*(1-$K14)<J14,(J14-(IF(14=4,0,F13))*(1-$K14))*Hypothèses!$B$10,0)),1) -> 0 | G14: =(IF(B14=1,0,IF(B14=2,Hypothèses!$B$26,IF(B14=3,Hypothèses!$C$26,Hypothèses!$D$26)))+(IF(B14=1,Hypothèses!$B$26,IF(B14=2,Hypothèses!$C$26,IF(B14=3,Hypothèses!$D$26,Hypothèses!$D$26)))-(IF(B14=1,0,IF(B14=2,Hypothèses!$B$26,IF(B14=3,Hypothèses!$C$26,Hypothèses!$D$26)))))*((A14)-INT((A14-1)/12)*12)/12)*$B$1 -> 4.5833333 | H14: =(IF(B14=1,0,IF(B14=2,Hypothèses!$B$27,IF(B14=3,Hypothèses!$C$27,Hypothèses!$D$27)))+(IF(B14=1,Hypothèses!$B$27,IF(B14=2,Hypothèses!$C$27,IF(B14=3,Hypothèses!$D$27,Hypothèses!$D$27)))-(IF(B14=1,0,IF(B14=2,Hypothèses!$B$27,IF(B14=3,Hypothèses!$C$27,Hypothèses!$D$27)))))*((A14)-INT((A14-1)/12)*12)/12)*$B$1 -> 9.1666667 | I14: =(IF(B14=1,0,IF(B14=2,Hypothèses!$B$28,IF(B14=3,Hypothèses!$C$28,Hypothèses!$D$28)))+(IF(B14=1,Hypothèses!$B$28,IF(B14=2,Hypothèses!$C$28,IF(B14=3,Hypothèses!$D$28,Hypothèses!$D$28)))-(IF(B14=1,0,IF(B14=2,Hypothèses!$B$28,IF(B14=3,Hypothèses!$C$28,Hypothèses!$D$28)))))*((A14)-INT((A14-1)/12)*12)/12)*$B$1 -> 0 | J14: =(IF(B14=1,0,IF(B14=2,Hypothèses!$B$29,IF(B14=3,Hypothèses!$C$29,Hypothèses!$D$29)))+(IF(B14=1,Hypothèses!$B$29,IF(B14=2,Hypothèses!$C$29,IF(B14=3,Hypothèses!$D$29,Hypothèses!$D$29)))-(IF(B14=1,0,IF(B14=2,Hypothèses!$B$29,IF(B14=3,Hypothèses!$C$29,Hypothèses!$D$29)))))*((A14)-INT((A14-1)/12)*12)/12)*$B$1 -> 0 | K14: =IF(A14<Hypothèses!$B$7,0,Hypothèses!$B$8*(1-Hypothèses!$B$9)^(A14-Hypothèses!$B$7)) -> 0.0405 | L14: =C14+D14+E14+F14 -> 11.4 | M14: =(C14*Hypothèses!$B$11+D14*Hypothèses!$B$12+E14*Hypothèses!$B$13+F14*Hypothèses!$B$14)*(IF(B14=1,Hypothèses!$B$20,IF(B14=2,Hypothèses!$B$21,Hypothèses!$B$22))+(1-(IF(B14=1,Hypothèses!$B$20,IF(B14=2,Hypothèses!$B$21,Hypothèses!$B$22))))*11/12) -> 1421.58 | N14: =L14*IF(B14=1,Hypothèses!$C$20,IF(B14=2,Hypothèses!$C$21,Hypothèses!$C$22))*IF(B14=1,Hypothèses!$D$20,IF(B14=2,Hypothèses!$D$21,Hypothèses!$D$22)) -> 11.4 | O14: =IF(A14=18,IF($B$2>=1,Hypothèses!$B$33,0),IF(AND(OR(A14=30,A14=34),$D$2>=1),Hypothèses!$B$34*MIN(1,$D$2/3),0)) -> 0 | P14: =M14+N14+O14 -> 1432.98 | Q14: =P14/(1+Hypothèses!$B$6) -> 1194.15 | R14: =Hypothèses!$B$3*(1+Hypothèses!$B$4)^INT((A14-1)/3) -> 760.4375 | S14: =IF($A14>=13,1,0) -> 0 | T14: =S14*Hypothèses!$B$17 -> 0 | U14: =Q14*Hypothèses!$B$5 -> 11.9415 | V14: =Q14-R14-T14-U14 -> 421.771 | W14: =W13+V14 -> 1929.9583
A15: 12 | B15: =INT((A15-1)/12)+1 -> 1 | C15: =ROUND(IF(MOD($A15,12)=0,G15,(IF(15=4,0,C14))*(1-$K15)+IF((IF(15=4,0,C14))*(1-$K15)<G15,(G15-(IF(15=4,0,C14))*(1-$K15))*Hypothèses!$B$10,0)),1) -> 5 | D15: =ROUND(IF(MOD($A15,12)=0,H15,(IF(15=4,0,D14))*(1-$K15)+IF((IF(15=4,0,D14))*(1-$K15)<H15,(H15-(IF(15=4,0,D14))*(1-$K15))*Hypothèses!$B$10,0)),1) -> 10 | E15: =ROUND(IF(MOD($A15,12)=0,I15,(IF(15=4,0,E14))*(1-$K15)+IF((IF(15=4,0,E14))*(1-$K15)<I15,(I15-(IF(15=4,0,E14))*(1-$K15))*Hypothèses!$B$10,0)),1) -> 0 | F15: =ROUND(IF(MOD($A15,12)=0,J15,(IF(15=4,0,F14))*(1-$K15)+IF((IF(15=4,0,F14))*(1-$K15)<J15,(J15-(IF(15=4,0,F14))*(1-$K15))*Hypothèses!$B$10,0)),1) -> 0 | G15: =(IF(B15=1,0,IF(B15=2,Hypothèses!$B$26,IF(B15=3,Hypothèses!$C$26,Hypothèses!$D$26)))+(IF(B15=1,Hypothèses!$B$26,IF(B15=2,Hypothèses!$C$26,IF(B15=3,Hypothèses!$D$26,Hypothèses!$D$26)))-(IF(B15=1,0,IF(B15=2,Hypothèses!$B$26,IF(B15=3,Hypothèses!$C$26,Hypothèses!$D$26)))))*((A15)-INT((A15-1)/12)*12)/12)*$B$1 -> 5 | H15: =(IF(B15=1,0,IF(B15=2,Hypothèses!$B$27,IF(B15=3,Hypothèses!$C$27,Hypothèses!$D$27)))+(IF(B15=1,Hypothèses!$B$27,IF(B15=2,Hypothèses!$C$27,IF(B15=3,Hypothèses!$D$27,Hypothèses!$D$27)))-(IF(B15=1,0,IF(B15=2,Hypothèses!$B$27,IF(B15=3,Hypothèses!$C$27,Hypothèses!$D$27)))))*((A15)-INT((A15-1)/12)*12)/12)*$B$1 -> 10 | I15: =(IF(B15=1,0,IF(B15=2,Hypothèses!$B$28,IF(B15=3,Hypothèses!$C$28,Hypothèses!$D$28)))+(IF(B15=1,Hypothèses!$B$28,IF(B15=2,Hypothèses!$C$28,IF(B15=3,Hypothèses!$D$28,Hypothèses!$D$28)))-(IF(B15=1,0,IF(B15=2,Hypothèses!$B$28,IF(B15=3,Hypothèses!$C$28,Hypothèses!$D$28)))))*((A15)-INT((A15-1)/12)*12)/12)*$B$1 -> 0 | J15: =(IF(B15=1,0,IF(B15=2,Hypothèses!$B$29,IF(B15=3,Hypothèses!$C$29,Hypothèses!$D$29)))+(IF(B15=1,Hypothèses!$B$29,IF(B15=2,Hypothèses!$C$29,IF(B15=3,Hypothèses!$D$29,Hypothèses!$D$29)))-(IF(B15=1,0,IF(B15=2,Hypothèses!$B$29,IF(B15=3,Hypothèses!$C$29,Hypothèses!$D$29)))))*((A15)-INT((A15-1)/12)*12)/12)*$B$1 -> 0 | K15: =IF(A15<Hypothèses!$B$7,0,Hypothèses!$B$8*(1-Hypothèses!$B$9)^(A15-Hypothèses!$B$7)) -> 0.03645 | L15: =C15+D15+E15+F15 -> 15 | M15: =(C15*Hypothèses!$B$11+D15*Hypothèses!$B$12+E15*Hypothèses!$B$13+F15*Hypothèses!$B$14)*(IF(B15=1,Hypothèses!$B$20,IF(B15=2,Hypothèses!$B$21,Hypothèses!$B$22))+(1-(IF(B15=1,Hypothèses!$B$20,IF(B15=2,Hypothèses!$B$21,Hypothèses!$B$22))))*11/12) -> 1870.5 | N15: =L15*IF(B15=1,Hypothèses!$C$20,IF(B15=2,Hypothèses!$C$21,Hypothèses!$C$22))*IF(B15=1,Hypothèses!$D$20,IF(B15=2,Hypothèses!$D$21,Hypothèses!$D$22)) -> 15 | O15: =IF(A15=18,IF($B$2>=1,Hypothèses!$B$33,0),IF(AND(OR(A15=30,A15=34),$D$2>=1),Hypothèses!$B$34*MIN(1,$D$2/3),0)) -> 0 | P15: =M15+N15+O15 -> 1885.5 | Q15: =P15/(1+Hypothèses!$B$6) -> 1571.25 | R15: =Hypothèses!$B$3*(1+Hypothèses!$B$4)^INT((A15-1)/3) -> 760.4375 | S15: =IF($A15>=13,1,0) -> 0 | T15: =S15*Hypothèses!$B$17 -> 0 | U15: =Q15*Hypothèses!$B$5 -> 15.7125 | V15: =Q15-R15-T15-U15 -> 795.1 | W15: =W14+V15 -> 2725.0583
A16: 13 | B16: =INT((A16-1)/12)+1 -> 2 | C16: =ROUND(IF(MOD($A16,12)=0,G16,(IF(16=4,0,C15))*(1-$K16)+IF((IF(16=4,0,C15))*(1-$K16)<G16,(G16-(IF(16=4,0,C15))*(1-$K16))*Hypothèses!$B$10,0)),1) -> 5.1 | D16: =ROUND(IF(MOD($A16,12)=0,H16,(IF(16=4,0,D15))*(1-$K16)+IF((IF(16=4,0,D15))*(1-$K16)<H16,(H16-(IF(16=4,0,D15))*(1-$K16))*Hypothèses!$B$10,0)),1) -> 10.6 | E16: =ROUND(IF(MOD($A16,12)=0,I16,(IF(16=4,0,E15))*(1-$K16)+IF((IF(16=4,0,E15))*(1-$K16)<I16,(I16-(IF(16=4,0,E15))*(1-$K16))*Hypothèses!$B$10,0)),1) -> 0 | F16: =ROUND(IF(MOD($A16,12)=0,J16,(IF(16=4,0,F15))*(1-$K16)+IF((IF(16=4,0,F15))*(1-$K16)<J16,(J16-(IF(16=4,0,F15))*(1-$K16))*Hypothèses!$B$10,0)),1) -> 0 | G16: =(IF(B16=1,0,IF(B16=2,Hypothèses!$B$26,IF(B16=3,Hypothèses!$C$26,Hypothèses!$D$26)))+(IF(B16=1,Hypothèses!$B$26,IF(B16=2,Hypothèses!$C$26,IF(B16=3,Hypothèses!$D$26,Hypothèses!$D$26)))-(IF(B16=1,0,IF(B16=2,Hypothèses!$B$26,IF(B16=3,Hypothèses!$C$26,Hypothèses!$D$26)))))*((A16)-INT((A16-1)/12)*12)/12)*$B$1 -> 5.4166667 | H16: =(IF(B16=1,0,IF(B16=2,Hypothèses!$B$27,IF(B16=3,Hypothèses!$C$27,Hypothèses!$D$27)))+(IF(B16=1,Hypothèses!$B$27,IF(B16=2,Hypothèses!$C$27,IF(B16=3,Hypothèses!$D$27,Hypothèses!$D$27)))-(IF(B16=1,0,IF(B16=2,Hypothèses!$B$27,IF(B16=3,Hypothèses!$C$27,Hypothèses!$D$27)))))*((A16)-INT((A16-1)/12)*12)/12)*$B$1 -> 12.083333 | I16: =(IF(B16=1,0,IF(B16=2,Hypothèses!$B$28,IF(B16=3,Hypothèses!$C$28,Hypothèses!$D$28)))+(IF(B16=1,Hypothèses!$B$28,IF(B16=2,Hypothèses!$C$28,IF(B16=3,Hypothèses!$D$28,Hypothèses!$D$28)))-(IF(B16=1,0,IF(B16=2,Hypothèses!$B$28,IF(B16=3,Hypothèses!$C$28,Hypothèses!$D$28)))))*((A16)-INT((A16-1)/12)*12)/12)*$B$1 -> 0.083333333 | J16: =(IF(B16=1,0,IF(B16=2,Hypothèses!$B$29,IF(B16=3,Hypothèses!$C$29,Hypothèses!$D$29)))+(IF(B16=1,Hypothèses!$B$29,IF(B16=2,Hypothèses!$C$29,IF(B16=3,Hypothèses!$D$29,Hypothèses!$D$29)))-(IF(B16=1,0,IF(B16=2,Hypothèses!$B$29,IF(B16=3,Hypothèses!$C$29,Hypothèses!$D$29)))))*((A16)-INT((A16-1)/12)*12)/12)*$B$1 -> 0.083333333 | K16: =IF(A16<Hypothèses!$B$7,0,Hypothèses!$B$8*(1-Hypothèses!$B$9)^(A16-Hypothèses!$B$7)) -> 0.032805 | L16: =C16+D16+E16+F16 -> 15.7 | M16: =(C16*Hypothèses!$B$11+D16*Hypothèses!$B$12+E16*Hypothèses!$B$13+F16*Hypothèses!$B$14)*(IF(B16=1,Hypothèses!$B$20,IF(B16=2,Hypothèses!$B$21,Hypothèses!$B$22))+(1-(IF(B16=1,Hypothèses!$B$20,IF(B16=2,Hypothèses!$B$21,Hypothèses!$B$22))))*11/12) -> 1948.5792 | N16: =L16*IF(B16=1,Hypothèses!$C$20,IF(B16=2,Hypothèses!$C$21,Hypothèses!$C$22))*IF(B16=1,Hypothèses!$D$20,IF(B16=2,Hypothèses!$D$21,Hypothèses!$D$22)) -> 39.25 | O16: =IF(A16=18,IF($B$2>=1,Hypothèses!$B$33,0),IF(AND(OR(A16=30,A16=34),$D$2>=1),Hypothèses!$B$34*MIN(1,$D$2/3),0)) -> 0 | P16: =M16+N16+O16 -> 1987.8292 | Q16: =P16/(1+Hypothèses!$B$6) -> 1656.5243 | R16: =Hypothèses!$B$3*(1+Hypothèses!$B$4)^INT((A16-1)/3) -> 874.50312 | S16: =IF($A16>=13,1,0) -> 1 | T16: =S16*Hypothèses!$B$17 -> 4500 | U16: =Q16*Hypothèses!$B$5 -> 16.565243 | V16: =Q16-R16-T16-U16 -> -3734.5441 | W16: =W15+V16 -> -1009.4858
A17: 14 | B17: =INT((A17-1)/12)+1 -> 2 | C17: =ROUND(IF(MOD($A17,12)=0,G17,(IF(17=4,0,C16))*(1-$K17)+IF((IF(17=4,0,C16))*(1-$K17)<G17,(G17-(IF(17=4,0,C16))*(1-$K17))*Hypothèses!$B$10,0)),1) -> 5.3 | D17: =ROUND(IF(MOD($A17,12)=0,H17,(IF(17=4,0,D16))*(1-$K17)+IF((IF(17=4,0,D16))*(1-$K17)<H17,(H17-(IF(17=4,0,D16))*(1-$K17))*Hypothèses!$B$10,0)),1) -> 11.8 | E17: =ROUND(IF(MOD($A17,12)=0,I17,(IF(17=4,0,E16))*(1-$K17)+IF((IF(17=4,0,E16))*(1-$K17)<I17,(I17-(IF(17=4,0,E16))*(1-$K17))*Hypothèses!$B$10,0)),1) -> 0.1 | F17: =ROUND(IF(MOD($A17,12)=0,J17,(IF(17=4,0,F16))*(1-$K17)+IF((IF(17=4,0,F16))*(1-$K17)<J17,(J17-(IF(17=4,0,F16))*(1-$K17))*Hypothèses!$B$10,0)),1) -> 0.1 | G17: =(IF(B17=1,0,IF(B17=2,Hypothèses!$B$26,IF(B17=3,Hypothèses!$C$26,Hypothèses!$D$26)))+(IF(B17=1,Hypothèses!$B$26,IF(B17=2,Hypothèses!$C$26,IF(B17=3,Hypothèses!$D$26,Hypothèses!$D$26)))-(IF(B17=1,0,IF(B17=2,Hypothèses!$B$26,IF(B17=3,Hypothèses!$C$26,Hypothèses!$D$26)))))*((A17)-INT((A17-1)/12)*12)/12)*$B$1 -> 5.8333333 | H17: =(IF(B17=1,0,IF(B17=2,Hypothèses!$B$27,IF(B17=3,Hypothèses!$C$27,Hypothèses!$D$27)))+(IF(B17=1,Hypothèses!$B$27,IF(B17=2,Hypothèses!$C$27,IF(B17=3,Hypothèses!$D$27,Hypothèses!$D$27)))-(IF(B17=1,0,IF(B17=2,Hypothèses!$B$27,IF(B17=3,Hypothèses!$C$27,Hypothèses!$D$27)))))*((A17)-INT((A17-1)/12)*12)/12)*$B$1 -> 14.166667 | I17: =(IF(B17=1,0,IF(B17=2,Hypothèses!$B$28,IF(B17=3,Hypothèses!$C$28,Hypothèses!$D$28)))+(IF(B17=1,Hypothèses!$B$28,IF(B17=2,Hypothèses!$C$28,IF(B17=3,Hypothèses!$D$28,Hypothèses!$D$28)))-(IF(B17=1,0,IF(B17=2,Hypothèses!$B$28,IF(B17=3,Hypothèses!$C$28,Hypothèses!$D$28)))))*((A17)-INT((A17-1)/12)*12)/12)*$B$1 -> 0.16666667 | J17: =(IF(B17=1,0,IF(B17=2,Hypothèses!$B$29,IF(B17=3,Hypothèses!$C$29,Hypothèses!$D$29)))+(IF(B17=1,Hypothèses!$B$29,IF(B17=2,Hypothèses!$C$29,IF(B17=3,Hypothèses!$D$29,Hypothèses!$D$29)))-(IF(B17=1,0,IF(B17=2,Hypothèses!$B$29,IF(B17=3,Hypothèses!$C$29,Hypothèses!$D$29)))))*((A17)-INT((A17-1)/12)*12)/12)*$B$1 -> 0.16666667 | K17: =IF(A17<Hypothèses!$B$7,0,Hypothèses!$B$8*(1-Hypothèses!$B$9)^(A17-Hypothèses!$B$7)) -> 0.0295245 | L17: =C17+D17+E17+F17 -> 17.3 | M17: =(C17*Hypothèses!$B$11+D17*Hypothèses!$B$12+E17*Hypothèses!$B$13+F17*Hypothèses!$B$14)*(IF(B17=1,Hypothèses!$B$20,IF(B17=2,Hypothèses!$B$21,Hypothèses!$B$22))+(1-(IF(B17=1,Hypothèses!$B$20,IF(B17=2,Hypothèses!$B$21,Hypothèses!$B$22))))*11/12) -> 2279.6833 | N17: =L17*IF(B17=1,Hypothèses!$C$20,IF(B17=2,Hypothèses!$C$21,Hypothèses!$C$22))*IF(B17=1,Hypothèses!$D$20,IF(B17=2,Hypothèses!$D$21,Hypothèses!$D$22)) -> 43.25 | O17: =IF(A17=18,IF($B$2>=1,Hypothèses!$B$33,0),IF(AND(OR(A17=30,A17=34),$D$2>=1),Hypothèses!$B$34*MIN(1,$D$2/3),0)) -> 0 | P17: =M17+N17+O17 -> 2322.9333 | Q17: =P17/(1+Hypothèses!$B$6) -> 1935.7778 | R17: =Hypothèses!$B$3*(1+Hypothèses!$B$4)^INT((A17-1)/3) -> 874.50312 | S17: =IF($A17>=13,1,0) -> 1 | T17: =S17*Hypothèses!$B$17 -> 4500 | U17: =Q17*Hypothèses!$B$5 -> 19.357778 | V17: =Q17-R17-T17-U17 -> -3458.0831 | W17: =W16+V17 -> -4467.5689
A18: 15 | B18: =INT((A18-1)/12)+1 -> 2 | C18: =ROUND(IF(MOD($A18,12)=0,G18,(IF(18=4,0,C17))*(1-$K18)+IF((IF(18=4,0,C17))*(1-$K18)<G18,(G18-(IF(18=4,0,C17))*(1-$K18))*Hypothèses!$B$10,0)),1) -> 5.6 | D18: =ROUND(IF(MOD($A18,12)=0,H18,(IF(18=4,0,D17))*(1-$K18)+IF((IF(18=4,0,D17))*(1-$K18)<H18,(H18-(IF(18=4,0,D17))*(1-$K18))*Hypothèses!$B$10,0)),1) -> 13.4 | E18: =ROUND(IF(MOD($A18,12)=0,I18,(IF(18=4,0,E17))*(1-$K18)+IF((IF(18=4,0,E17))*(1-$K18)<I18,(I18-(IF(18=4,0,E17))*(1-$K18))*Hypothèses!$B$10,0)),1) -> 0.2 | F18: =ROUND(IF(MOD($A18,12)=0,J18,(IF(18=4,0,F17))*(1-$K18)+IF((IF(18=4,0,F17))*(1-$K18)<J18,(J18-(IF(18=4,0,F17))*(1-$K18))*Hypothèses!$B$10,0)),1) -> 0.2 | G18: =(IF(B18=1,0,IF(B18=2,Hypothèses!$B$26,IF(B18=3,Hypothèses!$C$26,Hypothèses!$D$26)))+(IF(B18=1,Hypothèses!$B$26,IF(B18=2,Hypothèses!$C$26,IF(B18=3,Hypothèses!$D$26,Hypothèses!$D$26)))-(IF(B18=1,0,IF(B18=2,Hypothèses!$B$26,IF(B18=3,Hypothèses!$C$26,Hypothèses!$D$26)))))*((A18)-INT((A18-1)/12)*12)/12)*$B$1 -> 6.25 | H18: =(IF(B18=1,0,IF(B18=2,Hypothèses!$B$27,IF(B18=3,Hypothèses!$C$27,Hypothèses!$D$27)))+(IF(B18=1,Hypothèses!$B$27,IF(B18=2,Hypothèses!$C$27,IF(B18=3,Hypothèses!$D$27,Hypothèses!$D$27)))-(IF(B18=1,0,IF(B18=2,Hypothèses!$B$27,IF(B18=3,Hypothèses!$C$27,Hypothèses!$D$27)))))*((A18)-INT((A18-1)/12)*12)/12)*$B$1 -> 16.25 | I18: =(IF(B18=1,0,IF(B18=2,Hypothèses!$B$28,IF(B18=3,Hypothèses!$C$28,Hypothèses!$D$28)))+(IF(B18=1,Hypothèses!$B$28,IF(B18=2,Hypothèses!$C$28,IF(B18=3,Hypothèses!$D$28,Hypothèses!$D$28)))-(IF(B18=1,0,IF(B18=2,Hypothèses!$B$28,IF(B18=3,Hypothèses!$C$28,Hypothèses!$D$28)))))*((A18)-INT((A18-1)/12)*12)/12)*$B$1 -> 0.25 | J18: =(IF(B18=1,0,IF(B18=2,Hypothèses!$B$29,IF(B18=3,Hypothèses!$C$29,Hypothèses!$D$29)))+(IF(B18=1,Hypothèses!$B$29,IF(B18=2,Hypothèses!$C$29,IF(B18=3,Hypothèses!$D$29,Hypothèses!$D$29)))-(IF(B18=1,0,IF(B18=2,Hypothèses!$B$29,IF(B18=3,Hypothèses!$C$29,Hypothèses!$D$29)))))*((A18)-INT((A18-1)/12)*12)/12)*$B$1 -> 0.25 | K18: =IF(A18<Hypothèses!$B$7,0,Hypothèses!$B$8*(1-Hypothèses!$B$9)^(A18-Hypothèses!$B$7)) -> 0.02657205 | L18: =C18+D18+E18+F18 -> 19.4 | M18: =(C18*Hypothèses!$B$11+D18*Hypothèses!$B$12+E18*Hypothèses!$B$13+F18*Hypothèses!$B$14)*(IF(B18=1,Hypothèses!$B$20,IF(B18=2,Hypothèses!$B$21,Hypothèses!$B$22))+(1-(IF(B18=1,Hypothèses!$B$20,IF(B18=2,Hypothèses!$B$21,Hypothèses!$B$22))))*11/12) -> 2676.4333 | N18: =L18*IF(B18=1,Hypothèses!$C$20,IF(B18=2,Hypothèses!$C$21,Hypothèses!$C$22))*IF(B18=1,Hypothèses!$D$20,IF(B18=2,Hypothèses!$D$21,Hypothèses!$D$22)) -> 48.5 | O18: =IF(A18=18,IF($B$2>=1,Hypothèses!$B$33,0),IF(AND(OR(A18=30,A18=34),$D$2>=1),Hypothèses!$B$34*MIN(1,$D$2/3),0)) -> 0 | P18: =M18+N18+O18 -> 2724.9333 | Q18: =P18/(1+Hypothèses!$B$6) -> 2270.7778 | R18: =Hypothèses!$B$3*(1+Hypothèses!$B$4)^INT((A18-1)/3) -> 874.50312 | S18: =IF($A18>=13,1,0) -> 1 | T18: =S18*Hypothèses!$B$17 -> 4500 | U18: =Q18*Hypothèses!$B$5 -> 22.707778 | V18: =Q18-R18-T18-U18 -> -3126.4331 | W18: =W17+V18 -> -7594.0021
A19: 16 | B19: =INT((A19-1)/12)+1 -> 2 | C19: =ROUND(IF(MOD($A19,12)=0,G19,(IF(19=4,0,C18))*(1-$K19)+IF((IF(19=4,0,C18))*(1-$K19)<G19,(G19-(IF(19=4,0,C18))*(1-$K19))*Hypothèses!$B$10,0)),1) -> 5.9 | D19: =ROUND(IF(MOD($A19,12)=0,H19,(IF(19=4,0,D18))*(1-$K19)+IF((IF(19=4,0,D18))*(1-$K19)<H19,(H19-(IF(19=4,0,D18))*(1-$K19))*Hypothèses!$B$10,0)),1) -> 15.2 | E19: =ROUND(IF(MOD($A19,12)=0,I19,(IF(19=4,0,E18))*(1-$K19)+IF((IF(19=4,0,E18))*(1-$K19)<I19,(I19-(IF(19=4,0,E18))*(1-$K19))*Hypothèses!$B$10,0)),1) -> 0.3 | F19: =ROUND(IF(MOD($A19,12)=0,J19,(IF(19=4,0,F18))*(1-$K19)+IF((IF(19=4,0,F18))*(1-$K19)<J19,(J19-(IF(19=4,0,F18))*(1-$K19))*Hypothèses!$B$10,0)),1) -> 0.3 | G19: =(IF(B19=1,0,IF(B19=2,Hypothèses!$B$26,IF(B19=3,Hypothèses!$C$26,Hypothèses!$D$26)))+(IF(B19=1,Hypothèses!$B$26,IF(B19=2,Hypothèses!$C$26,IF(B19=3,Hypothèses!$D$26,Hypothèses!$D$26)))-(IF(B19=1,0,IF(B19=2,Hypothèses!$B$26,IF(B19=3,Hypothèses!$C$26,Hypothèses!$D$26)))))*((A19)-INT((A19-1)/12)*12)/12)*$B$1 -> 6.6666667 | H19: =(IF(B19=1,0,IF(B19=2,Hypothèses!$B$27,IF(B19=3,Hypothèses!$C$27,Hypothèses!$D$27)))+(IF(B19=1,Hypothèses!$B$27,IF(B19=2,Hypothèses!$C$27,IF(B19=3,Hypothèses!$D$27,Hypothèses!$D$27)))-(IF(B19=1,0,IF(B19=2,Hypothèses!$B$27,IF(B19=3,Hypothèses!$C$27,Hypothèses!$D$27)))))*((A19)-INT((A19-1)/12)*12)/12)*$B$1 -> 18.333333 | I19: =(IF(B19=1,0,IF(B19=2,Hypothèses!$B$28,IF(B19=3,Hypothèses!$C$28,Hypothèses!$D$28)))+(IF(B19=1,Hypothèses!$B$28,IF(B19=2,Hypothèses!$C$28,IF(B19=3,Hypothèses!$D$28,Hypothèses!$D$28)))-(IF(B19=1,0,IF(B19=2,Hypothèses!$B$28,IF(B19=3,Hypothèses!$C$28,Hypothèses!$D$28)))))*((A19)-INT((A19-1)/12)*12)/12)*$B$1 -> 0.33333333 | J19: =(IF(B19=1,0,IF(B19=2,Hypothèses!$B$29,IF(B19=3,Hypothèses!$C$29,Hypothèses!$D$29)))+(IF(B19=1,Hypothèses!$B$29,IF(B19=2,Hypothèses!$C$29,IF(B19=3,Hypothèses!$D$29,Hypothèses!$D$29)))-(IF(B19=1,0,IF(B19=2,Hypothèses!$B$29,IF(B19=3,Hypothèses!$C$29,Hypothèses!$D$29)))))*((A19)-INT((A19-1)/12)*12)/12)*$B$1 -> 0.33333333 | K19: =IF(A19<Hypothèses!$B$7,0,Hypothèses!$B$8*(1-Hypothèses!$B$9)^(A19-Hypothèses!$B$7)) -> 0.023914845 | L19: =C19+D19+E19+F19 -> 21.7 | M19: =(C19*Hypothèses!$B$11+D19*Hypothèses!$B$12+E19*Hypothèses!$B$13+F19*Hypothèses!$B$14)*(IF(B19=1,Hypothèses!$B$20,IF(B19=2,Hypothèses!$B$21,Hypothèses!$B$22))+(1-(IF(B19=1,Hypothèses!$B$20,IF(B19=2,Hypothèses!$B$21,Hypothèses!$B$22))))*11/12) -> 3101.7417 | N19: =L19*IF(B19=1,Hypothèses!$C$20,IF(B19=2,Hypothèses!$C$21,Hypothèses!$C$22))*IF(B19=1,Hypothèses!$D$20,IF(B19=2,Hypothèses!$D$21,Hypothèses!$D$22)) -> 54.25 | O19: =IF(A19=18,IF($B$2>=1,Hypothèses!$B$33,0),IF(AND(OR(A19=30,A19=34),$D$2>=1),Hypothèses!$B$34*MIN(1,$D$2/3),0)) -> 0 | P19: =M19+N19+O19 -> 3155.9917 | Q19: =P19/(1+Hypothèses!$B$6) -> 2629.9931 | R19: =Hypothèses!$B$3*(1+Hypothèses!$B$4)^INT((A19-1)/3) -> 1005.6786 | S19: =IF($A19>=13,1,0) -> 1 | T19: =S19*Hypothèses!$B$17 -> 4500 | U19: =Q19*Hypothèses!$B$5 -> 26.299931 | V19: =Q19-R19-T19-U19 -> -2901.9855 | W19: =W18+V19 -> -10495.988
A20: 17 | B20: =INT((A20-1)/12)+1 -> 2 | C20: =ROUND(IF(MOD($A20,12)=0,G20,(IF(20=4,0,C19))*(1-$K20)+IF((IF(20=4,0,C19))*(1-$K20)<G20,(G20-(IF(20=4,0,C19))*(1-$K20))*Hypothèses!$B$10,0)),1) -> 6.3 | D20: =ROUND(IF(MOD($A20,12)=0,H20,(IF(20=4,0,D19))*(1-$K20)+IF((IF(20=4,0,D19))*(1-$K20)<H20,(H20-(IF(20=4,0,D19))*(1-$K20))*Hypothèses!$B$10,0)),1) -> 17.1 | E20: =ROUND(IF(MOD($A20,12)=0,I20,(IF(20=4,0,E19))*(1-$K20)+IF((IF(20=4,0,E19))*(1-$K20)<I20,(I20-(IF(20=4,0,E19))*(1-$K20))*Hypothèses!$B$10,0)),1) -> 0.3 | F20: =ROUND(IF(MOD($A20,12)=0,J20,(IF(20=4,0,F19))*(1-$K20)+IF((IF(20=4,0,F19))*(1-$K20)<J20,(J20-(IF(20=4,0,F19))*(1-$K20))*Hypothèses!$B$10,0)),1) -> 0.3 | G20: =(IF(B20=1,0,IF(B20=2,Hypothèses!$B$26,IF(B20=3,Hypothèses!$C$26,Hypothèses!$D$26)))+(IF(B20=1,Hypothèses!$B$26,IF(B20=2,Hypothèses!$C$26,IF(B20=3,Hypothèses!$D$26,Hypothèses!$D$26)))-(IF(B20=1,0,IF(B20=2,Hypothèses!$B$26,IF(B20=3,Hypothèses!$C$26,Hypothèses!$D$26)))))*((A20)-INT((A20-1)/12)*12)/12)*$B$1 -> 7.0833333 | H20: =(IF(B20=1,0,IF(B20=2,Hypothèses!$B$27,IF(B20=3,Hypothèses!$C$27,Hypothèses!$D$27)))+(IF(B20=1,Hypothèses!$B$27,IF(B20=2,Hypothèses!$C$27,IF(B20=3,Hypothèses!$D$27,Hypothèses!$D$27)))-(IF(B20=1,0,IF(B20=2,Hypothèses!$B$27,IF(B20=3,Hypothèses!$C$27,Hypothèses!$D$27)))))*((A20)-INT((A20-1)/12)*12)/12)*$B$1 -> 20.416667 | I20: =(IF(B20=1,0,IF(B20=2,Hypothèses!$B$28,IF(B20=3,Hypothèses!$C$28,Hypothèses!$D$28)))+(IF(B20=1,Hypothèses!$B$28,IF(B20=2,Hypothèses!$C$28,IF(B20=3,Hypothèses!$D$28,Hypothèses!$D$28)))-(IF(B20=1,0,IF(B20=2,Hypothèses!$B$28,IF(B20=3,Hypothèses!$C$28,Hypothèses!$D$28)))))*((A20)-INT((A20-1)/12)*12)/12)*$B$1 -> 0.41666667 | J20: =(IF(B20=1,0,IF(B20=2,Hypothèses!$B$29,IF(B20=3,Hypothèses!$C$29,Hypothèses!$D$29)))+(IF(B20=1,Hypothèses!$B$29,IF(B20=2,Hypothèses!$C$29,IF(B20=3,Hypothèses!$D$29,Hypothèses!$D$29)))-(IF(B20=1,0,IF(B20=2,Hypothèses!$B$29,IF(B20=3,Hypothèses!$C$29,Hypothèses!$D$29)))))*((A20)-INT((A20-1)/12)*12)/12)*$B$1 -> 0.41666667 | K20: =IF(A20<Hypothèses!$B$7,0,Hypothèses!$B$8*(1-Hypothèses!$B$9)^(A20-Hypothèses!$B$7)) -> 0.021523361 | L20: =C20+D20+E20+F20 -> 24 | M20: =(C20*Hypothèses!$B$11+D20*Hypothèses!$B$12+E20*Hypothèses!$B$13+F20*Hypothèses!$B$14)*(IF(B20=1,Hypothèses!$B$20,IF(B20=2,Hypothèses!$B$21,Hypothèses!$B$22))+(1-(IF(B20=1,Hypothèses!$B$20,IF(B20=2,Hypothèses!$B$21,Hypothèses!$B$22))))*11/12) -> 3407.1625 | N20: =L20*IF(B20=1,Hypothèses!$C$20,IF(B20=2,Hypothèses!$C$21,Hypothèses!$C$22))*IF(B20=1,Hypothèses!$D$20,IF(B20=2,Hypothèses!$D$21,Hypothèses!$D$22)) -> 60 | O20: =IF(A20=18,IF($B$2>=1,Hypothèses!$B$33,0),IF(AND(OR(A20=30,A20=34),$D$2>=1),Hypothèses!$B$34*MIN(1,$D$2/3),0)) -> 0 | P20: =M20+N20+O20 -> 3467.1625 | Q20: =P20/(1+Hypothèses!$B$6) -> 2889.3021 | R20: =Hypothèses!$B$3*(1+Hypothèses!$B$4)^INT((A20-1)/3) -> 1005.6786 | S20: =IF($A20>=13,1,0) -> 1 | T20: =S20*Hypothèses!$B$17 -> 4500 | U20: =Q20*Hypothèses!$B$5 -> 28.893021 | V20: =Q20-R20-T20-U20 -> -2645.2695 | W20: =W19+V20 -> -13141.257
A21: 18 | B21: =INT((A21-1)/12)+1 -> 2 | C21: =ROUND(IF(MOD($A21,12)=0,G21,(IF(21=4,0,C20))*(1-$K21)+IF((IF(21=4,0,C20))*(1-$K21)<G21,(G21-(IF(21=4,0,C20))*(1-$K21))*Hypothèses!$B$10,0)),1) -> 6.7 | D21: =ROUND(IF(MOD($A21,12)=0,H21,(IF(21=4,0,D20))*(1-$K21)+IF((IF(21=4,0,D20))*(1-$K21)<H21,(H21-(IF(21=4,0,D20))*(1-$K21))*Hypothèses!$B$10,0)),1) -> 19.1 | E21: =ROUND(IF(MOD($A21,12)=0,I21,(IF(21=4,0,E20))*(1-$K21)+IF((IF(21=4,0,E20))*(1-$K21)<I21,(I21-(IF(21=4,0,E20))*(1-$K21))*Hypothèses!$B$10,0)),1) -> 0.4 | F21: =ROUND(IF(MOD($A21,12)=0,J21,(IF(21=4,0,F20))*(1-$K21)+IF((IF(21=4,0,F20))*(1-$K21)<J21,(J21-(IF(21=4,0,F20))*(1-$K21))*Hypothèses!$B$10,0)),1) -> 0.4 | G21: =(IF(B21=1,0,IF(B21=2,Hypothèses!$B$26,IF(B21=3,Hypothèses!$C$26,Hypothèses!$D$26)))+(IF(B21=1,Hypothèses!$B$26,IF(B21=2,Hypothèses!$C$26,IF(B21=3,Hypothèses!$D$26,Hypothèses!$D$26)))-(IF(B21=1,0,IF(B21=2,Hypothèses!$B$26,IF(B21=3,Hypothèses!$C$26,Hypothèses!$D$26)))))*((A21)-INT((A21-1)/12)*12)/12)*$B$1 -> 7.5 | H21: =(IF(B21=1,0,IF(B21=2,Hypothèses!$B$27,IF(B21=3,Hypothèses!$C$27,Hypothèses!$D$27)))+(IF(B21=1,Hypothèses!$B$27,IF(B21=2,Hypothèses!$C$27,IF(B21=3,Hypothèses!$D$27,Hypothèses!$D$27)))-(IF(B21=1,0,IF(B21=2,Hypothèses!$B$27,IF(B21=3,Hypothèses!$C$27,Hypothèses!$D$27)))))*((A21)-INT((A21-1)/12)*12)/12)*$B$1 -> 22.5 | I21: =(IF(B21=1,0,IF(B21=2,Hypothèses!$B$28,IF(B21=3,Hypothèses!$C$28,Hypothèses!$D$28)))+(IF(B21=1,Hypothèses!$B$28,IF(B21=2,Hypothèses!$C$28,IF(B21=3,Hypothèses!$D$28,Hypothèses!$D$28)))-(IF(B21=1,0,IF(B21=2,Hypothèses!$B$28,IF(B21=3,Hypothèses!$C$28,Hypothèses!$D$28)))))*((A21)-INT((A21-1)/12)*12)/12)*$B$1 -> 0.5 | J21: =(IF(B21=1,0,IF(B21=2,Hypothèses!$B$29,IF(B21=3,Hypothèses!$C$29,Hypothèses!$D$29)))+(IF(B21=1,Hypothèses!$B$29,IF(B21=2,Hypothèses!$C$29,IF(B21=3,Hypothèses!$D$29,Hypothèses!$D$29)))-(IF(B21=1,0,IF(B21=2,Hypothèses!$B$29,IF(B21=3,Hypothèses!$C$29,Hypothèses!$D$29)))))*((A21)-INT((A21-1)/12)*12)/12)*$B$1 -> 0.5 | K21: =IF(A21<Hypothèses!$B$7,0,Hypothèses!$B$8*(1-Hypothèses!$B$9)^(A21-Hypothèses!$B$7)) -> 0.019371024 | L21: =C21+D21+E21+F21 -> 26.6 | M21: =(C21*Hypothèses!$B$11+D21*Hypothèses!$B$12+E21*Hypothèses!$B$13+F21*Hypothèses!$B$14)*(IF(B21=1,Hypothèses!$B$20,IF(B21=2,Hypothèses!$B$21,Hypothèses!$B$22))+(1-(IF(B21=1,Hypothèses!$B$20,IF(B21=2,Hypothèses!$B$21,Hypothèses!$B$22))))*11/12) -> 3869.5583 | N21: =L21*IF(B21=1,Hypothèses!$C$20,IF(B21=2,Hypothèses!$C$21,Hypothèses!$C$22))*IF(B21=1,Hypothèses!$D$20,IF(B21=2,Hypothèses!$D$21,Hypothèses!$D$22)) -> 66.5 | O21: =IF(A21=18,IF($B$2>=1,Hypothèses!$B$33,0),IF(AND(OR(A21=30,A21=34),$D$2>=1),Hypothèses!$B$34*MIN(1,$D$2/3),0)) -> 15000 | P21: =M21+N21+O21 -> 18936.058 | Q21: =P21/(1+Hypothèses!$B$6) -> 15780.049 | R21: =Hypothèses!$B$3*(1+Hypothèses!$B$4)^INT((A21-1)/3) -> 1005.6786 | S21: =IF($A21>=13,1,0) -> 1 | T21: =S21*Hypothèses!$B$17 -> 4500 | U21: =Q21*Hypothèses!$B$5 -> 157.80049 | V21: =Q21-R21-T21-U21 -> 10116.57 | W21: =W20+V21 -> -3024.6875
A22: 19 | B22: =INT((A22-1)/12)+1 -> 2 | C22: =ROUND(IF(MOD($A22,12)=0,G22,(IF(22=4,0,C21))*(1-$K22)+IF((IF(22=4,0,C21))*(1-$K22)<G22,(G22-(IF(22=4,0,C21))*(1-$K22))*Hypothèses!$B$10,0)),1) -> 7.1 | D22: =ROUND(IF(MOD($A22,12)=0,H22,(IF(22=4,0,D21))*(1-$K22)+IF((IF(22=4,0,D21))*(1-$K22)<H22,(H22-(IF(22=4,0,D21))*(1-$K22))*Hypothèses!$B$10,0)),1) -> 21.1 | E22: =ROUND(IF(MOD($A22,12)=0,I22,(IF(22=4,0,E21))*(1-$K22)+IF((IF(22=4,0,E21))*(1-$K22)<I22,(I22-(IF(22=4,0,E21))*(1-$K22))*Hypothèses!$B$10,0)),1) -> 0.5 | F22: =ROUND(IF(MOD($A22,12)=0,J22,(IF(22=4,0,F21))*(1-$K22)+IF((IF(22=4,0,F21))*(1-$K22)<J22,(J22-(IF(22=4,0,F21))*(1-$K22))*Hypothèses!$B$10,0)),1) -> 0.5 | G22: =(IF(B22=1,0,IF(B22=2,Hypothèses!$B$26,IF(B22=3,Hypothèses!$C$26,Hypothèses!$D$26)))+(IF(B22=1,Hypothèses!$B$26,IF(B22=2,Hypothèses!$C$26,IF(B22=3,Hypothèses!$D$26,Hypothèses!$D$26)))-(IF(B22=1,0,IF(B22=2,Hypothèses!$B$26,IF(B22=3,Hypothèses!$C$26,Hypothèses!$D$26)))))*((A22)-INT((A22-1)/12)*12)/12)*$B$1 -> 7.9166667 | H22: =(IF(B22=1,0,IF(B22=2,Hypothèses!$B$27,IF(B22=3,Hypothèses!$C$27,Hypothèses!$D$27)))+(IF(B22=1,Hypothèses!$B$27,IF(B22=2,Hypothèses!$C$27,IF(B22=3,Hypothèses!$D$27,Hypothèses!$D$27)))-(IF(B22=1,0,IF(B22=2,Hypothèses!$B$27,IF(B22=3,Hypothèses!$C$27,Hypothèses!$D$27)))))*((A22)-INT((A22-1)/12)*12)/12)*$B$1 -> 24.583333 | I22: =(IF(B22=1,0,IF(B22=2,Hypothèses!$B$28,IF(B22=3,Hypothèses!$C$28,Hypothèses!$D$28)))+(IF(B22=1,Hypothèses!$B$28,IF(B22=2,Hypothèses!$C$28,IF(B22=3,Hypothèses!$D$28,Hypothèses!$D$28)))-(IF(B22=1,0,IF(B22=2,Hypothèses!$B$28,IF(B22=3,Hypothèses!$C$28,Hypothèses!$D$28)))))*((A22)-INT((A22-1)/12)*12)/12)*$B$1 -> 0.58333333 | J22: =(IF(B22=1,0,IF(B22=2,Hypothèses!$B$29,IF(B22=3,Hypothèses!$C$29,Hypothèses!$D$29)))+(IF(B22=1,Hypothèses!$B$29,IF(B22=2,Hypothèses!$C$29,IF(B22=3,Hypothèses!$D$29,Hypothèses!$D$29)))-(IF(B22=1,0,IF(B22=2,Hypothèses!$B$29,IF(B22=3,Hypothèses!$C$29,Hypothèses!$D$29)))))*((A22)-INT((A22-1)/12)*12)/12)*$B$1 -> 0.58333333 | K22: =IF(A22<Hypothèses!$B$7,0,Hypothèses!$B$8*(1-Hypothèses!$B$9)^(A22-Hypothèses!$B$7)) -> 0.017433922 | L22: =C22+D22+E22+F22 -> 29.2 | M22: =(C22*Hypothèses!$B$11+D22*Hypothèses!$B$12+E22*Hypothèses!$B$13+F22*Hypothèses!$B$14)*(IF(B22=1,Hypothèses!$B$20,IF(B22=2,Hypothèses!$B$21,Hypothèses!$B$22))+(1-(IF(B22=1,Hypothèses!$B$20,IF(B22=2,Hypothèses!$B$21,Hypothèses!$B$22))))*11/12) -> 4331.9542 | N22: =L22*IF(B22=1,Hypothèses!$C$20,IF(B22=2,Hypothèses!$C$21,Hypothèses!$C$22))*IF(B22=1,Hypothèses!$D$20,IF(B22=2,Hypothèses!$D$21,Hypothèses!$D$22)) -> 73 | O22: =IF(A22=18,IF($B$2>=1,Hypothèses!$B$33,0),IF(AND(OR(A22=30,A22=34),$D$2>=1),Hypothèses!$B$34*MIN(1,$D$2/3),0)) -> 0 | P22: =M22+N22+O22 -> 4404.9542 | Q22: =P22/(1+Hypothèses!$B$6) -> 3670.7951 | R22: =Hypothèses!$B$3*(1+Hypothèses!$B$4)^INT((A22-1)/3) -> 1156.5304 | S22: =IF($A22>=13,1,0) -> 1 | T22: =S22*Hypothèses!$B$17 -> 4500 | U22: =Q22*Hypothèses!$B$5 -> 36.707951 | V22: =Q22-R22-T22-U22 -> -2022.4432 | W22: =W21+V22 -> -5047.1307
A23: 20 | B23: =INT((A23-1)/12)+1 -> 2 | C23: =ROUND(IF(MOD($A23,12)=0,G23,(IF(23=4,0,C22))*(1-$K23)+IF((IF(23=4,0,C22))*(1-$K23)<G23,(G23-(IF(23=4,0,C22))*(1-$K23))*Hypothèses!$B$10,0)),1) -> 7.5 | D23: =ROUND(IF(MOD($A23,12)=0,H23,(IF(23=4,0,D22))*(1-$K23)+IF((IF(23=4,0,D22))*(1-$K23)<H23,(H23-(IF(23=4,0,D22))*(1-$K23))*Hypothèses!$B$10,0)),1) -> 23.1 | E23: =ROUND(IF(MOD($A23,12)=0,I23,(IF(23=4,0,E22))*(1-$K23)+IF((IF(23=4,0,E22))*(1-$K23)<I23,(I23-(IF(23=4,0,E22))*(1-$K23))*Hypothèses!$B$10,0)),1) -> 0.6 | F23: =ROUND(IF(MOD($A23,12)=0,J23,(IF(23=4,0,F22))*(1-$K23)+IF((IF(23=4,0,F22))*(1-$K23)<J23,(J23-(IF(23=4,0,F22))*(1-$K23))*Hypothèses!$B$10,0)),1) -> 0.6 | G23: =(IF(B23=1,0,IF(B23=2,Hypothèses!$B$26,IF(B23=3,Hypothèses!$C$26,Hypothèses!$D$26)))+(IF(B23=1,Hypothèses!$B$26,IF(B23=2,Hypothèses!$C$26,IF(B23=3,Hypothèses!$D$26,Hypothèses!$D$26)))-(IF(B23=1,0,IF(B23=2,Hypothèses!$B$26,IF(B23=3,Hypothèses!$C$26,Hypothèses!$D$26)))))*((A23)-INT((A23-1)/12)*12)/12)*$B$1 -> 8.3333333 | H23: =(IF(B23=1,0,IF(B23=2,Hypothèses!$B$27,IF(B23=3,Hypothèses!$C$27,Hypothèses!$D$27)))+(IF(B23=1,Hypothèses!$B$27,IF(B23=2,Hypothèses!$C$27,IF(B23=3,Hypothèses!$D$27,Hypothèses!$D$27)))-(IF(B23=1,0,IF(B23=2,Hypothèses!$B$27,IF(B23=3,Hypothèses!$C$27,Hypothèses!$D$27)))))*((A23)-INT((A23-1)/12)*12)/12)*$B$1 -> 26.666667 | I23: =(IF(B23=1,0,IF(B23=2,Hypothèses!$B$28,IF(B23=3,Hypothèses!$C$28,Hypothèses!$D$28)))+(IF(B23=1,Hypothèses!$B$28,IF(B23=2,Hypothèses!$C$28,IF(B23=3,Hypothèses!$D$28,Hypothèses!$D$28)))-(IF(B23=1,0,IF(B23=2,Hypothèses!$B$28,IF(B23=3,Hypothèses!$C$28,Hypothèses!$D$28)))))*((A23)-INT((A23-1)/12)*12)/12)*$B$1 -> 0.66666667 | J23: =(IF(B23=1,0,IF(B23=2,Hypothèses!$B$29,IF(B23=3,Hypothèses!$C$29,Hypothèses!$D$29)))+(IF(B23=1,Hypothèses!$B$29,IF(B23=2,Hypothèses!$C$29,IF(B23=3,Hypothèses!$D$29,Hypothèses!$D$29)))-(IF(B23=1,0,IF(B23=2,Hypothèses!$B$29,IF(B23=3,Hypothèses!$C$29,Hypothèses!$D$29)))))*((A23)-INT((A23-1)/12)*12)/12)*$B$1 -> 0.66666667 | K23: =IF(A23<Hypothèses!$B$7,0,Hypothèses!$B$8*(1-Hypothèses!$B$9)^(A23-Hypothèses!$B$7)) -> 0.01569053 | L23: =C23+D23+E23+F23 -> 31.8 | M23: =(C23*Hypothèses!$B$11+D23*Hypothèses!$B$12+E23*Hypothèses!$B$13+F23*Hypothèses!$B$14)*(IF(B23=1,Hypothèses!$B$20,IF(B23=2,Hypothèses!$B$21,Hypothèses!$B$22))+(1-(IF(B23=1,Hypothèses!$B$20,IF(B23=2,Hypothèses!$B$21,Hypothèses!$B$22))))*11/12) -> 4794.35 | N23: =L23*IF(B23=1,Hypothèses!$C$20,IF(B23=2,Hypothèses!$C$21,Hypothèses!$C$22))*IF(B23=1,Hypothèses!$D$20,IF(B23=2,Hypothèses!$D$21,Hypothèses!$D$22)) -> 79.5 | O23: =IF(A23=18,IF($B$2>=1,Hypothèses!$B$33,0),IF(AND(OR(A23=30,A23=34),$D$2>=1),Hypothèses!$B$34*MIN(1,$D$2/3),0)) -> 0 | P23: =M23+N23+O23 -> 4873.85 | Q23: =P23/(1+Hypothèses!$B$6) -> 4061.5417 | R23: =Hypothèses!$B$3*(1+Hypothèses!$B$4)^INT((A23-1)/3) -> 1156.5304 | S23: =IF($A23>=13,1,0) -> 1 | T23: =S23*Hypothèses!$B$17 -> 4500 | U23: =Q23*Hypothèses!$B$5 -> 40.615417 | V23: =Q23-R23-T23-U23 -> -1635.6041 | W23: =W22+V23 -> -6682.7349
A24: 21 | B24: =INT((A24-1)/12)+1 -> 2 | C24: =ROUND(IF(MOD($A24,12)=0,G24,(IF(24=4,0,C23))*(1-$K24)+IF((IF(24=4,0,C23))*(1-$K24)<G24,(G24-(IF(24=4,0,C23))*(1-$K24))*Hypothèses!$B$10,0)),1) -> 7.9 | D24: =ROUND(IF(MOD($A24,12)=0,H24,(IF(24=4,0,D23))*(1-$K24)+IF((IF(24=4,0,D23))*(1-$K24)<H24,(H24-(IF(24=4,0,D23))*(1-$K24))*Hypothèses!$B$10,0)),1) -> 25.2 | E24: =ROUND(IF(MOD($A24,12)=0,I24,(IF(24=4,0,E23))*(1-$K24)+IF((IF(24=4,0,E23))*(1-$K24)<I24,(I24-(IF(24=4,0,E23))*(1-$K24))*Hypothèses!$B$10,0)),1) -> 0.7 | F24: =ROUND(IF(MOD($A24,12)=0,J24,(IF(24=4,0,F23))*(1-$K24)+IF((IF(24=4,0,F23))*(1-$K24)<J24,(J24-(IF(24=4,0,F23))*(1-$K24))*Hypothèses!$B$10,0)),1) -> 0.7 | G24: =(IF(B24=1,0,IF(B24=2,Hypothèses!$B$26,IF(B24=3,Hypothèses!$C$26,Hypothèses!$D$26)))+(IF(B24=1,Hypothèses!$B$26,IF(B24=2,Hypothèses!$C$26,IF(B24=3,Hypothèses!$D$26,Hypothèses!$D$26)))-(IF(B24=1,0,IF(B24=2,Hypothèses!$B$26,IF(B24=3,Hypothèses!$C$26,Hypothèses!$D$26)))))*((A24)-INT((A24-1)/12)*12)/12)*$B$1 -> 8.75 | H24: =(IF(B24=1,0,IF(B24=2,Hypothèses!$B$27,IF(B24=3,Hypothèses!$C$27,Hypothèses!$D$27)))+(IF(B24=1,Hypothèses!$B$27,IF(B24=2,Hypothèses!$C$27,IF(B24=3,Hypothèses!$D$27,Hypothèses!$D$27)))-(IF(B24=1,0,IF(B24=2,Hypothèses!$B$27,IF(B24=3,Hypothèses!$C$27,Hypothèses!$D$27)))))*((A24)-INT((A24-1)/12)*12)/12)*$B$1 -> 28.75 | I24: =(IF(B24=1,0,IF(B24=2,Hypothèses!$B$28,IF(B24=3,Hypothèses!$C$28,Hypothèses!$D$28)))+(IF(B24=1,Hypothèses!$B$28,IF(B24=2,Hypothèses!$C$28,IF(B24=3,Hypothèses!$D$28,Hypothèses!$D$28)))-(IF(B24=1,0,IF(B24=2,Hypothèses!$B$28,IF(B24=3,Hypothèses!$C$28,Hypothèses!$D$28)))))*((A24)-INT((A24-1)/12)*12)/12)*$B$1 -> 0.75 | J24: =(IF(B24=1,0,IF(B24=2,Hypothèses!$B$29,IF(B24=3,Hypothèses!$C$29,Hypothèses!$D$29)))+(IF(B24=1,Hypothèses!$B$29,IF(B24=2,Hypothèses!$C$29,IF(B24=3,Hypothèses!$D$29,Hypothèses!$D$29)))-(IF(B24=1,0,IF(B24=2,Hypothèses!$B$29,IF(B24=3,Hypothèses!$C$29,Hypothèses!$D$29)))))*((A24)-INT((A24-1)/12)*12)/12)*$B$1 -> 0.75 | K24: =IF(A24<Hypothèses!$B$7,0,Hypothèses!$B$8*(1-Hypothèses!$B$9)^(A24-Hypothèses!$B$7)) -> 0.014121477 | L24: =C24+D24+E24+F24 -> 34.5 | M24: =(C24*Hypothèses!$B$11+D24*Hypothèses!$B$12+E24*Hypothèses!$B$13+F24*Hypothèses!$B$14)*(IF(B24=1,Hypothèses!$B$20,IF(B24=2,Hypothèses!$B$21,Hypothèses!$B$22))+(1-(IF(B24=1,Hypothèses!$B$20,IF(B24=2,Hypothèses!$B$21,Hypothèses!$B$22))))*11/12) -> 5271.025 | N24: =L24*IF(B24=1,Hypothèses!$C$20,IF(B24=2,Hypothèses!$C$21,Hypothèses!$C$22))*IF(B24=1,Hypothèses!$D$20,IF(B24=2,Hypothèses!$D$21,Hypothèses!$D$22)) -> 86.25 | O24: =IF(A24=18,IF($B$2>=1,Hypothèses!$B$33,0),IF(AND(OR(A24=30,A24=34),$D$2>=1),Hypothèses!$B$34*MIN(1,$D$2/3),0)) -> 0 | P24: =M24+N24+O24 -> 5357.275 | Q24: =P24/(1+Hypothèses!$B$6) -> 4464.3958 | R24: =Hypothèses!$B$3*(1+Hypothèses!$B$4)^INT((A24-1)/3) -> 1156.5304 | S24: =IF($A24>=13,1,0) -> 1 | T24: =S24*Hypothèses!$B$17 -> 4500 | U24: =Q24*Hypothèses!$B$5 -> 44.643958 | V24: =Q24-R24-T24-U24 -> -1236.7785 | W24: =W23+V24 -> -7919.5134
A25: 22 | B25: =INT((A25-1)/12)+1 -> 2 | C25: =ROUND(IF(MOD($A25,12)=0,G25,(IF(25=4,0,C24))*(1-$K25)+IF((IF(25=4,0,C24))*(1-$K25)<G25,(G25-(IF(25=4,0,C24))*(1-$K25))*Hypothèses!$B$10,0)),1) -> 8.3 | D25: =ROUND(IF(MOD($A25,12)=0,H25,(IF(25=4,0,D24))*(1-$K25)+IF((IF(25=4,0,D24))*(1-$K25)<H25,(H25-(IF(25=4,0,D24))*(1-$K25))*Hypothèses!$B$10,0)),1) -> 27.3 | E25: =ROUND(IF(MOD($A25,12)=0,I25,(IF(25=4,0,E24))*(1-$K25)+IF((IF(25=4,0,E24))*(1-$K25)<I25,(I25-(IF(25=4,0,E24))*(1-$K25))*Hypothèses!$B$10,0)),1) -> 0.7 | F25: =ROUND(IF(MOD($A25,12)=0,J25,(IF(25=4,0,F24))*(1-$K25)+IF((IF(25=4,0,F24))*(1-$K25)<J25,(J25-(IF(25=4,0,F24))*(1-$K25))*Hypothèses!$B$10,0)),1) -> 0.7 | G25: =(IF(B25=1,0,IF(B25=2,Hypothèses!$B$26,IF(B25=3,Hypothèses!$C$26,Hypothèses!$D$26)))+(IF(B25=1,Hypothèses!$B$26,IF(B25=2,Hypothèses!$C$26,IF(B25=3,Hypothèses!$D$26,Hypothèses!$D$26)))-(IF(B25=1,0,IF(B25=2,Hypothèses!$B$26,IF(B25=3,Hypothèses!$C$26,Hypothèses!$D$26)))))*((A25)-INT((A25-1)/12)*12)/12)*$B$1 -> 9.1666667 | H25: =(IF(B25=1,0,IF(B25=2,Hypothèses!$B$27,IF(B25=3,Hypothèses!$C$27,Hypothèses!$D$27)))+(IF(B25=1,Hypothèses!$B$27,IF(B25=2,Hypothèses!$C$27,IF(B25=3,Hypothèses!$D$27,Hypothèses!$D$27)))-(IF(B25=1,0,IF(B25=2,Hypothèses!$B$27,IF(B25=3,Hypothèses!$C$27,Hypothèses!$D$27)))))*((A25)-INT((A25-1)/12)*12)/12)*$B$1 -> 30.833333 | I25: =(IF(B25=1,0,IF(B25=2,Hypothèses!$B$28,IF(B25=3,Hypothèses!$C$28,Hypothèses!$D$28)))+(IF(B25=1,Hypothèses!$B$28,IF(B25=2,Hypothèses!$C$28,IF(B25=3,Hypothèses!$D$28,Hypothèses!$D$28)))-(IF(B25=1,0,IF(B25=2,Hypothèses!$B$28,IF(B25=3,Hypothèses!$C$28,Hypothèses!$D$28)))))*((A25)-INT((A25-1)/12)*12)/12)*$B$1 -> 0.83333333 | J25: =(IF(B25=1,0,IF(B25=2,Hypothèses!$B$29,IF(B25=3,Hypothèses!$C$29,Hypothèses!$D$29)))+(IF(B25=1,Hypothèses!$B$29,IF(B25=2,Hypothèses!$C$29,IF(B25=3,Hypothèses!$D$29,Hypothèses!$D$29)))-(IF(B25=1,0,IF(B25=2,Hypothèses!$B$29,IF(B25=3,Hypothèses!$C$29,Hypothèses!$D$29)))))*((A25)-INT((A25-1)/12)*12)/12)*$B$1 -> 0.83333333 | K25: =IF(A25<Hypothèses!$B$7,0,Hypothèses!$B$8*(1-Hypothèses!$B$9)^(A25-Hypothèses!$B$7)) -> 0.012709329 | L25: =C25+D25+E25+F25 -> 37 | M25: =(C25*Hypothèses!$B$11+D25*Hypothèses!$B$12+E25*Hypothèses!$B$13+F25*Hypothèses!$B$14)*(IF(B25=1,Hypothèses!$B$20,IF(B25=2,Hypothèses!$B$21,Hypothèses!$B$22))+(1-(IF(B25=1,Hypothèses!$B$20,IF(B25=2,Hypothèses!$B$21,Hypothèses!$B$22))))*11/12) -> 5605.0042 | N25: =L25*IF(B25=1,Hypothèses!$C$20,IF(B25=2,Hypothèses!$C$21,Hypothèses!$C$22))*IF(B25=1,Hypothèses!$D$20,IF(B25=2,Hypothèses!$D$21,Hypothèses!$D$22)) -> 92.5 | O25: =IF(A25=18,IF($B$2>=1,Hypothèses!$B$33,0),IF(AND(OR(A25=30,A25=34),$D$2>=1),Hypothèses!$B$34*MIN(1,$D$2/3),0)) -> 0 | P25: =M25+N25+O25 -> 5697.5042 | Q25: =P25/(1+Hypothèses!$B$6) -> 4747.9201 | R25: =Hypothèses!$B$3*(1+Hypothèses!$B$4)^INT((A25-1)/3) -> 1330.0099 | S25: =IF($A25>=13,1,0) -> 1 | T25: =S25*Hypothèses!$B$17 -> 4500 | U25: =Q25*Hypothèses!$B$5 -> 47.479201 | V25: =Q25-R25-T25-U25 -> -1129.569 | W25: =W24+V25 -> -9049.0824
A26: 23 | B26: =INT((A26-1)/12)+1 -> 2 | C26: =ROUND(IF(MOD($A26,12)=0,G26,(IF(26=4,0,C25))*(1-$K26)+IF((IF(26=4,0,C25))*(1-$K26)<G26,(G26-(IF(26=4,0,C25))*(1-$K26))*Hypothèses!$B$10,0)),1) -> 8.8 | D26: =ROUND(IF(MOD($A26,12)=0,H26,(IF(26=4,0,D25))*(1-$K26)+IF((IF(26=4,0,D25))*(1-$K26)<H26,(H26-(IF(26=4,0,D25))*(1-$K26))*Hypothèses!$B$10,0)),1) -> 29.4 | E26: =ROUND(IF(MOD($A26,12)=0,I26,(IF(26=4,0,E25))*(1-$K26)+IF((IF(26=4,0,E25))*(1-$K26)<I26,(I26-(IF(26=4,0,E25))*(1-$K26))*Hypothèses!$B$10,0)),1) -> 0.8 | F26: =ROUND(IF(MOD($A26,12)=0,J26,(IF(26=4,0,F25))*(1-$K26)+IF((IF(26=4,0,F25))*(1-$K26)<J26,(J26-(IF(26=4,0,F25))*(1-$K26))*Hypothèses!$B$10,0)),1) -> 0.8 | G26: =(IF(B26=1,0,IF(B26=2,Hypothèses!$B$26,IF(B26=3,Hypothèses!$C$26,Hypothèses!$D$26)))+(IF(B26=1,Hypothèses!$B$26,IF(B26=2,Hypothèses!$C$26,IF(B26=3,Hypothèses!$D$26,Hypothèses!$D$26)))-(IF(B26=1,0,IF(B26=2,Hypothèses!$B$26,IF(B26=3,Hypothèses!$C$26,Hypothèses!$D$26)))))*((A26)-INT((A26-1)/12)*12)/12)*$B$1 -> 9.5833333 | H26: =(IF(B26=1,0,IF(B26=2,Hypothèses!$B$27,IF(B26=3,Hypothèses!$C$27,Hypothèses!$D$27)))+(IF(B26=1,Hypothèses!$B$27,IF(B26=2,Hypothèses!$C$27,IF(B26=3,Hypothèses!$D$27,Hypothèses!$D$27)))-(IF(B26=1,0,IF(B26=2,Hypothèses!$B$27,IF(B26=3,Hypothèses!$C$27,Hypothèses!$D$27)))))*((A26)-INT((A26-1)/12)*12)/12)*$B$1 -> 32.916667 | I26: =(IF(B26=1,0,IF(B26=2,Hypothèses!$B$28,IF(B26=3,Hypothèses!$C$28,Hypothèses!$D$28)))+(IF(B26=1,Hypothèses!$B$28,IF(B26=2,Hypothèses!$C$28,IF(B26=3,Hypothèses!$D$28,Hypothèses!$D$28)))-(IF(B26=1,0,IF(B26=2,Hypothèses!$B$28,IF(B26=3,Hypothèses!$C$28,Hypothèses!$D$28)))))*((A26)-INT((A26-1)/12)*12)/12)*$B$1 -> 0.91666667 | J26: =(IF(B26=1,0,IF(B26=2,Hypothèses!$B$29,IF(B26=3,Hypothèses!$C$29,Hypothèses!$D$29)))+(IF(B26=1,Hypothèses!$B$29,IF(B26=2,Hypothèses!$C$29,IF(B26=3,Hypothèses!$D$29,Hypothèses!$D$29)))-(IF(B26=1,0,IF(B26=2,Hypothèses!$B$29,IF(B26=3,Hypothèses!$C$29,Hypothèses!$D$29)))))*((A26)-INT((A26-1)/12)*12)/12)*$B$1 -> 0.91666667 | K26: =IF(A26<Hypothèses!$B$7,0,Hypothèses!$B$8*(1-Hypothèses!$B$9)^(A26-Hypothèses!$B$7)) -> 0.011438396 | L26: =C26+D26+E26+F26 -> 39.8 | M26: =(C26*Hypothèses!$B$11+D26*Hypothèses!$B$12+E26*Hypothèses!$B$13+F26*Hypothèses!$B$14)*(IF(B26=1,Hypothèses!$B$20,IF(B26=2,Hypothèses!$B$21,Hypothèses!$B$22))+(1-(IF(B26=1,Hypothèses!$B$20,IF(B26=2,Hypothèses!$B$21,Hypothèses!$B$22))))*11/12) -> 6090.2083 | N26: =L26*IF(B26=1,Hypothèses!$C$20,IF(B26=2,Hypothèses!$C$21,Hypothèses!$C$22))*IF(B26=1,Hypothèses!$D$20,IF(B26=2,Hypothèses!$D$21,Hypothèses!$D$22)) -> 99.5 | O26: =IF(A26=18,IF($B$2>=1,Hypothèses!$B$33,0),IF(AND(OR(A26=30,A26=34),$D$2>=1),Hypothèses!$B$34*MIN(1,$D$2/3),0)) -> 0 | P26: =M26+N26+O26 -> 6189.7083 | Q26: =P26/(1+Hypothèses!$B$6) -> 5158.0903 | R26: =Hypothèses!$B$3*(1+Hypothèses!$B$4)^INT((A26-1)/3) -> 1330.0099 | S26: =IF($A26>=13,1,0) -> 1 | T26: =S26*Hypothèses!$B$17 -> 4500 | U26: =Q26*Hypothèses!$B$5 -> 51.580903 | V26: =Q26-R26-T26-U26 -> -723.50057 | W26: =W25+V26 -> -9772.5829
A27: 24 | B27: =INT((A27-1)/12)+1 -> 2 | C27: =ROUND(IF(MOD($A27,12)=0,G27,(IF(27=4,0,C26))*(1-$K27)+IF((IF(27=4,0,C26))*(1-$K27)<G27,(G27-(IF(27=4,0,C26))*(1-$K27))*Hypothèses!$B$10,0)),1) -> 10 | D27: =ROUND(IF(MOD($A27,12)=0,H27,(IF(27=4,0,D26))*(1-$K27)+IF((IF(27=4,0,D26))*(1-$K27)<H27,(H27-(IF(27=4,0,D26))*(1-$K27))*Hypothèses!$B$10,0)),1) -> 35 | E27: =ROUND(IF(MOD($A27,12)=0,I27,(IF(27=4,0,E26))*(1-$K27)+IF((IF(27=4,0,E26))*(1-$K27)<I27,(I27-(IF(27=4,0,E26))*(1-$K27))*Hypothèses!$B$10,0)),1) -> 1 | F27: =ROUND(IF(MOD($A27,12)=0,J27,(IF(27=4,0,F26))*(1-$K27)+IF((IF(27=4,0,F26))*(1-$K27)<J27,(J27-(IF(27=4,0,F26))*(1-$K27))*Hypothèses!$B$10,0)),1) -> 1 | G27: =(IF(B27=1,0,IF(B27=2,Hypothèses!$B$26,IF(B27=3,Hypothèses!$C$26,Hypothèses!$D$26)))+(IF(B27=1,Hypothèses!$B$26,IF(B27=2,Hypothèses!$C$26,IF(B27=3,Hypothèses!$D$26,Hypothèses!$D$26)))-(IF(B27=1,0,IF(B27=2,Hypothèses!$B$26,IF(B27=3,Hypothèses!$C$26,Hypothèses!$D$26)))))*((A27)-INT((A27-1)/12)*12)/12)*$B$1 -> 10 | H27: =(IF(B27=1,0,IF(B27=2,Hypothèses!$B$27,IF(B27=3,Hypothèses!$C$27,Hypothèses!$D$27)))+(IF(B27=1,Hypothèses!$B$27,IF(B27=2,Hypothèses!$C$27,IF(B27=3,Hypothèses!$D$27,Hypothèses!$D$27)))-(IF(B27=1,0,IF(B27=2,Hypothèses!$B$27,IF(B27=3,Hypothèses!$C$27,Hypothèses!$D$27)))))*((A27)-INT((A27-1)/12)*12)/12)*$B$1 -> 35 | I27: =(IF(B27=1,0,IF(B27=2,Hypothèses!$B$28,IF(B27=3,Hypothèses!$C$28,Hypothèses!$D$28)))+(IF(B27=1,Hypothèses!$B$28,IF(B27=2,Hypothèses!$C$28,IF(B27=3,Hypothèses!$D$28,Hypothèses!$D$28)))-(IF(B27=1,0,IF(B27=2,Hypothèses!$B$28,IF(B27=3,Hypothèses!$C$28,Hypothèses!$D$28)))))*((A27)-INT((A27-1)/12)*12)/12)*$B$1 -> 1 | J27: =(IF(B27=1,0,IF(B27=2,Hypothèses!$B$29,IF(B27=3,Hypothèses!$C$29,Hypothèses!$D$29)))+(IF(B27=1,Hypothèses!$B$29,IF(B27=2,Hypothèses!$C$29,IF(B27=3,Hypothèses!$D$29,Hypothèses!$D$29)))-(IF(B27=1,0,IF(B27=2,Hypothèses!$B$29,IF(B27=3,Hypothèses!$C$29,Hypothèses!$D$29)))))*((A27)-INT((A27-1)/12)*12)/12)*$B$1 -> 1 | K27: =IF(A27<Hypothèses!$B$7,0,Hypothèses!$B$8*(1-Hypothèses!$B$9)^(A27-Hypothèses!$B$7)) -> 0.010294557 | L27: =C27+D27+E27+F27 -> 47 | M27: =(C27*Hypothèses!$B$11+D27*Hypothèses!$B$12+E27*Hypothèses!$B$13+F27*Hypothèses!$B$14)*(IF(B27=1,Hypothèses!$B$20,IF(B27=2,Hypothèses!$B$21,Hypothèses!$B$22))+(1-(IF(B27=1,Hypothèses!$B$20,IF(B27=2,Hypothèses!$B$21,Hypothèses!$B$22))))*11/12) -> 7277.5833 | N27: =L27*IF(B27=1,Hypothèses!$C$20,IF(B27=2,Hypothèses!$C$21,Hypothèses!$C$22))*IF(B27=1,Hypothèses!$D$20,IF(B27=2,Hypothèses!$D$21,Hypothèses!$D$22)) -> 117.5 | O27: =IF(A27=18,IF($B$2>=1,Hypothèses!$B$33,0),IF(AND(OR(A27=30,A27=34),$D$2>=1),Hypothèses!$B$34*MIN(1,$D$2/3),0)) -> 0 | P27: =M27+N27+O27 -> 7395.0833 | Q27: =P27/(1+Hypothèses!$B$6) -> 6162.5694 | R27: =Hypothèses!$B$3*(1+Hypothèses!$B$4)^INT((A27-1)/3) -> 1330.0099 | S27: =IF($A27>=13,1,0) -> 1 | T27: =S27*Hypothèses!$B$17 -> 4500 | U27: =Q27*Hypothèses!$B$5 -> 61.625694 | V27: =Q27-R27-T27-U27 -> 270.93381 | W27: =W26+V27 -> -9501.6491
A28: 25 | B28: =INT((A28-1)/12)+1 -> 3 | C28: =ROUND(IF(MOD($A28,12)=0,G28,(IF(28=4,0,C27))*(1-$K28)+IF((IF(28=4,0,C27))*(1-$K28)<G28,(G28-(IF(28=4,0,C27))*(1-$K28))*Hypothèses!$B$10,0)),1) -> 10.3 | D28: =ROUND(IF(MOD($A28,12)=0,H28,(IF(28=4,0,D27))*(1-$K28)+IF((IF(28=4,0,D27))*(1-$K28)<H28,(H28-(IF(28=4,0,D27))*(1-$K28))*Hypothèses!$B$10,0)),1) -> 36 | E28: =ROUND(IF(MOD($A28,12)=0,I28,(IF(28=4,0,E27))*(1-$K28)+IF((IF(28=4,0,E27))*(1-$K28)<I28,(I28-(IF(28=4,0,E27))*(1-$K28))*Hypothèses!$B$10,0)),1) -> 1.1 | F28: =ROUND(IF(MOD($A28,12)=0,J28,(IF(28=4,0,F27))*(1-$K28)+IF((IF(28=4,0,F27))*(1-$K28)<J28,(J28-(IF(28=4,0,F27))*(1-$K28))*Hypothèses!$B$10,0)),1) -> 1 | G28: =(IF(B28=1,0,IF(B28=2,Hypothèses!$B$26,IF(B28=3,Hypothèses!$C$26,Hypothèses!$D$26)))+(IF(B28=1,Hypothèses!$B$26,IF(B28=2,Hypothèses!$C$26,IF(B28=3,Hypothèses!$D$26,Hypothèses!$D$26)))-(IF(B28=1,0,IF(B28=2,Hypothèses!$B$26,IF(B28=3,Hypothèses!$C$26,Hypothèses!$D$26)))))*((A28)-INT((A28-1)/12)*12)/12)*$B$1 -> 10.833333 | H28: =(IF(B28=1,0,IF(B28=2,Hypothèses!$B$27,IF(B28=3,Hypothèses!$C$27,Hypothèses!$D$27)))+(IF(B28=1,Hypothèses!$B$27,IF(B28=2,Hypothèses!$C$27,IF(B28=3,Hypothèses!$D$27,Hypothèses!$D$27)))-(IF(B28=1,0,IF(B28=2,Hypothèses!$B$27,IF(B28=3,Hypothèses!$C$27,Hypothèses!$D$27)))))*((A28)-INT((A28-1)/12)*12)/12)*$B$1 -> 37.916667 | I28: =(IF(B28=1,0,IF(B28=2,Hypothèses!$B$28,IF(B28=3,Hypothèses!$C$28,Hypothèses!$D$28)))+(IF(B28=1,Hypothèses!$B$28,IF(B28=2,Hypothèses!$C$28,IF(B28=3,Hypothèses!$D$28,Hypothèses!$D$28)))-(IF(B28=1,0,IF(B28=2,Hypothèses!$B$28,IF(B28=3,Hypothèses!$C$28,Hypothèses!$D$28)))))*((A28)-INT((A28-1)/12)*12)/12)*$B$1 -> 1.1666667 | J28: =(IF(B28=1,0,IF(B28=2,Hypothèses!$B$29,IF(B28=3,Hypothèses!$C$29,Hypothèses!$D$29)))+(IF(B28=1,Hypothèses!$B$29,IF(B28=2,Hypothèses!$C$29,IF(B28=3,Hypothèses!$D$29,Hypothèses!$D$29)))-(IF(B28=1,0,IF(B28=2,Hypothèses!$B$29,IF(B28=3,Hypothèses!$C$29,Hypothèses!$D$29)))))*((A28)-INT((A28-1)/12)*12)/12)*$B$1 -> 1.0833333 | K28: =IF(A28<Hypothèses!$B$7,0,Hypothèses!$B$8*(1-Hypothèses!$B$9)^(A28-Hypothèses!$B$7)) -> 0.0092651009 | L28: =C28+D28+E28+F28 -> 48.4 | M28: =(C28*Hypothèses!$B$11+D28*Hypothèses!$B$12+E28*Hypothèses!$B$13+F28*Hypothèses!$B$14)*(IF(B28=1,Hypothèses!$B$20,IF(B28=2,Hypothèses!$B$21,Hypothèses!$B$22))+(1-(IF(B28=1,Hypothèses!$B$20,IF(B28=2,Hypothèses!$B$21,Hypothèses!$B$22))))*11/12) -> 7428.62 | N28: =L28*IF(B28=1,Hypothèses!$C$20,IF(B28=2,Hypothèses!$C$21,Hypothèses!$C$22))*IF(B28=1,Hypothèses!$D$20,IF(B28=2,Hypothèses!$D$21,Hypothèses!$D$22)) -> 174.24 | O28: =IF(A28=18,IF($B$2>=1,Hypothèses!$B$33,0),IF(AND(OR(A28=30,A28=34),$D$2>=1),Hypothèses!$B$34*MIN(1,$D$2/3),0)) -> 0 | P28: =M28+N28+O28 -> 7602.86 | Q28: =P28/(1+Hypothèses!$B$6) -> 6335.7167 | R28: =Hypothèses!$B$3*(1+Hypothèses!$B$4)^INT((A28-1)/3) -> 1529.5114 | S28: =IF($A28>=13,1,0) -> 1 | T28: =S28*Hypothèses!$B$17 -> 4500 | U28: =Q28*Hypothèses!$B$5 -> 63.357167 | V28: =Q28-R28-T28-U28 -> 242.84807 | W28: =W27+V28 -> -9258.8011
A29: 26 | B29: =INT((A29-1)/12)+1 -> 3 | C29: =ROUND(IF(MOD($A29,12)=0,G29,(IF(29=4,0,C28))*(1-$K29)+IF((IF(29=4,0,C28))*(1-$K29)<G29,(G29-(IF(29=4,0,C28))*(1-$K29))*Hypothèses!$B$10,0)),1) -> 10.8 | D29: =ROUND(IF(MOD($A29,12)=0,H29,(IF(29=4,0,D28))*(1-$K29)+IF((IF(29=4,0,D28))*(1-$K29)<H29,(H29-(IF(29=4,0,D28))*(1-$K29))*Hypothèses!$B$10,0)),1) -> 37.8 | E29: =ROUND(IF(MOD($A29,12)=0,I29,(IF(29=4,0,E28))*(1-$K29)+IF((IF(29=4,0,E28))*(1-$K29)<I29,(I29-(IF(29=4,0,E28))*(1-$K29))*Hypothèses!$B$10,0)),1) -> 1.2 | F29: =ROUND(IF(MOD($A29,12)=0,J29,(IF(29=4,0,F28))*(1-$K29)+IF((IF(29=4,0,F28))*(1-$K29)<J29,(J29-(IF(29=4,0,F28))*(1-$K29))*Hypothèses!$B$10,0)),1) -> 1.1 | G29: =(IF(B29=1,0,IF(B29=2,Hypothèses!$B$26,IF(B29=3,Hypothèses!$C$26,Hypothèses!$D$26)))+(IF(B29=1,Hypothèses!$B$26,IF(B29=2,Hypothèses!$C$26,IF(B29=3,Hypothèses!$D$26,Hypothèses!$D$26)))-(IF(B29=1,0,IF(B29=2,Hypothèses!$B$26,IF(B29=3,Hypothèses!$C$26,Hypothèses!$D$26)))))*((A29)-INT((A29-1)/12)*12)/12)*$B$1 -> 11.666667 | H29: =(IF(B29=1,0,IF(B29=2,Hypothèses!$B$27,IF(B29=3,Hypothèses!$C$27,Hypothèses!$D$27)))+(IF(B29=1,Hypothèses!$B$27,IF(B29=2,Hypothèses!$C$27,IF(B29=3,Hypothèses!$D$27,Hypothèses!$D$27)))-(IF(B29=1,0,IF(B29=2,Hypothèses!$B$27,IF(B29=3,Hypothèses!$C$27,Hypothèses!$D$27)))))*((A29)-INT((A29-1)/12)*12)/12)*$B$1 -> 40.833333 | I29: =(IF(B29=1,0,IF(B29=2,Hypothèses!$B$28,IF(B29=3,Hypothèses!$C$28,Hypothèses!$D$28)))+(IF(B29=1,Hypothèses!$B$28,IF(B29=2,Hypothèses!$C$28,IF(B29=3,Hypothèses!$D$28,Hypothèses!$D$28)))-(IF(B29=1,0,IF(B29=2,Hypothèses!$B$28,IF(B29=3,Hypothèses!$C$28,Hypothèses!$D$28)))))*((A29)-INT((A29-1)/12)*12)/12)*$B$1 -> 1.3333333 | J29: =(IF(B29=1,0,IF(B29=2,Hypothèses!$B$29,IF(B29=3,Hypothèses!$C$29,Hypothèses!$D$29)))+(IF(B29=1,Hypothèses!$B$29,IF(B29=2,Hypothèses!$C$29,IF(B29=3,Hypothèses!$D$29,Hypothèses!$D$29)))-(IF(B29=1,0,IF(B29=2,Hypothèses!$B$29,IF(B29=3,Hypothèses!$C$29,Hypothèses!$D$29)))))*((A29)-INT((A29-1)/12)*12)/12)*$B$1 -> 1.1666667 | K29: =IF(A29<Hypothèses!$B$7,0,Hypothèses!$B$8*(1-Hypothèses!$B$9)^(A29-Hypothèses!$B$7)) -> 0.0083385908 | L29: =C29+D29+E29+F29 -> 50.9 | M29: =(C29*Hypothèses!$B$11+D29*Hypothèses!$B$12+E29*Hypothèses!$B$13+F29*Hypothèses!$B$14)*(IF(B29=1,Hypothèses!$B$20,IF(B29=2,Hypothèses!$B$21,Hypothèses!$B$22))+(1-(IF(B29=1,Hypothèses!$B$20,IF(B29=2,Hypothèses!$B$21,Hypothèses!$B$22))))*11/12) -> 7867.14 | N29: =L29*IF(B29=1,Hypothèses!$C$20,IF(B29=2,Hypothèses!$C$21,Hypothèses!$C$22))*IF(B29=1,Hypothèses!$D$20,IF(B29=2,Hypothèses!$D$21,Hypothèses!$D$22)) -> 183.24 | O29: =IF(A29=18,IF($B$2>=1,Hypothèses!$B$33,0),IF(AND(OR(A29=30,A29=34),$D$2>=1),Hypothèses!$B$34*MIN(1,$D$2/3),0)) -> 0 | P29: =M29+N29+O29 -> 8050.38 | Q29: =P29/(1+Hypothèses!$B$6) -> 6708.65 | R29: =Hypothèses!$B$3*(1+Hypothèses!$B$4)^INT((A29-1)/3) -> 1529.5114 | S29: =IF($A29>=13,1,0) -> 1 | T29: =S29*Hypothèses!$B$17 -> 4500 | U29: =Q29*Hypothèses!$B$5 -> 67.0865 | V29: =Q29-R29-T29-U29 -> 612.05207 | W29: =W28+V29 -> -8646.749
A30: 27 | B30: =INT((A30-1)/12)+1 -> 3 | C30: =ROUND(IF(MOD($A30,12)=0,G30,(IF(30=4,0,C29))*(1-$K30)+IF((IF(30=4,0,C29))*(1-$K30)<G30,(G30-(IF(30=4,0,C29))*(1-$K30))*Hypothèses!$B$10,0)),1) -> 11.4 | D30: =ROUND(IF(MOD($A30,12)=0,H30,(IF(30=4,0,D29))*(1-$K30)+IF((IF(30=4,0,D29))*(1-$K30)<H30,(H30-(IF(30=4,0,D29))*(1-$K30))*Hypothèses!$B$10,0)),1) -> 40 | E30: =ROUND(IF(MOD($A30,12)=0,I30,(IF(30=4,0,E29))*(1-$K30)+IF((IF(30=4,0,E29))*(1-$K30)<I30,(I30-(IF(30=4,0,E29))*(1-$K30))*Hypothèses!$B$10,0)),1) -> 1.3 | F30: =ROUND(IF(MOD($A30,12)=0,J30,(IF(30=4,0,F29))*(1-$K30)+IF((IF(30=4,0,F29))*(1-$K30)<J30,(J30-(IF(30=4,0,F29))*(1-$K30))*Hypothèses!$B$10,0)),1) -> 1.2 | G30: =(IF(B30=1,0,IF(B30=2,Hypothèses!$B$26,IF(B30=3,Hypothèses!$C$26,Hypothèses!$D$26)))+(IF(B30=1,Hypothèses!$B$26,IF(B30=2,Hypothèses!$C$26,IF(B30=3,Hypothèses!$D$26,Hypothèses!$D$26)))-(IF(B30=1,0,IF(B30=2,Hypothèses!$B$26,IF(B30=3,Hypothèses!$C$26,Hypothèses!$D$26)))))*((A30)-INT((A30-1)/12)*12)/12)*$B$1 -> 12.5 | H30: =(IF(B30=1,0,IF(B30=2,Hypothèses!$B$27,IF(B30=3,Hypothèses!$C$27,Hypothèses!$D$27)))+(IF(B30=1,Hypothèses!$B$27,IF(B30=2,Hypothèses!$C$27,IF(B30=3,Hypothèses!$D$27,Hypothèses!$D$27)))-(IF(B30=1,0,IF(B30=2,Hypothèses!$B$27,IF(B30=3,Hypothèses!$C$27,Hypothèses!$D$27)))))*((A30)-INT((A30-1)/12)*12)/12)*$B$1 -> 43.75 | I30: =(IF(B30=1,0,IF(B30=2,Hypothèses!$B$28,IF(B30=3,Hypothèses!$C$28,Hypothèses!$D$28)))+(IF(B30=1,Hypothèses!$B$28,IF(B30=2,Hypothèses!$C$28,IF(B30=3,Hypothèses!$D$28,Hypothèses!$D$28)))-(IF(B30=1,0,IF(B30=2,Hypothèses!$B$28,IF(B30=3,Hypothèses!$C$28,Hypothèses!$D$28)))))*((A30)-INT((A30-1)/12)*12)/12)*$B$1 -> 1.5 | J30: =(IF(B30=1,0,IF(B30=2,Hypothèses!$B$29,IF(B30=3,Hypothèses!$C$29,Hypothèses!$D$29)))+(IF(B30=1,Hypothèses!$B$29,IF(B30=2,Hypothèses!$C$29,IF(B30=3,Hypothèses!$D$29,Hypothèses!$D$29)))-(IF(B30=1,0,IF(B30=2,Hypothèses!$B$29,IF(B30=3,Hypothèses!$C$29,Hypothèses!$D$29)))))*((A30)-INT((A30-1)/12)*12)/12)*$B$1 -> 1.25 | K30: =IF(A30<Hypothèses!$B$7,0,Hypothèses!$B$8*(1-Hypothèses!$B$9)^(A30-Hypothèses!$B$7)) -> 0.0075047318 | L30: =C30+D30+E30+F30 -> 53.9 | M30: =(C30*Hypothèses!$B$11+D30*Hypothèses!$B$12+E30*Hypothèses!$B$13+F30*Hypothèses!$B$14)*(IF(B30=1,Hypothèses!$B$20,IF(B30=2,Hypothèses!$B$21,Hypothèses!$B$22))+(1-(IF(B30=1,Hypothèses!$B$20,IF(B30=2,Hypothèses!$B$21,Hypothèses!$B$22))))*11/12) -> 8370.735 | N30: =L30*IF(B30=1,Hypothèses!$C$20,IF(B30=2,Hypothèses!$C$21,Hypothèses!$C$22))*IF(B30=1,Hypothèses!$D$20,IF(B30=2,Hypothèses!$D$21,Hypothèses!$D$22)) -> 194.04 | O30: =IF(A30=18,IF($B$2>=1,Hypothèses!$B$33,0),IF(AND(OR(A30=30,A30=34),$D$2>=1),Hypothèses!$B$34*MIN(1,$D$2/3),0)) -> 0 | P30: =M30+N30+O30 -> 8564.775 | Q30: =P30/(1+Hypothèses!$B$6) -> 7137.3125 | R30: =Hypothèses!$B$3*(1+Hypothèses!$B$4)^INT((A30-1)/3) -> 1529.5114 | S30: =IF($A30>=13,1,0) -> 1 | T30: =S30*Hypothèses!$B$17 -> 4500 | U30: =Q30*Hypothèses!$B$5 -> 71.373125 | V30: =Q30-R30-T30-U30 -> 1036.4279 | W30: =W29+V30 -> -7610.321
A31: 28 | B31: =INT((A31-1)/12)+1 -> 3 | C31: =ROUND(IF(MOD($A31,12)=0,G31,(IF(31=4,0,C30))*(1-$K31)+IF((IF(31=4,0,C30))*(1-$K31)<G31,(G31-(IF(31=4,0,C30))*(1-$K31))*Hypothèses!$B$10,0)),1) -> 12.1 | D31: =ROUND(IF(MOD($A31,12)=0,H31,(IF(31=4,0,D30))*(1-$K31)+IF((IF(31=4,0,D30))*(1-$K31)<H31,(H31-(IF(31=4,0,D30))*(1-$K31))*Hypothèses!$B$10,0)),1) -> 42.5 | E31: =ROUND(IF(MOD($A31,12)=0,I31,(IF(31=4,0,E30))*(1-$K31)+IF((IF(31=4,0,E30))*(1-$K31)<I31,(I31-(IF(31=4,0,E30))*(1-$K31))*Hypothèses!$B$10,0)),1) -> 1.4 | F31: =ROUND(IF(MOD($A31,12)=0,J31,(IF(31=4,0,F30))*(1-$K31)+IF((IF(31=4,0,F30))*(1-$K31)<J31,(J31-(IF(31=4,0,F30))*(1-$K31))*Hypothèses!$B$10,0)),1) -> 1.2 | G31: =(IF(B31=1,0,IF(B31=2,Hypothèses!$B$26,IF(B31=3,Hypothèses!$C$26,Hypothèses!$D$26)))+(IF(B31=1,Hypothèses!$B$26,IF(B31=2,Hypothèses!$C$26,IF(B31=3,Hypothèses!$D$26,Hypothèses!$D$26)))-(IF(B31=1,0,IF(B31=2,Hypothèses!$B$26,IF(B31=3,Hypothèses!$C$26,Hypothèses!$D$26)))))*((A31)-INT((A31-1)/12)*12)/12)*$B$1 -> 13.333333 | H31: =(IF(B31=1,0,IF(B31=2,Hypothèses!$B$27,IF(B31=3,Hypothèses!$C$27,Hypothèses!$D$27)))+(IF(B31=1,Hypothèses!$B$27,IF(B31=2,Hypothèses!$C$27,IF(B31=3,Hypothèses!$D$27,Hypothèses!$D$27)))-(IF(B31=1,0,IF(B31=2,Hypothèses!$B$27,IF(B31=3,Hypothèses!$C$27,Hypothèses!$D$27)))))*((A31)-INT((A31-1)/12)*12)/12)*$B$1 -> 46.666667 | I31: =(IF(B31=1,0,IF(B31=2,Hypothèses!$B$28,IF(B31=3,Hypothèses!$C$28,Hypothèses!$D$28)))+(IF(B31=1,Hypothèses!$B$28,IF(B31=2,Hypothèses!$C$28,IF(B31=3,Hypothèses!$D$28,Hypothèses!$D$28)))-(IF(B31=1,0,IF(B31=2,Hypothèses!$B$28,IF(B31=3,Hypothèses!$C$28,Hypothèses!$D$28)))))*((A31)-INT((A31-1)/12)*12)/12)*$B$1 -> 1.6666667 | J31: =(IF(B31=1,0,IF(B31=2,Hypothèses!$B$29,IF(B31=3,Hypothèses!$C$29,Hypothèses!$D$29)))+(IF(B31=1,Hypothèses!$B$29,IF(B31=2,Hypothèses!$C$29,IF(B31=3,Hypothèses!$D$29,Hypothèses!$D$29)))-(IF(B31=1,0,IF(B31=2,Hypothèses!$B$29,IF(B31=3,Hypothèses!$C$29,Hypothèses!$D$29)))))*((A31)-INT((A31-1)/12)*12)/12)*$B$1 -> 1.3333333 | K31: =IF(A31<Hypothèses!$B$7,0,Hypothèses!$B$8*(1-Hypothèses!$B$9)^(A31-Hypothèses!$B$7)) -> 0.0067542586 | L31: =C31+D31+E31+F31 -> 57.2 | M31: =(C31*Hypothèses!$B$11+D31*Hypothèses!$B$12+E31*Hypothèses!$B$13+F31*Hypothèses!$B$14)*(IF(B31=1,Hypothèses!$B$20,IF(B31=2,Hypothèses!$B$21,Hypothèses!$B$22))+(1-(IF(B31=1,Hypothèses!$B$20,IF(B31=2,Hypothèses!$B$21,Hypothèses!$B$22))))*11/12) -> 8831.2 | N31: =L31*IF(B31=1,Hypothèses!$C$20,IF(B31=2,Hypothèses!$C$21,Hypothèses!$C$22))*IF(B31=1,Hypothèses!$D$20,IF(B31=2,Hypothèses!$D$21,Hypothèses!$D$22)) -> 205.92 | O31: =IF(A31=18,IF($B$2>=1,Hypothèses!$B$33,0),IF(AND(OR(A31=30,A31=34),$D$2>=1),Hypothèses!$B$34*MIN(1,$D$2/3),0)) -> 0 | P31: =M31+N31+O31 -> 9037.12 | Q31: =P31/(1+Hypothèses!$B$6) -> 7530.9333 | R31: =Hypothèses!$B$3*(1+Hypothèses!$B$4)^INT((A31-1)/3) -> 1758.9381 | S31: =IF($A31>=13,1,0) -> 1 | T31: =S31*Hypothèses!$B$17 -> 4500 | U31: =Q31*Hypothèses!$B$5 -> 75.309333 | V31: =Q31-R31-T31-U31 -> 1196.6859 | W31: =W30+V31 -> -6413.6352
A32: 29 | B32: =INT((A32-1)/12)+1 -> 3 | C32: =ROUND(IF(MOD($A32,12)=0,G32,(IF(32=4,0,C31))*(1-$K32)+IF((IF(32=4,0,C31))*(1-$K32)<G32,(G32-(IF(32=4,0,C31))*(1-$K32))*Hypothèses!$B$10,0)),1) -> 12.9 | D32: =ROUND(IF(MOD($A32,12)=0,H32,(IF(32=4,0,D31))*(1-$K32)+IF((IF(32=4,0,D31))*(1-$K32)<H32,(H32-(IF(32=4,0,D31))*(1-$K32))*Hypothèses!$B$10,0)),1) -> 45.2 | E32: =ROUND(IF(MOD($A32,12)=0,I32,(IF(32=4,0,E31))*(1-$K32)+IF((IF(32=4,0,E31))*(1-$K32)<I32,(I32-(IF(32=4,0,E31))*(1-$K32))*Hypothèses!$B$10,0)),1) -> 1.6 | F32: =ROUND(IF(MOD($A32,12)=0,J32,(IF(32=4,0,F31))*(1-$K32)+IF((IF(32=4,0,F31))*(1-$K32)<J32,(J32-(IF(32=4,0,F31))*(1-$K32))*Hypothèses!$B$10,0)),1) -> 1.3 | G32: =(IF(B32=1,0,IF(B32=2,Hypothèses!$B$26,IF(B32=3,Hypothèses!$C$26,Hypothèses!$D$26)))+(IF(B32=1,Hypothèses!$B$26,IF(B32=2,Hypothèses!$C$26,IF(B32=3,Hypothèses!$D$26,Hypothèses!$D$26)))-(IF(B32=1,0,IF(B32=2,Hypothèses!$B$26,IF(B32=3,Hypothèses!$C$26,Hypothèses!$D$26)))))*((A32)-INT((A32-1)/12)*12)/12)*$B$1 -> 14.166667 | H32: =(IF(B32=1,0,IF(B32=2,Hypothèses!$B$27,IF(B32=3,Hypothèses!$C$27,Hypothèses!$D$27)))+(IF(B32=1,Hypothèses!$B$27,IF(B32=2,Hypothèses!$C$27,IF(B32=3,Hypothèses!$D$27,Hypothèses!$D$27)))-(IF(B32=1,0,IF(B32=2,Hypothèses!$B$27,IF(B32=3,Hypothèses!$C$27,Hypothèses!$D$27)))))*((A32)-INT((A32-1)/12)*12)/12)*$B$1 -> 49.583333 | I32: =(IF(B32=1,0,IF(B32=2,Hypothèses!$B$28,IF(B32=3,Hypothèses!$C$28,Hypothèses!$D$28)))+(IF(B32=1,Hypothèses!$B$28,IF(B32=2,Hypothèses!$C$28,IF(B32=3,Hypothèses!$D$28,Hypothèses!$D$28)))-(IF(B32=1,0,IF(B32=2,Hypothèses!$B$28,IF(B32=3,Hypothèses!$C$28,Hypothèses!$D$28)))))*((A32)-INT((A32-1)/12)*12)/12)*$B$1 -> 1.8333333 | J32: =(IF(B32=1,0,IF(B32=2,Hypothèses!$B$29,IF(B32=3,Hypothèses!$C$29,Hypothèses!$D$29)))+(IF(B32=1,Hypothèses!$B$29,IF(B32=2,Hypothèses!$C$29,IF(B32=3,Hypothèses!$D$29,Hypothèses!$D$29)))-(IF(B32=1,0,IF(B32=2,Hypothèses!$B$29,IF(B32=3,Hypothèses!$C$29,Hypothèses!$D$29)))))*((A32)-INT((A32-1)/12)*12)/12)*$B$1 -> 1.4166667 | K32: =IF(A32<Hypothèses!$B$7,0,Hypothèses!$B$8*(1-Hypothèses!$B$9)^(A32-Hypothèses!$B$7)) -> 0.0060788327 | L32: =C32+D32+E32+F32 -> 61 | M32: =(C32*Hypothèses!$B$11+D32*Hypothèses!$B$12+E32*Hypothèses!$B$13+F32*Hypothèses!$B$14)*(IF(B32=1,Hypothèses!$B$20,IF(B32=2,Hypothèses!$B$21,Hypothèses!$B$22))+(1-(IF(B32=1,Hypothèses!$B$20,IF(B32=2,Hypothèses!$B$21,Hypothèses!$B$22))))*11/12) -> 9469.885 | N32: =L32*IF(B32=1,Hypothèses!$C$20,IF(B32=2,Hypothèses!$C$21,Hypothèses!$C$22))*IF(B32=1,Hypothèses!$D$20,IF(B32=2,Hypothèses!$D$21,Hypothèses!$D$22)) -> 219.6 | O32: =IF(A32=18,IF($B$2>=1,Hypothèses!$B$33,0),IF(AND(OR(A32=30,A32=34),$D$2>=1),Hypothèses!$B$34*MIN(1,$D$2/3),0)) -> 0 | P32: =M32+N32+O32 -> 9689.485 | Q32: =P32/(1+Hypothèses!$B$6) -> 8074.5708 | R32: =Hypothèses!$B$3*(1+Hypothèses!$B$4)^INT((A32-1)/3) -> 1758.9381 | S32: =IF($A32>=13,1,0) -> 1 | T32: =S32*Hypothèses!$B$17 -> 4500 | U32: =Q32*Hypothèses!$B$5 -> 80.745708 | V32: =Q32-R32-T32-U32 -> 1734.887 | W32: =W31+V32 -> -4678.7482
A33: 30 | B33: =INT((A33-1)/12)+1 -> 3 | C33: =ROUND(IF(MOD($A33,12)=0,G33,(IF(33=4,0,C32))*(1-$K33)+IF((IF(33=4,0,C32))*(1-$K33)<G33,(G33-(IF(33=4,0,C32))*(1-$K33))*Hypothèses!$B$10,0)),1) -> 13.7 | D33: =ROUND(IF(MOD($A33,12)=0,H33,(IF(33=4,0,D32))*(1-$K33)+IF((IF(33=4,0,D32))*(1-$K33)<H33,(H33-(IF(33=4,0,D32))*(1-$K33))*Hypothèses!$B$10,0)),1) -> 48 | E33: =ROUND(IF(MOD($A33,12)=0,I33,(IF(33=4,0,E32))*(1-$K33)+IF((IF(33=4,0,E32))*(1-$K33)<I33,(I33-(IF(33=4,0,E32))*(1-$K33))*Hypothèses!$B$10,0)),1) -> 1.8 | F33: =ROUND(IF(MOD($A33,12)=0,J33,(IF(33=4,0,F32))*(1-$K33)+IF((IF(33=4,0,F32))*(1-$K33)<J33,(J33-(IF(33=4,0,F32))*(1-$K33))*Hypothèses!$B$10,0)),1) -> 1.4 | G33: =(IF(B33=1,0,IF(B33=2,Hypothèses!$B$26,IF(B33=3,Hypothèses!$C$26,Hypothèses!$D$26)))+(IF(B33=1,Hypothèses!$B$26,IF(B33=2,Hypothèses!$C$26,IF(B33=3,Hypothèses!$D$26,Hypothèses!$D$26)))-(IF(B33=1,0,IF(B33=2,Hypothèses!$B$26,IF(B33=3,Hypothèses!$C$26,Hypothèses!$D$26)))))*((A33)-INT((A33-1)/12)*12)/12)*$B$1 -> 15 | H33: =(IF(B33=1,0,IF(B33=2,Hypothèses!$B$27,IF(B33=3,Hypothèses!$C$27,Hypothèses!$D$27)))+(IF(B33=1,Hypothèses!$B$27,IF(B33=2,Hypothèses!$C$27,IF(B33=3,Hypothèses!$D$27,Hypothèses!$D$27)))-(IF(B33=1,0,IF(B33=2,Hypothèses!$B$27,IF(B33=3,Hypothèses!$C$27,Hypothèses!$D$27)))))*((A33)-INT((A33-1)/12)*12)/12)*$B$1 -> 52.5 | I33: =(IF(B33=1,0,IF(B33=2,Hypothèses!$B$28,IF(B33=3,Hypothèses!$C$28,Hypothèses!$D$28)))+(IF(B33=1,Hypothèses!$B$28,IF(B33=2,Hypothèses!$C$28,IF(B33=3,Hypothèses!$D$28,Hypothèses!$D$28)))-(IF(B33=1,0,IF(B33=2,Hypothèses!$B$28,IF(B33=3,Hypothèses!$C$28,Hypothèses!$D$28)))))*((A33)-INT((A33-1)/12)*12)/12)*$B$1 -> 2 | J33: =(IF(B33=1,0,IF(B33=2,Hypothèses!$B$29,IF(B33=3,Hypothèses!$C$29,Hypothèses!$D$29)))+(IF(B33=1,Hypothèses!$B$29,IF(B33=2,Hypothèses!$C$29,IF(B33=3,Hypothèses!$D$29,Hypothèses!$D$29)))-(IF(B33=1,0,IF(B33=2,Hypothèses!$B$29,IF(B33=3,Hypothèses!$C$29,Hypothèses!$D$29)))))*((A33)-INT((A33-1)/12)*12)/12)*$B$1 -> 1.5 | K33: =IF(A33<Hypothèses!$B$7,0,Hypothèses!$B$8*(1-Hypothèses!$B$9)^(A33-Hypothèses!$B$7)) -> 0.0054709495 | L33: =C33+D33+E33+F33 -> 64.9 | M33: =(C33*Hypothèses!$B$11+D33*Hypothèses!$B$12+E33*Hypothèses!$B$13+F33*Hypothèses!$B$14)*(IF(B33=1,Hypothèses!$B$20,IF(B33=2,Hypothèses!$B$21,Hypothèses!$B$22))+(1-(IF(B33=1,Hypothèses!$B$20,IF(B33=2,Hypothèses!$B$21,Hypothèses!$B$22))))*11/12) -> 10122.725 | N33: =L33*IF(B33=1,Hypothèses!$C$20,IF(B33=2,Hypothèses!$C$21,Hypothèses!$C$22))*IF(B33=1,Hypothèses!$D$20,IF(B33=2,Hypothèses!$D$21,Hypothèses!$D$22)) -> 233.64 | O33: =IF(A33=18,IF($B$2>=1,Hypothèses!$B$33,0),IF(AND(OR(A33=30,A33=34),$D$2>=1),Hypothèses!$B$34*MIN(1,$D$2/3),0)) -> 17000 | P33: =M33+N33+O33 -> 27356.365 | Q33: =P33/(1+Hypothèses!$B$6) -> 22796.971 | R33: =Hypothèses!$B$3*(1+Hypothèses!$B$4)^INT((A33-1)/3) -> 1758.9381 | S33: =IF($A33>=13,1,0) -> 1 | T33: =S33*Hypothèses!$B$17 -> 4500 | U33: =Q33*Hypothèses!$B$5 -> 227.96971 | V33: =Q33-R33-T33-U33 -> 16310.063 | W33: =W32+V33 -> 11631.315
A34: 31 | B34: =INT((A34-1)/12)+1 -> 3 | C34: =ROUND(IF(MOD($A34,12)=0,G34,(IF(34=4,0,C33))*(1-$K34)+IF((IF(34=4,0,C33))*(1-$K34)<G34,(G34-(IF(34=4,0,C33))*(1-$K34))*Hypothèses!$B$10,0)),1) -> 14.5 | D34: =ROUND(IF(MOD($A34,12)=0,H34,(IF(34=4,0,D33))*(1-$K34)+IF((IF(34=4,0,D33))*(1-$K34)<H34,(H34-(IF(34=4,0,D33))*(1-$K34))*Hypothèses!$B$10,0)),1) -> 50.8 | E34: =ROUND(IF(MOD($A34,12)=0,I34,(IF(34=4,0,E33))*(1-$K34)+IF((IF(34=4,0,E33))*(1-$K34)<I34,(I34-(IF(34=4,0,E33))*(1-$K34))*Hypothèses!$B$10,0)),1) -> 1.9 | F34: =ROUND(IF(MOD($A34,12)=0,J34,(IF(34=4,0,F33))*(1-$K34)+IF((IF(34=4,0,F33))*(1-$K34)<J34,(J34-(IF(34=4,0,F33))*(1-$K34))*Hypothèses!$B$10,0)),1) -> 1.5 | G34: =(IF(B34=1,0,IF(B34=2,Hypothèses!$B$26,IF(B34=3,Hypothèses!$C$26,Hypothèses!$D$26)))+(IF(B34=1,Hypothèses!$B$26,IF(B34=2,Hypothèses!$C$26,IF(B34=3,Hypothèses!$D$26,Hypothèses!$D$26)))-(IF(B34=1,0,IF(B34=2,Hypothèses!$B$26,IF(B34=3,Hypothèses!$C$26,Hypothèses!$D$26)))))*((A34)-INT((A34-1)/12)*12)/12)*$B$1 -> 15.833333 | H34: =(IF(B34=1,0,IF(B34=2,Hypothèses!$B$27,IF(B34=3,Hypothèses!$C$27,Hypothèses!$D$27)))+(IF(B34=1,Hypothèses!$B$27,IF(B34=2,Hypothèses!$C$27,IF(B34=3,Hypothèses!$D$27,Hypothèses!$D$27)))-(IF(B34=1,0,IF(B34=2,Hypothèses!$B$27,IF(B34=3,Hypothèses!$C$27,Hypothèses!$D$27)))))*((A34)-INT((A34-1)/12)*12)/12)*$B$1 -> 55.416667 | I34: =(IF(B34=1,0,IF(B34=2,Hypothèses!$B$28,IF(B34=3,Hypothèses!$C$28,Hypothèses!$D$28)))+(IF(B34=1,Hypothèses!$B$28,IF(B34=2,Hypothèses!$C$28,IF(B34=3,Hypothèses!$D$28,Hypothèses!$D$28)))-(IF(B34=1,0,IF(B34=2,Hypothèses!$B$28,IF(B34=3,Hypothèses!$C$28,Hypothèses!$D$28)))))*((A34)-INT((A34-1)/12)*12)/12)*$B$1 -> 2.1666667 | J34: =(IF(B34=1,0,IF(B34=2,Hypothèses!$B$29,IF(B34=3,Hypothèses!$C$29,Hypothèses!$D$29)))+(IF(B34=1,Hypothèses!$B$29,IF(B34=2,Hypothèses!$C$29,IF(B34=3,Hypothèses!$D$29,Hypothèses!$D$29)))-(IF(B34=1,0,IF(B34=2,Hypothèses!$B$29,IF(B34=3,Hypothèses!$C$29,Hypothèses!$D$29)))))*((A34)-INT((A34-1)/12)*12)/12)*$B$1 -> 1.5833333 | K34: =IF(A34<Hypothèses!$B$7,0,Hypothèses!$B$8*(1-Hypothèses!$B$9)^(A34-Hypothèses!$B$7)) -> 0.0049238545 | L34: =C34+D34+E34+F34 -> 68.7 | M34: =(C34*Hypothèses!$B$11+D34*Hypothèses!$B$12+E34*Hypothèses!$B$13+F34*Hypothèses!$B$14)*(IF(B34=1,Hypothèses!$B$20,IF(B34=2,Hypothèses!$B$21,Hypothèses!$B$22))+(1-(IF(B34=1,Hypothèses!$B$20,IF(B34=2,Hypothèses!$B$21,Hypothèses!$B$22))))*11/12) -> 10728.16 | N34: =L34*IF(B34=1,Hypothèses!$C$20,IF(B34=2,Hypothèses!$C$21,Hypothèses!$C$22))*IF(B34=1,Hypothèses!$D$20,IF(B34=2,Hypothèses!$D$21,Hypothèses!$D$22)) -> 247.32 | O34: =IF(A34=18,IF($B$2>=1,Hypothèses!$B$33,0),IF(AND(OR(A34=30,A34=34),$D$2>=1),Hypothèses!$B$34*MIN(1,$D$2/3),0)) -> 0 | P34: =M34+N34+O34 -> 10975.48 | Q34: =P34/(1+Hypothèses!$B$6) -> 9146.2333 | R34: =Hypothèses!$B$3*(1+Hypothèses!$B$4)^INT((A34-1)/3) -> 2022.7789 | S34: =IF($A34>=13,1,0) -> 1 | T34: =S34*Hypothèses!$B$17 -> 4500 | U34: =Q34*Hypothèses!$B$5 -> 91.462333 | V34: =Q34-R34-T34-U34 -> 2531.9921 | W34: =W33+V34 -> 14163.307
